Workbook

Sheet 📊 Dashboard Ejecutivo
B1: 📊 DASHBOARD EJECUTIVO DE RENTABILIDAD INDUSTRIAL (CBC)
B2: Panel de Control para Toma de Decisiones | Actualizado: 18/06/2026
B5: 🔧 CONTROLES DE FILTRO
B6: Mes Selector: | C6: TODOS | D6: ⬇️ Usa las listas desplegables | E6: Turno Selector: | F6: TODOS
B8: 💰 INDICADORES CLAVE DE RENTABILIDAD
B9: 💵 INGRESOS TOTALES | C9: 💸 COSTO TOTAL OPERATIVO | D9: 💰 UTILIDAD PRODUCIDA | E9: 📈 MARGEN PRODUCCIÓN % | F9: 💎 UTILIDAD NETA | G9: 📊 MARGEN NETO %
B10: =SUMIFS('📅 Resumen Diario'!$J$5:$J$504,'📅 Resumen Diario'!$O$5:$O$504,IF($C$6="TODOS","*",$C$6),'📅 Resumen Diario'!$C$5:$C$504,IF($F$6="TODOS","*",$F$6)) -> 647038.09 | C10: =SUMIFS('📅 Resumen Diario'!$P$5:$P$504,'📅 Resumen Diario'!$O$5:$O$504,IF($C$6="TODOS","*",$C$6),'📅 Resumen Diario'!$C$5:$C$504,IF($F$6="TODOS","*",$F$6)) -> 435903.18 | D10: =SUMIFS('📅 Resumen Diario'!$L$5:$L$504,'📅 Resumen Diario'!$O$5:$O$504,IF($C$6="TODOS","*",$C$6),'📅 Resumen Diario'!$C$5:$C$504,IF($F$6="TODOS","*",$F$6)) -> 228707.86 | E10: =IF(B10=0,0,D10/B10) -> 0.35346893 | F10: =D10+D12+E12 -> 241127.86 | G10: =IF(B10=0,0,F10/B10) -> 0.37266409
B11: 📦 UNIDADES PRODUCIDAS | C11: 🏷️ ETIQUETAS PROCESADAS | D11: 🔄 REPOSICIÓN PALETIZANTE | E11: ⏰ INGRESOS H.EXTRAS
B12: =SUMIFS('📅 Resumen Diario'!$D$5:$D$504,'📅 Resumen Diario'!$O$5:$O$504,IF($C$6="TODOS","*",$C$6),'📅 Resumen Diario'!$C$5:$C$504,IF($F$6="TODOS","*",$F$6)) -> 53232.3 | C12: =SUMIFS('📅 Resumen Diario'!$G$5:$G$504,'📅 Resumen Diario'!$O$5:$O$504,IF($C$6="TODOS","*",$C$6),'📅 Resumen Diario'!$C$5:$C$504,IF($F$6="TODOS","*",$F$6)) -> 195255 | D12: =SUMIFS('📋 Detalle Diario'!$I$5:$I$489,'📋 Detalle Diario'!$H$5:$H$489,IF($C$6="TODOS","*",$C$6),'📋 Detalle Diario'!$C$5:$C$489,IF($F$6="TODOS","*",$F$6))*200 -> 0 | E12: =SUMIFS('📋 Detalle Diario'!$E$5:$E$489,'📋 Detalle Diario'!$H$5:$H$489,IF($C$6="TODOS","*",$C$6),'📋 Detalle Diario'!$C$5:$C$489,IF($F$6="TODOS","*",$F$6))*135 -> 12420
B14: 📢 DETECCIONES AUTOMÁTICAS DEL MIX (PARA EL PERÍODO SELECCIONADO)
B15: 🏆 Producto con Mayor Volumen | D15: 📉 Producto con Menor Volumen | F15: ⚠️ Producto con Menor Margen
B16: =IFERROR(INDEX(B20:B69, MATCH(MAX(C20:C69), C20:C69, 0)), "N/A") -> 2 Pack Pepsi + Roja 3 Litro | D16: =IFERROR(INDEX(B20:B69, MATCH(SMALL(C20:C69, COUNTIF(C20:C69, 0) + 1), C20:C69, 0)), "N/A") -> TRASIEGO MANTICA | F16: =IFERROR(INDEX(B20:B69, MATCH(MIN(F20:F69), F20:F69, 0)), "N/A") -> 18 Pack Pepsi + Roja 500 ML
B18: 📋 DETALLE DE DESEMPEÑO POR PRODUCTO Y MARGEN NETO
B19: Producto | C19: Unidades Producidas (Packs) | D19: Ingreso Total (C$) | E19: Costo Total Asignado (C$) | F19: Utilidad Neta Real (C$) | G19: Margen Neto %
B20: =IFERROR(INDEX('📦 Precios Proforma'!$B$5:$B$104, 1), "") -> 12 pack 12 oz pepsi +sabores | C20: =IF(B20="","",SUMIFS('📈 Datos Completos'!$E$7:$E$5000, '📈 Datos Completos'!$C$7:$C$5000, B20, '📈 Datos Completos'!$Q$7:$Q$5000, IF($C$6="TODOS","*",$C$6), '📈 Datos Completos'!$D$7:$D$5000, IF($F$6="TODOS","*",$F$6))) -> 252 | D20: =IF(B20="","",SUMIFS('📈 Datos Completos'!$K$7:$K$5000, '📈 Datos Completos'!$C$7:$C$5000, B20, '📈 Datos Completos'!$Q$7:$Q$5000, IF($C$6="TODOS","*",$C$6), '📈 Datos Completos'!$D$7:$D$5000, IF($F$6="TODOS","*",$F$6))) -> 1348.2 | E20: =IF(B20="","",SUMIFS('📈 Datos Completos'!$N$7:$N$5000, '📈 Datos Completos'!$C$7:$C$5000, B20, '📈 Datos Completos'!$Q$7:$Q$5000, IF($C$6="TODOS","*",$C$6), '📈 Datos Completos'!$D$7:$D$5000, IF($F$6="TODOS","*",$F$6))) -> 1348.8084 | F20: =IF(B20="","",SUMIFS('📈 Datos Completos'!$O$7:$O$5000, '📈 Datos Completos'!$C$7:$C$5000, B20, '📈 Datos Completos'!$Q$7:$Q$5000, IF($C$6="TODOS","*",$C$6), '📈 Datos Completos'!$D$7:$D$5000, IF($F$6="TODOS","*",$F$6))) -> -0.60839975 | G20: =IF(B20="","",IF(D20=0,0,F20/D20)) -> -0.00045126817
B21: =IFERROR(INDEX('📦 Precios Proforma'!$B$5:$B$104, 2), "") -> 12 Pack Adrenalina Rush 16 Onz | C21: =IF(B21="","",SUMIFS('📈 Datos Completos'!$E$7:$E$5000, '📈 Datos Completos'!$C$7:$C$5000, B21, '📈 Datos Completos'!$Q$7:$Q$5000, IF($C$6="TODOS","*",$C$6), '📈 Datos Completos'!$D$7:$D$5000, IF($F$6="TODOS","*",$F$6))) -> 0 | D21: =IF(B21="","",SUMIFS('📈 Datos Completos'!$K$7:$K$5000, '📈 Datos Completos'!$C$7:$C$5000, B21, '📈 Datos Completos'!$Q$7:$Q$5000, IF($C$6="TODOS","*",$C$6), '📈 Datos Completos'!$D$7:$D$5000, IF($F$6="TODOS","*",$F$6))) -> 0 | E21: =IF(B21="","",SUMIFS('📈 Datos Completos'!$N$7:$N$5000, '📈 Datos Completos'!$C$7:$C$5000, B21, '📈 Datos Completos'!$Q$7:$Q$5000, IF($C$6="TODOS","*",$C$6), '📈 Datos Completos'!$D$7:$D$5000, IF($F$6="TODOS","*",$F$6))) -> 0 | F21: =IF(B21="","",SUMIFS('📈 Datos Completos'!$O$7:$O$5000, '📈 Datos Completos'!$C$7:$C$5000, B21, '📈 Datos Completos'!$Q$7:$Q$5000, IF($C$6="TODOS","*",$C$6), '📈 Datos Completos'!$D$7:$D$5000, IF($F$6="TODOS","*",$F$6))) -> 0 | G21: =IF(B21="","",IF(D21=0,0,F21/D21)) -> 0
B22: =IFERROR(INDEX('📦 Precios Proforma'!$B$5:$B$104, 3), "") -> 12 PACK AMP 600 ML | C22: =IF(B22="","",SUMIFS('📈 Datos Completos'!$E$7:$E$5000, '📈 Datos Completos'!$C$7:$C$5000, B22, '📈 Datos Completos'!$Q$7:$Q$5000, IF($C$6="TODOS","*",$C$6), '📈 Datos Completos'!$D$7:$D$5000, IF($F$6="TODOS","*",$F$6))) -> 974 | D22: =IF(B22="","",SUMIFS('📈 Datos Completos'!$K$7:$K$5000, '📈 Datos Completos'!$C$7:$C$5000, B22, '📈 Datos Completos'!$Q$7:$Q$5000, IF($C$6="TODOS","*",$C$6), '📈 Datos Completos'!$D$7:$D$5000, IF($F$6="TODOS","*",$F$6))) -> 19113.1 | E22: =IF(B22="","",SUMIFS('📈 Datos Completos'!$N$7:$N$5000, '📈 Datos Completos'!$C$7:$C$5000, B22, '📈 Datos Completos'!$Q$7:$Q$5000, IF($C$6="TODOS","*",$C$6), '📈 Datos Completos'!$D$7:$D$5000, IF($F$6="TODOS","*",$F$6))) -> 12177.374 | F22: =IF(B22="","",SUMIFS('📈 Datos Completos'!$O$7:$O$5000, '📈 Datos Completos'!$C$7:$C$5000, B22, '📈 Datos Completos'!$Q$7:$Q$5000, IF($C$6="TODOS","*",$C$6), '📈 Datos Completos'!$D$7:$D$5000, IF($F$6="TODOS","*",$F$6))) -> 6935.7255 | G22: =IF(B22="","",IF(D22=0,0,F22/D22)) -> 0.36287811
B23: =IFERROR(INDEX('📦 Precios Proforma'!$B$5:$B$104, 4), "") -> 12 Pack California Surtido 400 ML | C23: =IF(B23="","",SUMIFS('📈 Datos Completos'!$E$7:$E$5000, '📈 Datos Completos'!$C$7:$C$5000, B23, '📈 Datos Completos'!$Q$7:$Q$5000, IF($C$6="TODOS","*",$C$6), '📈 Datos Completos'!$D$7:$D$5000, IF($F$6="TODOS","*",$F$6))) -> 1192 | D23: =IF(B23="","",SUMIFS('📈 Datos Completos'!$K$7:$K$5000, '📈 Datos Completos'!$C$7:$C$5000, B23, '📈 Datos Completos'!$Q$7:$Q$5000, IF($C$6="TODOS","*",$C$6), '📈 Datos Completos'!$D$7:$D$5000, IF($F$6="TODOS","*",$F$6))) -> 7672.2 | E23: =IF(B23="","",SUMIFS('📈 Datos Completos'!$N$7:$N$5000, '📈 Datos Completos'!$C$7:$C$5000, B23, '📈 Datos Completos'!$Q$7:$Q$5000, IF($C$6="TODOS","*",$C$6), '📈 Datos Completos'!$D$7:$D$5000, IF($F$6="TODOS","*",$F$6))) -> 9839.4712 | F23: =IF(B23="","",SUMIFS('📈 Datos Completos'!$O$7:$O$5000, '📈 Datos Completos'!$C$7:$C$5000, B23, '📈 Datos Completos'!$Q$7:$Q$5000, IF($C$6="TODOS","*",$C$6), '📈 Datos Completos'!$D$7:$D$5000, IF($F$6="TODOS","*",$F$6))) -> -2167.2712 | G23: =IF(B23="","",IF(D23=0,0,F23/D23)) -> -0.28248367
B24: =IFERROR(INDEX('📦 Precios Proforma'!$B$5:$B$104, 5), "") -> 12 Pack CSD 500 ML PET | C24: =IF(B24="","",SUMIFS('📈 Datos Completos'!$E$7:$E$5000, '📈 Datos Completos'!$C$7:$C$5000, B24, '📈 Datos Completos'!$Q$7:$Q$5000, IF($C$6="TODOS","*",$C$6), '📈 Datos Completos'!$D$7:$D$5000, IF($F$6="TODOS","*",$F$6))) -> 0 | D24: =IF(B24="","",SUMIFS('📈 Datos Completos'!$K$7:$K$5000, '📈 Datos Completos'!$C$7:$C$5000, B24, '📈 Datos Completos'!$Q$7:$Q$5000, IF($C$6="TODOS","*",$C$6), '📈 Datos Completos'!$D$7:$D$5000, IF($F$6="TODOS","*",$F$6))) -> 0 | E24: =IF(B24="","",SUMIFS('📈 Datos Completos'!$N$7:$N$5000, '📈 Datos Completos'!$C$7:$C$5000, B24, '📈 Datos Completos'!$Q$7:$Q$5000, IF($C$6="TODOS","*",$C$6), '📈 Datos Completos'!$D$7:$D$5000, IF($F$6="TODOS","*",$F$6))) -> 0 | F24: =IF(B24="","",SUMIFS('📈 Datos Completos'!$O$7:$O$5000, '📈 Datos Completos'!$C$7:$C$5000, B24, '📈 Datos Completos'!$Q$7:$Q$5000, IF($C$6="TODOS","*",$C$6), '📈 Datos Completos'!$D$7:$D$5000, IF($F$6="TODOS","*",$F$6))) -> 0 | G24: =IF(B24="","",IF(D24=0,0,F24/D24)) -> 0
B25: =IFERROR(INDEX('📦 Precios Proforma'!$B$5:$B$104, 6), "") -> 12 Pack Ensa Soda 500ml Pet | C25: =IF(B25="","",SUMIFS('📈 Datos Completos'!$E$7:$E$5000, '📈 Datos Completos'!$C$7:$C$5000, B25, '📈 Datos Completos'!$Q$7:$Q$5000, IF($C$6="TODOS","*",$C$6), '📈 Datos Completos'!$D$7:$D$5000, IF($F$6="TODOS","*",$F$6))) -> 438 | D25: =IF(B25="","",SUMIFS('📈 Datos Completos'!$K$7:$K$5000, '📈 Datos Completos'!$C$7:$C$5000, B25, '📈 Datos Completos'!$Q$7:$Q$5000, IF($C$6="TODOS","*",$C$6), '📈 Datos Completos'!$D$7:$D$5000, IF($F$6="TODOS","*",$F$6))) -> 10328.04 | E25: =IF(B25="","",SUMIFS('📈 Datos Completos'!$N$7:$N$5000, '📈 Datos Completos'!$C$7:$C$5000, B25, '📈 Datos Completos'!$Q$7:$Q$5000, IF($C$6="TODOS","*",$C$6), '📈 Datos Completos'!$D$7:$D$5000, IF($F$6="TODOS","*",$F$6))) -> 6194.2709 | F25: =IF(B25="","",SUMIFS('📈 Datos Completos'!$O$7:$O$5000, '📈 Datos Completos'!$C$7:$C$5000, B25, '📈 Datos Completos'!$Q$7:$Q$5000, IF($C$6="TODOS","*",$C$6), '📈 Datos Completos'!$D$7:$D$5000, IF($F$6="TODOS","*",$F$6))) -> 4133.7691 | G25: =IF(B25="","",IF(D25=0,0,F25/D25)) -> 0.4002472
B26: =IFERROR(INDEX('📦 Precios Proforma'!$B$5:$B$104, 7), "") -> 12 Pack Jugazzo Lata Surtido | C26: =IF(B26="","",SUMIFS('📈 Datos Completos'!$E$7:$E$5000, '📈 Datos Completos'!$C$7:$C$5000, B26, '📈 Datos Completos'!$Q$7:$Q$5000, IF($C$6="TODOS","*",$C$6), '📈 Datos Completos'!$D$7:$D$5000, IF($F$6="TODOS","*",$F$6))) -> 820 | D26: =IF(B26="","",SUMIFS('📈 Datos Completos'!$K$7:$K$5000, '📈 Datos Completos'!$C$7:$C$5000, B26, '📈 Datos Completos'!$Q$7:$Q$5000, IF($C$6="TODOS","*",$C$6), '📈 Datos Completos'!$D$7:$D$5000, IF($F$6="TODOS","*",$F$6))) -> 4874.4 | E26: =IF(B26="","",SUMIFS('📈 Datos Completos'!$N$7:$N$5000, '📈 Datos Completos'!$C$7:$C$5000, B26, '📈 Datos Completos'!$Q$7:$Q$5000, IF($C$6="TODOS","*",$C$6), '📈 Datos Completos'!$D$7:$D$5000, IF($F$6="TODOS","*",$F$6))) -> 12971.833 | F26: =IF(B26="","",SUMIFS('📈 Datos Completos'!$O$7:$O$5000, '📈 Datos Completos'!$C$7:$C$5000, B26, '📈 Datos Completos'!$Q$7:$Q$5000, IF($C$6="TODOS","*",$C$6), '📈 Datos Completos'!$D$7:$D$5000, IF($F$6="TODOS","*",$F$6))) -> -6383.1478 | G26: =IF(B26="","",IF(D26=0,0,F26/D26)) -> -1.3095248
B27: =IFERROR(INDEX('📦 Precios Proforma'!$B$5:$B$104, 8), "") -> 12 Pack LIPTON TE 500 ML | C27: =IF(B27="","",SUMIFS('📈 Datos Completos'!$E$7:$E$5000, '📈 Datos Completos'!$C$7:$C$5000, B27, '📈 Datos Completos'!$Q$7:$Q$5000, IF($C$6="TODOS","*",$C$6), '📈 Datos Completos'!$D$7:$D$5000, IF($F$6="TODOS","*",$F$6))) -> 0 | D27: =IF(B27="","",SUMIFS('📈 Datos Completos'!$K$7:$K$5000, '📈 Datos Completos'!$C$7:$C$5000, B27, '📈 Datos Completos'!$Q$7:$Q$5000, IF($C$6="TODOS","*",$C$6), '📈 Datos Completos'!$D$7:$D$5000, IF($F$6="TODOS","*",$F$6))) -> 0 | E27: =IF(B27="","",SUMIFS('📈 Datos Completos'!$N$7:$N$5000, '📈 Datos Completos'!$C$7:$C$5000, B27, '📈 Datos Completos'!$Q$7:$Q$5000, IF($C$6="TODOS","*",$C$6), '📈 Datos Completos'!$D$7:$D$5000, IF($F$6="TODOS","*",$F$6))) -> 0 | F27: =IF(B27="","",SUMIFS('📈 Datos Completos'!$O$7:$O$5000, '📈 Datos Completos'!$C$7:$C$5000, B27, '📈 Datos Completos'!$Q$7:$Q$5000, IF($C$6="TODOS","*",$C$6), '📈 Datos Completos'!$D$7:$D$5000, IF($F$6="TODOS","*",$F$6))) -> 0 | G27: =IF(B27="","",IF(D27=0,0,F27/D27)) -> 0
B28: =IFERROR(INDEX('📦 Precios Proforma'!$B$5:$B$104, 9), "") -> 12 Pack pepsi + sabores 12 onza | C28: =IF(B28="","",SUMIFS('📈 Datos Completos'!$E$7:$E$5000, '📈 Datos Completos'!$C$7:$C$5000, B28, '📈 Datos Completos'!$Q$7:$Q$5000, IF($C$6="TODOS","*",$C$6), '📈 Datos Completos'!$D$7:$D$5000, IF($F$6="TODOS","*",$F$6))) -> 924 | D28: =IF(B28="","",SUMIFS('📈 Datos Completos'!$K$7:$K$5000, '📈 Datos Completos'!$C$7:$C$5000, B28, '📈 Datos Completos'!$Q$7:$Q$5000, IF($C$6="TODOS","*",$C$6), '📈 Datos Completos'!$D$7:$D$5000, IF($F$6="TODOS","*",$F$6))) -> 5594.96 | E28: =IF(B28="","",SUMIFS('📈 Datos Completos'!$N$7:$N$5000, '📈 Datos Completos'!$C$7:$C$5000, B28, '📈 Datos Completos'!$Q$7:$Q$5000, IF($C$6="TODOS","*",$C$6), '📈 Datos Completos'!$D$7:$D$5000, IF($F$6="TODOS","*",$F$6))) -> 12500.119 | F28: =IF(B28="","",SUMIFS('📈 Datos Completos'!$O$7:$O$5000, '📈 Datos Completos'!$C$7:$C$5000, B28, '📈 Datos Completos'!$Q$7:$Q$5000, IF($C$6="TODOS","*",$C$6), '📈 Datos Completos'!$D$7:$D$5000, IF($F$6="TODOS","*",$F$6))) -> -3525.1592 | G28: =IF(B28="","",IF(D28=0,0,F28/D28)) -> -0.63005976
B29: =IFERROR(INDEX('📦 Precios Proforma'!$B$5:$B$104, 10), "") -> 12 Pack pepsi 1.5 ltr | C29: =IF(B29="","",SUMIFS('📈 Datos Completos'!$E$7:$E$5000, '📈 Datos Completos'!$C$7:$C$5000, B29, '📈 Datos Completos'!$Q$7:$Q$5000, IF($C$6="TODOS","*",$C$6), '📈 Datos Completos'!$D$7:$D$5000, IF($F$6="TODOS","*",$F$6))) -> 0 | D29: =IF(B29="","",SUMIFS('📈 Datos Completos'!$K$7:$K$5000, '📈 Datos Completos'!$C$7:$C$5000, B29, '📈 Datos Completos'!$Q$7:$Q$5000, IF($C$6="TODOS","*",$C$6), '📈 Datos Completos'!$D$7:$D$5000, IF($F$6="TODOS","*",$F$6))) -> 0 | E29: =IF(B29="","",SUMIFS('📈 Datos Completos'!$N$7:$N$5000, '📈 Datos Completos'!$C$7:$C$5000, B29, '📈 Datos Completos'!$Q$7:$Q$5000, IF($C$6="TODOS","*",$C$6), '📈 Datos Completos'!$D$7:$D$5000, IF($F$6="TODOS","*",$F$6))) -> 0 | F29: =IF(B29="","",SUMIFS('📈 Datos Completos'!$O$7:$O$5000, '📈 Datos Completos'!$C$7:$C$5000, B29, '📈 Datos Completos'!$Q$7:$Q$5000, IF($C$6="TODOS","*",$C$6), '📈 Datos Completos'!$D$7:$D$5000, IF($F$6="TODOS","*",$F$6))) -> 0 | G29: =IF(B29="","",IF(D29=0,0,F29/D29)) -> 0
B30: =IFERROR(INDEX('📦 Precios Proforma'!$B$5:$B$104, 11), "") -> 12 Pack Pepsi 500 ML | C30: =IF(B30="","",SUMIFS('📈 Datos Completos'!$E$7:$E$5000, '📈 Datos Completos'!$C$7:$C$5000, B30, '📈 Datos Completos'!$Q$7:$Q$5000, IF($C$6="TODOS","*",$C$6), '📈 Datos Completos'!$D$7:$D$5000, IF($F$6="TODOS","*",$F$6))) -> 48 | D30: =IF(B30="","",SUMIFS('📈 Datos Completos'!$K$7:$K$5000, '📈 Datos Completos'!$C$7:$C$5000, B30, '📈 Datos Completos'!$Q$7:$Q$5000, IF($C$6="TODOS","*",$C$6), '📈 Datos Completos'!$D$7:$D$5000, IF($F$6="TODOS","*",$F$6))) -> 847.2 | E30: =IF(B30="","",SUMIFS('📈 Datos Completos'!$N$7:$N$5000, '📈 Datos Completos'!$C$7:$C$5000, B30, '📈 Datos Completos'!$Q$7:$Q$5000, IF($C$6="TODOS","*",$C$6), '📈 Datos Completos'!$D$7:$D$5000, IF($F$6="TODOS","*",$F$6))) -> 1143.4699 | F30: =IF(B30="","",SUMIFS('📈 Datos Completos'!$O$7:$O$5000, '📈 Datos Completos'!$C$7:$C$5000, B30, '📈 Datos Completos'!$Q$7:$Q$5000, IF($C$6="TODOS","*",$C$6), '📈 Datos Completos'!$D$7:$D$5000, IF($F$6="TODOS","*",$F$6))) -> -296.26994 | G30: =IF(B30="","",IF(D30=0,0,F30/D30)) -> -0.34970484
B31: =IFERROR(INDEX('📦 Precios Proforma'!$B$5:$B$104, 12), "") -> 12 Pack Soda Ensa 500 ML | C31: =IF(B31="","",SUMIFS('📈 Datos Completos'!$E$7:$E$5000, '📈 Datos Completos'!$C$7:$C$5000, B31, '📈 Datos Completos'!$Q$7:$Q$5000, IF($C$6="TODOS","*",$C$6), '📈 Datos Completos'!$D$7:$D$5000, IF($F$6="TODOS","*",$F$6))) -> 640 | D31: =IF(B31="","",SUMIFS('📈 Datos Completos'!$K$7:$K$5000, '📈 Datos Completos'!$C$7:$C$5000, B31, '📈 Datos Completos'!$Q$7:$Q$5000, IF($C$6="TODOS","*",$C$6), '📈 Datos Completos'!$D$7:$D$5000, IF($F$6="TODOS","*",$F$6))) -> 11892.8 | E31: =IF(B31="","",SUMIFS('📈 Datos Completos'!$N$7:$N$5000, '📈 Datos Completos'!$C$7:$C$5000, B31, '📈 Datos Completos'!$Q$7:$Q$5000, IF($C$6="TODOS","*",$C$6), '📈 Datos Completos'!$D$7:$D$5000, IF($F$6="TODOS","*",$F$6))) -> 7271.34 | F31: =IF(B31="","",SUMIFS('📈 Datos Completos'!$O$7:$O$5000, '📈 Datos Completos'!$C$7:$C$5000, B31, '📈 Datos Completos'!$Q$7:$Q$5000, IF($C$6="TODOS","*",$C$6), '📈 Datos Completos'!$D$7:$D$5000, IF($F$6="TODOS","*",$F$6))) -> 4621.46 | G31: =IF(B31="","",IF(D31=0,0,F31/D31)) -> 0.3885931
B32: =IFERROR(INDEX('📦 Precios Proforma'!$B$5:$B$104, 13), "") -> 16 Pack Adrenaline 12 oz | C32: =IF(B32="","",SUMIFS('📈 Datos Completos'!$E$7:$E$5000, '📈 Datos Completos'!$C$7:$C$5000, B32, '📈 Datos Completos'!$Q$7:$Q$5000, IF($C$6="TODOS","*",$C$6), '📈 Datos Completos'!$D$7:$D$5000, IF($F$6="TODOS","*",$F$6))) -> 0 | D32: =IF(B32="","",SUMIFS('📈 Datos Completos'!$K$7:$K$5000, '📈 Datos Completos'!$C$7:$C$5000, B32, '📈 Datos Completos'!$Q$7:$Q$5000, IF($C$6="TODOS","*",$C$6), '📈 Datos Completos'!$D$7:$D$5000, IF($F$6="TODOS","*",$F$6))) -> 0 | E32: =IF(B32="","",SUMIFS('📈 Datos Completos'!$N$7:$N$5000, '📈 Datos Completos'!$C$7:$C$5000, B32, '📈 Datos Completos'!$Q$7:$Q$5000, IF($C$6="TODOS","*",$C$6), '📈 Datos Completos'!$D$7:$D$5000, IF($F$6="TODOS","*",$F$6))) -> 0 | F32: =IF(B32="","",SUMIFS('📈 Datos Completos'!$O$7:$O$5000, '📈 Datos Completos'!$C$7:$C$5000, B32, '📈 Datos Completos'!$Q$7:$Q$5000, IF($C$6="TODOS","*",$C$6), '📈 Datos Completos'!$D$7:$D$5000, IF($F$6="TODOS","*",$F$6))) -> 0 | G32: =IF(B32="","",IF(D32=0,0,F32/D32)) -> 0
B33: =IFERROR(INDEX('📦 Precios Proforma'!$B$5:$B$104, 14), "") -> 18 Pack 500 ml (pepsi,rojita) | C33: =IF(B33="","",SUMIFS('📈 Datos Completos'!$E$7:$E$5000, '📈 Datos Completos'!$C$7:$C$5000, B33, '📈 Datos Completos'!$Q$7:$Q$5000, IF($C$6="TODOS","*",$C$6), '📈 Datos Completos'!$D$7:$D$5000, IF($F$6="TODOS","*",$F$6))) -> 680 | D33: =IF(B33="","",SUMIFS('📈 Datos Completos'!$K$7:$K$5000, '📈 Datos Completos'!$C$7:$C$5000, B33, '📈 Datos Completos'!$Q$7:$Q$5000, IF($C$6="TODOS","*",$C$6), '📈 Datos Completos'!$D$7:$D$5000, IF($F$6="TODOS","*",$F$6))) -> 5472 | E33: =IF(B33="","",SUMIFS('📈 Datos Completos'!$N$7:$N$5000, '📈 Datos Completos'!$C$7:$C$5000, B33, '📈 Datos Completos'!$Q$7:$Q$5000, IF($C$6="TODOS","*",$C$6), '📈 Datos Completos'!$D$7:$D$5000, IF($F$6="TODOS","*",$F$6))) -> 8746.7261 | F33: =IF(B33="","",SUMIFS('📈 Datos Completos'!$O$7:$O$5000, '📈 Datos Completos'!$C$7:$C$5000, B33, '📈 Datos Completos'!$Q$7:$Q$5000, IF($C$6="TODOS","*",$C$6), '📈 Datos Completos'!$D$7:$D$5000, IF($F$6="TODOS","*",$F$6))) -> -3274.7261 | G33: =IF(B33="","",IF(D33=0,0,F33/D33)) -> -0.59845141
B34: =IFERROR(INDEX('📦 Precios Proforma'!$B$5:$B$104, 15), "") -> 18 PACK 500 ML PET SURTIDO | C34: =IF(B34="","",SUMIFS('📈 Datos Completos'!$E$7:$E$5000, '📈 Datos Completos'!$C$7:$C$5000, B34, '📈 Datos Completos'!$Q$7:$Q$5000, IF($C$6="TODOS","*",$C$6), '📈 Datos Completos'!$D$7:$D$5000, IF($F$6="TODOS","*",$F$6))) -> 0 | D34: =IF(B34="","",SUMIFS('📈 Datos Completos'!$K$7:$K$5000, '📈 Datos Completos'!$C$7:$C$5000, B34, '📈 Datos Completos'!$Q$7:$Q$5000, IF($C$6="TODOS","*",$C$6), '📈 Datos Completos'!$D$7:$D$5000, IF($F$6="TODOS","*",$F$6))) -> 0 | E34: =IF(B34="","",SUMIFS('📈 Datos Completos'!$N$7:$N$5000, '📈 Datos Completos'!$C$7:$C$5000, B34, '📈 Datos Completos'!$Q$7:$Q$5000, IF($C$6="TODOS","*",$C$6), '📈 Datos Completos'!$D$7:$D$5000, IF($F$6="TODOS","*",$F$6))) -> 0 | F34: =IF(B34="","",SUMIFS('📈 Datos Completos'!$O$7:$O$5000, '📈 Datos Completos'!$C$7:$C$5000, B34, '📈 Datos Completos'!$Q$7:$Q$5000, IF($C$6="TODOS","*",$C$6), '📈 Datos Completos'!$D$7:$D$5000, IF($F$6="TODOS","*",$F$6))) -> 0 | G34: =IF(B34="","",IF(D34=0,0,F34/D34)) -> 0
B35: =IFERROR(INDEX('📦 Precios Proforma'!$B$5:$B$104, 16), "") -> 18 Pack Be Light Surtido | C35: =IF(B35="","",SUMIFS('📈 Datos Completos'!$E$7:$E$5000, '📈 Datos Completos'!$C$7:$C$5000, B35, '📈 Datos Completos'!$Q$7:$Q$5000, IF($C$6="TODOS","*",$C$6), '📈 Datos Completos'!$D$7:$D$5000, IF($F$6="TODOS","*",$F$6))) -> 240 | D35: =IF(B35="","",SUMIFS('📈 Datos Completos'!$K$7:$K$5000, '📈 Datos Completos'!$C$7:$C$5000, B35, '📈 Datos Completos'!$Q$7:$Q$5000, IF($C$6="TODOS","*",$C$6), '📈 Datos Completos'!$D$7:$D$5000, IF($F$6="TODOS","*",$F$6))) -> 1728 | E35: =IF(B35="","",SUMIFS('📈 Datos Completos'!$N$7:$N$5000, '📈 Datos Completos'!$C$7:$C$5000, B35, '📈 Datos Completos'!$Q$7:$Q$5000, IF($C$6="TODOS","*",$C$6), '📈 Datos Completos'!$D$7:$D$5000, IF($F$6="TODOS","*",$F$6))) -> 2052.8185 | F35: =IF(B35="","",SUMIFS('📈 Datos Completos'!$O$7:$O$5000, '📈 Datos Completos'!$C$7:$C$5000, B35, '📈 Datos Completos'!$Q$7:$Q$5000, IF($C$6="TODOS","*",$C$6), '📈 Datos Completos'!$D$7:$D$5000, IF($F$6="TODOS","*",$F$6))) -> -324.81849 | G35: =IF(B35="","",IF(D35=0,0,F35/D35)) -> -0.18797366
B36: =IFERROR(INDEX('📦 Precios Proforma'!$B$5:$B$104, 17), "") -> 18 Pack Pepsi + Roja 500 ML | C36: =IF(B36="","",SUMIFS('📈 Datos Completos'!$E$7:$E$5000, '📈 Datos Completos'!$C$7:$C$5000, B36, '📈 Datos Completos'!$Q$7:$Q$5000, IF($C$6="TODOS","*",$C$6), '📈 Datos Completos'!$D$7:$D$5000, IF($F$6="TODOS","*",$F$6))) -> 1080 | D36: =IF(B36="","",SUMIFS('📈 Datos Completos'!$K$7:$K$5000, '📈 Datos Completos'!$C$7:$C$5000, B36, '📈 Datos Completos'!$Q$7:$Q$5000, IF($C$6="TODOS","*",$C$6), '📈 Datos Completos'!$D$7:$D$5000, IF($F$6="TODOS","*",$F$6))) -> 8496 | E36: =IF(B36="","",SUMIFS('📈 Datos Completos'!$N$7:$N$5000, '📈 Datos Completos'!$C$7:$C$5000, B36, '📈 Datos Completos'!$Q$7:$Q$5000, IF($C$6="TODOS","*",$C$6), '📈 Datos Completos'!$D$7:$D$5000, IF($F$6="TODOS","*",$F$6))) -> 19223.451 | F36: =IF(B36="","",SUMIFS('📈 Datos Completos'!$O$7:$O$5000, '📈 Datos Completos'!$C$7:$C$5000, B36, '📈 Datos Completos'!$Q$7:$Q$5000, IF($C$6="TODOS","*",$C$6), '📈 Datos Completos'!$D$7:$D$5000, IF($F$6="TODOS","*",$F$6))) -> -10727.451 | G36: =IF(B36="","",IF(D36=0,0,F36/D36)) -> -1.2626472
B37: =IFERROR(INDEX('📦 Precios Proforma'!$B$5:$B$104, 18), "") -> 2 Pack Pepsi + Ensa Toronja 3 Lts | C37: =IF(B37="","",SUMIFS('📈 Datos Completos'!$E$7:$E$5000, '📈 Datos Completos'!$C$7:$C$5000, B37, '📈 Datos Completos'!$Q$7:$Q$5000, IF($C$6="TODOS","*",$C$6), '📈 Datos Completos'!$D$7:$D$5000, IF($F$6="TODOS","*",$F$6))) -> 0 | D37: =IF(B37="","",SUMIFS('📈 Datos Completos'!$K$7:$K$5000, '📈 Datos Completos'!$C$7:$C$5000, B37, '📈 Datos Completos'!$Q$7:$Q$5000, IF($C$6="TODOS","*",$C$6), '📈 Datos Completos'!$D$7:$D$5000, IF($F$6="TODOS","*",$F$6))) -> 0 | E37: =IF(B37="","",SUMIFS('📈 Datos Completos'!$N$7:$N$5000, '📈 Datos Completos'!$C$7:$C$5000, B37, '📈 Datos Completos'!$Q$7:$Q$5000, IF($C$6="TODOS","*",$C$6), '📈 Datos Completos'!$D$7:$D$5000, IF($F$6="TODOS","*",$F$6))) -> 0 | F37: =IF(B37="","",SUMIFS('📈 Datos Completos'!$O$7:$O$5000, '📈 Datos Completos'!$C$7:$C$5000, B37, '📈 Datos Completos'!$Q$7:$Q$5000, IF($C$6="TODOS","*",$C$6), '📈 Datos Completos'!$D$7:$D$5000, IF($F$6="TODOS","*",$F$6))) -> 0 | G37: =IF(B37="","",IF(D37=0,0,F37/D37)) -> 0
B38: =IFERROR(INDEX('📦 Precios Proforma'!$B$5:$B$104, 19), "") -> 2 Pack Pepsi + Mirinda 3 Litro | C38: =IF(B38="","",SUMIFS('📈 Datos Completos'!$E$7:$E$5000, '📈 Datos Completos'!$C$7:$C$5000, B38, '📈 Datos Completos'!$Q$7:$Q$5000, IF($C$6="TODOS","*",$C$6), '📈 Datos Completos'!$D$7:$D$5000, IF($F$6="TODOS","*",$F$6))) -> 54 | D38: =IF(B38="","",SUMIFS('📈 Datos Completos'!$K$7:$K$5000, '📈 Datos Completos'!$C$7:$C$5000, B38, '📈 Datos Completos'!$Q$7:$Q$5000, IF($C$6="TODOS","*",$C$6), '📈 Datos Completos'!$D$7:$D$5000, IF($F$6="TODOS","*",$F$6))) -> 491.19 | E38: =IF(B38="","",SUMIFS('📈 Datos Completos'!$N$7:$N$5000, '📈 Datos Completos'!$C$7:$C$5000, B38, '📈 Datos Completos'!$Q$7:$Q$5000, IF($C$6="TODOS","*",$C$6), '📈 Datos Completos'!$D$7:$D$5000, IF($F$6="TODOS","*",$F$6))) -> 4028.5686 | F38: =IF(B38="","",SUMIFS('📈 Datos Completos'!$O$7:$O$5000, '📈 Datos Completos'!$C$7:$C$5000, B38, '📈 Datos Completos'!$Q$7:$Q$5000, IF($C$6="TODOS","*",$C$6), '📈 Datos Completos'!$D$7:$D$5000, IF($F$6="TODOS","*",$F$6))) -> -3253.8786 | G38: =IF(B38="","",IF(D38=0,0,F38/D38)) -> -6.6244806
B39: =IFERROR(INDEX('📦 Precios Proforma'!$B$5:$B$104, 20), "") -> 2 Pack Pepsi + Mirinda 3 lts | C39: =IF(B39="","",SUMIFS('📈 Datos Completos'!$E$7:$E$5000, '📈 Datos Completos'!$C$7:$C$5000, B39, '📈 Datos Completos'!$Q$7:$Q$5000, IF($C$6="TODOS","*",$C$6), '📈 Datos Completos'!$D$7:$D$5000, IF($F$6="TODOS","*",$F$6))) -> 0 | D39: =IF(B39="","",SUMIFS('📈 Datos Completos'!$K$7:$K$5000, '📈 Datos Completos'!$C$7:$C$5000, B39, '📈 Datos Completos'!$Q$7:$Q$5000, IF($C$6="TODOS","*",$C$6), '📈 Datos Completos'!$D$7:$D$5000, IF($F$6="TODOS","*",$F$6))) -> 0 | E39: =IF(B39="","",SUMIFS('📈 Datos Completos'!$N$7:$N$5000, '📈 Datos Completos'!$C$7:$C$5000, B39, '📈 Datos Completos'!$Q$7:$Q$5000, IF($C$6="TODOS","*",$C$6), '📈 Datos Completos'!$D$7:$D$5000, IF($F$6="TODOS","*",$F$6))) -> 0 | F39: =IF(B39="","",SUMIFS('📈 Datos Completos'!$O$7:$O$5000, '📈 Datos Completos'!$C$7:$C$5000, B39, '📈 Datos Completos'!$Q$7:$Q$5000, IF($C$6="TODOS","*",$C$6), '📈 Datos Completos'!$D$7:$D$5000, IF($F$6="TODOS","*",$F$6))) -> 0 | G39: =IF(B39="","",IF(D39=0,0,F39/D39)) -> 0
B40: =IFERROR(INDEX('📦 Precios Proforma'!$B$5:$B$104, 21), "") -> 2 Pack Pepsi + Roja 3 Litro | C40: =IF(B40="","",SUMIFS('📈 Datos Completos'!$E$7:$E$5000, '📈 Datos Completos'!$C$7:$C$5000, B40, '📈 Datos Completos'!$Q$7:$Q$5000, IF($C$6="TODOS","*",$C$6), '📈 Datos Completos'!$D$7:$D$5000, IF($F$6="TODOS","*",$F$6))) -> 14919 | D40: =IF(B40="","",SUMIFS('📈 Datos Completos'!$K$7:$K$5000, '📈 Datos Completos'!$C$7:$C$5000, B40, '📈 Datos Completos'!$Q$7:$Q$5000, IF($C$6="TODOS","*",$C$6), '📈 Datos Completos'!$D$7:$D$5000, IF($F$6="TODOS","*",$F$6))) -> 136938.92 | E40: =IF(B40="","",SUMIFS('📈 Datos Completos'!$N$7:$N$5000, '📈 Datos Completos'!$C$7:$C$5000, B40, '📈 Datos Completos'!$Q$7:$Q$5000, IF($C$6="TODOS","*",$C$6), '📈 Datos Completos'!$D$7:$D$5000, IF($F$6="TODOS","*",$F$6))) -> 77535.751 | F40: =IF(B40="","",SUMIFS('📈 Datos Completos'!$O$7:$O$5000, '📈 Datos Completos'!$C$7:$C$5000, B40, '📈 Datos Completos'!$Q$7:$Q$5000, IF($C$6="TODOS","*",$C$6), '📈 Datos Completos'!$D$7:$D$5000, IF($F$6="TODOS","*",$F$6))) -> 59653.316 | G40: =IF(B40="","",IF(D40=0,0,F40/D40)) -> 0.43561988
B41: =IFERROR(INDEX('📦 Precios Proforma'!$B$5:$B$104, 22), "") -> 2 Pack Pepsi + Rojita 3 Lts | C41: =IF(B41="","",SUMIFS('📈 Datos Completos'!$E$7:$E$5000, '📈 Datos Completos'!$C$7:$C$5000, B41, '📈 Datos Completos'!$Q$7:$Q$5000, IF($C$6="TODOS","*",$C$6), '📈 Datos Completos'!$D$7:$D$5000, IF($F$6="TODOS","*",$F$6))) -> 1788 | D41: =IF(B41="","",SUMIFS('📈 Datos Completos'!$K$7:$K$5000, '📈 Datos Completos'!$C$7:$C$5000, B41, '📈 Datos Completos'!$Q$7:$Q$5000, IF($C$6="TODOS","*",$C$6), '📈 Datos Completos'!$D$7:$D$5000, IF($F$6="TODOS","*",$F$6))) -> 15890.25 | E41: =IF(B41="","",SUMIFS('📈 Datos Completos'!$N$7:$N$5000, '📈 Datos Completos'!$C$7:$C$5000, B41, '📈 Datos Completos'!$Q$7:$Q$5000, IF($C$6="TODOS","*",$C$6), '📈 Datos Completos'!$D$7:$D$5000, IF($F$6="TODOS","*",$F$6))) -> 11080.352 | F41: =IF(B41="","",SUMIFS('📈 Datos Completos'!$O$7:$O$5000, '📈 Datos Completos'!$C$7:$C$5000, B41, '📈 Datos Completos'!$Q$7:$Q$5000, IF($C$6="TODOS","*",$C$6), '📈 Datos Completos'!$D$7:$D$5000, IF($F$6="TODOS","*",$F$6))) -> 4809.8976 | G41: =IF(B41="","",IF(D41=0,0,F41/D41)) -> 0.3026949
B42: =IFERROR(INDEX('📦 Precios Proforma'!$B$5:$B$104, 23), "") -> 2 Pack Pepsi + Toronja 3 Litro | C42: =IF(B42="","",SUMIFS('📈 Datos Completos'!$E$7:$E$5000, '📈 Datos Completos'!$C$7:$C$5000, B42, '📈 Datos Completos'!$Q$7:$Q$5000, IF($C$6="TODOS","*",$C$6), '📈 Datos Completos'!$D$7:$D$5000, IF($F$6="TODOS","*",$F$6))) -> 1620 | D42: =IF(B42="","",SUMIFS('📈 Datos Completos'!$K$7:$K$5000, '📈 Datos Completos'!$C$7:$C$5000, B42, '📈 Datos Completos'!$Q$7:$Q$5000, IF($C$6="TODOS","*",$C$6), '📈 Datos Completos'!$D$7:$D$5000, IF($F$6="TODOS","*",$F$6))) -> 13597.2 | E42: =IF(B42="","",SUMIFS('📈 Datos Completos'!$N$7:$N$5000, '📈 Datos Completos'!$C$7:$C$5000, B42, '📈 Datos Completos'!$Q$7:$Q$5000, IF($C$6="TODOS","*",$C$6), '📈 Datos Completos'!$D$7:$D$5000, IF($F$6="TODOS","*",$F$6))) -> 16529.829 | F42: =IF(B42="","",SUMIFS('📈 Datos Completos'!$O$7:$O$5000, '📈 Datos Completos'!$C$7:$C$5000, B42, '📈 Datos Completos'!$Q$7:$Q$5000, IF($C$6="TODOS","*",$C$6), '📈 Datos Completos'!$D$7:$D$5000, IF($F$6="TODOS","*",$F$6))) -> -2932.6286 | G42: =IF(B42="","",IF(D42=0,0,F42/D42)) -> -0.21567886
B43: =IFERROR(INDEX('📦 Precios Proforma'!$B$5:$B$104, 24), "") -> 24 Pack Gatorade Surtido | C43: =IF(B43="","",SUMIFS('📈 Datos Completos'!$E$7:$E$5000, '📈 Datos Completos'!$C$7:$C$5000, B43, '📈 Datos Completos'!$Q$7:$Q$5000, IF($C$6="TODOS","*",$C$6), '📈 Datos Completos'!$D$7:$D$5000, IF($F$6="TODOS","*",$F$6))) -> 2570 | D43: =IF(B43="","",SUMIFS('📈 Datos Completos'!$K$7:$K$5000, '📈 Datos Completos'!$C$7:$C$5000, B43, '📈 Datos Completos'!$Q$7:$Q$5000, IF($C$6="TODOS","*",$C$6), '📈 Datos Completos'!$D$7:$D$5000, IF($F$6="TODOS","*",$F$6))) -> 20424 | E43: =IF(B43="","",SUMIFS('📈 Datos Completos'!$N$7:$N$5000, '📈 Datos Completos'!$C$7:$C$5000, B43, '📈 Datos Completos'!$Q$7:$Q$5000, IF($C$6="TODOS","*",$C$6), '📈 Datos Completos'!$D$7:$D$5000, IF($F$6="TODOS","*",$F$6))) -> 16133.017 | F43: =IF(B43="","",SUMIFS('📈 Datos Completos'!$O$7:$O$5000, '📈 Datos Completos'!$C$7:$C$5000, B43, '📈 Datos Completos'!$Q$7:$Q$5000, IF($C$6="TODOS","*",$C$6), '📈 Datos Completos'!$D$7:$D$5000, IF($F$6="TODOS","*",$F$6))) -> 4290.9832 | G43: =IF(B43="","",IF(D43=0,0,F43/D43)) -> 0.21009514
B44: =IFERROR(INDEX('📦 Precios Proforma'!$B$5:$B$104, 25), "") -> 24 PACK GATORADE SURTIDO 500ML | C44: =IF(B44="","",SUMIFS('📈 Datos Completos'!$E$7:$E$5000, '📈 Datos Completos'!$C$7:$C$5000, B44, '📈 Datos Completos'!$Q$7:$Q$5000, IF($C$6="TODOS","*",$C$6), '📈 Datos Completos'!$D$7:$D$5000, IF($F$6="TODOS","*",$F$6))) -> 0 | D44: =IF(B44="","",SUMIFS('📈 Datos Completos'!$K$7:$K$5000, '📈 Datos Completos'!$C$7:$C$5000, B44, '📈 Datos Completos'!$Q$7:$Q$5000, IF($C$6="TODOS","*",$C$6), '📈 Datos Completos'!$D$7:$D$5000, IF($F$6="TODOS","*",$F$6))) -> 0 | E44: =IF(B44="","",SUMIFS('📈 Datos Completos'!$N$7:$N$5000, '📈 Datos Completos'!$C$7:$C$5000, B44, '📈 Datos Completos'!$Q$7:$Q$5000, IF($C$6="TODOS","*",$C$6), '📈 Datos Completos'!$D$7:$D$5000, IF($F$6="TODOS","*",$F$6))) -> 0 | F44: =IF(B44="","",SUMIFS('📈 Datos Completos'!$O$7:$O$5000, '📈 Datos Completos'!$C$7:$C$5000, B44, '📈 Datos Completos'!$Q$7:$Q$5000, IF($C$6="TODOS","*",$C$6), '📈 Datos Completos'!$D$7:$D$5000, IF($F$6="TODOS","*",$F$6))) -> 0 | G44: =IF(B44="","",IF(D44=0,0,F44/D44)) -> 0
B45: =IFERROR(INDEX('📦 Precios Proforma'!$B$5:$B$104, 26), "") -> 24 Pack Gatorade Surtido 600 ML | C45: =IF(B45="","",SUMIFS('📈 Datos Completos'!$E$7:$E$5000, '📈 Datos Completos'!$C$7:$C$5000, B45, '📈 Datos Completos'!$Q$7:$Q$5000, IF($C$6="TODOS","*",$C$6), '📈 Datos Completos'!$D$7:$D$5000, IF($F$6="TODOS","*",$F$6))) -> 720 | D45: =IF(B45="","",SUMIFS('📈 Datos Completos'!$K$7:$K$5000, '📈 Datos Completos'!$C$7:$C$5000, B45, '📈 Datos Completos'!$Q$7:$Q$5000, IF($C$6="TODOS","*",$C$6), '📈 Datos Completos'!$D$7:$D$5000, IF($F$6="TODOS","*",$F$6))) -> 6336 | E45: =IF(B45="","",SUMIFS('📈 Datos Completos'!$N$7:$N$5000, '📈 Datos Completos'!$C$7:$C$5000, B45, '📈 Datos Completos'!$Q$7:$Q$5000, IF($C$6="TODOS","*",$C$6), '📈 Datos Completos'!$D$7:$D$5000, IF($F$6="TODOS","*",$F$6))) -> 6384.9742 | F45: =IF(B45="","",SUMIFS('📈 Datos Completos'!$O$7:$O$5000, '📈 Datos Completos'!$C$7:$C$5000, B45, '📈 Datos Completos'!$Q$7:$Q$5000, IF($C$6="TODOS","*",$C$6), '📈 Datos Completos'!$D$7:$D$5000, IF($F$6="TODOS","*",$F$6))) -> -48.974161 | G45: =IF(B45="","",IF(D45=0,0,F45/D45)) -> -0.0077295078
B46: =IFERROR(INDEX('📦 Precios Proforma'!$B$5:$B$104, 27), "") -> 24 PACK PEPSI BLACK + SABORES 355ML LATA | C46: =IF(B46="","",SUMIFS('📈 Datos Completos'!$E$7:$E$5000, '📈 Datos Completos'!$C$7:$C$5000, B46, '📈 Datos Completos'!$Q$7:$Q$5000, IF($C$6="TODOS","*",$C$6), '📈 Datos Completos'!$D$7:$D$5000, IF($F$6="TODOS","*",$F$6))) -> 0 | D46: =IF(B46="","",SUMIFS('📈 Datos Completos'!$K$7:$K$5000, '📈 Datos Completos'!$C$7:$C$5000, B46, '📈 Datos Completos'!$Q$7:$Q$5000, IF($C$6="TODOS","*",$C$6), '📈 Datos Completos'!$D$7:$D$5000, IF($F$6="TODOS","*",$F$6))) -> 0 | E46: =IF(B46="","",SUMIFS('📈 Datos Completos'!$N$7:$N$5000, '📈 Datos Completos'!$C$7:$C$5000, B46, '📈 Datos Completos'!$Q$7:$Q$5000, IF($C$6="TODOS","*",$C$6), '📈 Datos Completos'!$D$7:$D$5000, IF($F$6="TODOS","*",$F$6))) -> 0 | F46: =IF(B46="","",SUMIFS('📈 Datos Completos'!$O$7:$O$5000, '📈 Datos Completos'!$C$7:$C$5000, B46, '📈 Datos Completos'!$Q$7:$Q$5000, IF($C$6="TODOS","*",$C$6), '📈 Datos Completos'!$D$7:$D$5000, IF($F$6="TODOS","*",$F$6))) -> 0 | G46: =IF(B46="","",IF(D46=0,0,F46/D46)) -> 0
B47: =IFERROR(INDEX('📦 Precios Proforma'!$B$5:$B$104, 28), "") -> 24 Pack pepsi Black lata | C47: =IF(B47="","",SUMIFS('📈 Datos Completos'!$E$7:$E$5000, '📈 Datos Completos'!$C$7:$C$5000, B47, '📈 Datos Completos'!$Q$7:$Q$5000, IF($C$6="TODOS","*",$C$6), '📈 Datos Completos'!$D$7:$D$5000, IF($F$6="TODOS","*",$F$6))) -> 0 | D47: =IF(B47="","",SUMIFS('📈 Datos Completos'!$K$7:$K$5000, '📈 Datos Completos'!$C$7:$C$5000, B47, '📈 Datos Completos'!$Q$7:$Q$5000, IF($C$6="TODOS","*",$C$6), '📈 Datos Completos'!$D$7:$D$5000, IF($F$6="TODOS","*",$F$6))) -> 0 | E47: =IF(B47="","",SUMIFS('📈 Datos Completos'!$N$7:$N$5000, '📈 Datos Completos'!$C$7:$C$5000, B47, '📈 Datos Completos'!$Q$7:$Q$5000, IF($C$6="TODOS","*",$C$6), '📈 Datos Completos'!$D$7:$D$5000, IF($F$6="TODOS","*",$F$6))) -> 0 | F47: =IF(B47="","",SUMIFS('📈 Datos Completos'!$O$7:$O$5000, '📈 Datos Completos'!$C$7:$C$5000, B47, '📈 Datos Completos'!$Q$7:$Q$5000, IF($C$6="TODOS","*",$C$6), '📈 Datos Completos'!$D$7:$D$5000, IF($F$6="TODOS","*",$F$6))) -> 0 | G47: =IF(B47="","",IF(D47=0,0,F47/D47)) -> 0
B48: =IFERROR(INDEX('📦 Precios Proforma'!$B$5:$B$104, 29), "") -> 24 Pack Soda Ensa Lata | C48: =IF(B48="","",SUMIFS('📈 Datos Completos'!$E$7:$E$5000, '📈 Datos Completos'!$C$7:$C$5000, B48, '📈 Datos Completos'!$Q$7:$Q$5000, IF($C$6="TODOS","*",$C$6), '📈 Datos Completos'!$D$7:$D$5000, IF($F$6="TODOS","*",$F$6))) -> 0 | D48: =IF(B48="","",SUMIFS('📈 Datos Completos'!$K$7:$K$5000, '📈 Datos Completos'!$C$7:$C$5000, B48, '📈 Datos Completos'!$Q$7:$Q$5000, IF($C$6="TODOS","*",$C$6), '📈 Datos Completos'!$D$7:$D$5000, IF($F$6="TODOS","*",$F$6))) -> 0 | E48: =IF(B48="","",SUMIFS('📈 Datos Completos'!$N$7:$N$5000, '📈 Datos Completos'!$C$7:$C$5000, B48, '📈 Datos Completos'!$Q$7:$Q$5000, IF($C$6="TODOS","*",$C$6), '📈 Datos Completos'!$D$7:$D$5000, IF($F$6="TODOS","*",$F$6))) -> 0 | F48: =IF(B48="","",SUMIFS('📈 Datos Completos'!$O$7:$O$5000, '📈 Datos Completos'!$C$7:$C$5000, B48, '📈 Datos Completos'!$Q$7:$Q$5000, IF($C$6="TODOS","*",$C$6), '📈 Datos Completos'!$D$7:$D$5000, IF($F$6="TODOS","*",$F$6))) -> 0 | G48: =IF(B48="","",IF(D48=0,0,F48/D48)) -> 0
B49: =IFERROR(INDEX('📦 Precios Proforma'!$B$5:$B$104, 30), "") -> 3 Pack Pepsi + Ensa Toronja 3 Lts | C49: =IF(B49="","",SUMIFS('📈 Datos Completos'!$E$7:$E$5000, '📈 Datos Completos'!$C$7:$C$5000, B49, '📈 Datos Completos'!$Q$7:$Q$5000, IF($C$6="TODOS","*",$C$6), '📈 Datos Completos'!$D$7:$D$5000, IF($F$6="TODOS","*",$F$6))) -> 0 | D49: =IF(B49="","",SUMIFS('📈 Datos Completos'!$K$7:$K$5000, '📈 Datos Completos'!$C$7:$C$5000, B49, '📈 Datos Completos'!$Q$7:$Q$5000, IF($C$6="TODOS","*",$C$6), '📈 Datos Completos'!$D$7:$D$5000, IF($F$6="TODOS","*",$F$6))) -> 0 | E49: =IF(B49="","",SUMIFS('📈 Datos Completos'!$N$7:$N$5000, '📈 Datos Completos'!$C$7:$C$5000, B49, '📈 Datos Completos'!$Q$7:$Q$5000, IF($C$6="TODOS","*",$C$6), '📈 Datos Completos'!$D$7:$D$5000, IF($F$6="TODOS","*",$F$6))) -> 0 | F49: =IF(B49="","",SUMIFS('📈 Datos Completos'!$O$7:$O$5000, '📈 Datos Completos'!$C$7:$C$5000, B49, '📈 Datos Completos'!$Q$7:$Q$5000, IF($C$6="TODOS","*",$C$6), '📈 Datos Completos'!$D$7:$D$5000, IF($F$6="TODOS","*",$F$6))) -> 0 | G49: =IF(B49="","",IF(D49=0,0,F49/D49)) -> 0
B50: =IFERROR(INDEX('📦 Precios Proforma'!$B$5:$B$104, 31), "") -> 3 Pack Pepsi + Roja + Campestre | C50: =IF(B50="","",SUMIFS('📈 Datos Completos'!$E$7:$E$5000, '📈 Datos Completos'!$C$7:$C$5000, B50, '📈 Datos Completos'!$Q$7:$Q$5000, IF($C$6="TODOS","*",$C$6), '📈 Datos Completos'!$D$7:$D$5000, IF($F$6="TODOS","*",$F$6))) -> 6776 | D50: =IF(B50="","",SUMIFS('📈 Datos Completos'!$K$7:$K$5000, '📈 Datos Completos'!$C$7:$C$5000, B50, '📈 Datos Completos'!$Q$7:$Q$5000, IF($C$6="TODOS","*",$C$6), '📈 Datos Completos'!$D$7:$D$5000, IF($F$6="TODOS","*",$F$6))) -> 61827.32 | E50: =IF(B50="","",SUMIFS('📈 Datos Completos'!$N$7:$N$5000, '📈 Datos Completos'!$C$7:$C$5000, B50, '📈 Datos Completos'!$Q$7:$Q$5000, IF($C$6="TODOS","*",$C$6), '📈 Datos Completos'!$D$7:$D$5000, IF($F$6="TODOS","*",$F$6))) -> 38463.831 | F50: =IF(B50="","",SUMIFS('📈 Datos Completos'!$O$7:$O$5000, '📈 Datos Completos'!$C$7:$C$5000, B50, '📈 Datos Completos'!$Q$7:$Q$5000, IF($C$6="TODOS","*",$C$6), '📈 Datos Completos'!$D$7:$D$5000, IF($F$6="TODOS","*",$F$6))) -> 28043.862 | G50: =IF(B50="","",IF(D50=0,0,F50/D50)) -> 0.45358366
B51: =IFERROR(INDEX('📦 Precios Proforma'!$B$5:$B$104, 32), "") -> 3 Pack Pepsi + Roja + Campestre 3 Litro | C51: =IF(B51="","",SUMIFS('📈 Datos Completos'!$E$7:$E$5000, '📈 Datos Completos'!$C$7:$C$5000, B51, '📈 Datos Completos'!$Q$7:$Q$5000, IF($C$6="TODOS","*",$C$6), '📈 Datos Completos'!$D$7:$D$5000, IF($F$6="TODOS","*",$F$6))) -> 1930 | D51: =IF(B51="","",SUMIFS('📈 Datos Completos'!$K$7:$K$5000, '📈 Datos Completos'!$C$7:$C$5000, B51, '📈 Datos Completos'!$Q$7:$Q$5000, IF($C$6="TODOS","*",$C$6), '📈 Datos Completos'!$D$7:$D$5000, IF($F$6="TODOS","*",$F$6))) -> 17554 | E51: =IF(B51="","",SUMIFS('📈 Datos Completos'!$N$7:$N$5000, '📈 Datos Completos'!$C$7:$C$5000, B51, '📈 Datos Completos'!$Q$7:$Q$5000, IF($C$6="TODOS","*",$C$6), '📈 Datos Completos'!$D$7:$D$5000, IF($F$6="TODOS","*",$F$6))) -> 10209.156 | F51: =IF(B51="","",SUMIFS('📈 Datos Completos'!$O$7:$O$5000, '📈 Datos Completos'!$C$7:$C$5000, B51, '📈 Datos Completos'!$Q$7:$Q$5000, IF($C$6="TODOS","*",$C$6), '📈 Datos Completos'!$D$7:$D$5000, IF($F$6="TODOS","*",$F$6))) -> 7344.8438 | G51: =IF(B51="","",IF(D51=0,0,F51/D51)) -> 0.41841425
B52: =IFERROR(INDEX('📦 Precios Proforma'!$B$5:$B$104, 33), "") -> 3 Pack Pepsi + Roja 3 Litro | C52: =IF(B52="","",SUMIFS('📈 Datos Completos'!$E$7:$E$5000, '📈 Datos Completos'!$C$7:$C$5000, B52, '📈 Datos Completos'!$Q$7:$Q$5000, IF($C$6="TODOS","*",$C$6), '📈 Datos Completos'!$D$7:$D$5000, IF($F$6="TODOS","*",$F$6))) -> 0 | D52: =IF(B52="","",SUMIFS('📈 Datos Completos'!$K$7:$K$5000, '📈 Datos Completos'!$C$7:$C$5000, B52, '📈 Datos Completos'!$Q$7:$Q$5000, IF($C$6="TODOS","*",$C$6), '📈 Datos Completos'!$D$7:$D$5000, IF($F$6="TODOS","*",$F$6))) -> 0 | E52: =IF(B52="","",SUMIFS('📈 Datos Completos'!$N$7:$N$5000, '📈 Datos Completos'!$C$7:$C$5000, B52, '📈 Datos Completos'!$Q$7:$Q$5000, IF($C$6="TODOS","*",$C$6), '📈 Datos Completos'!$D$7:$D$5000, IF($F$6="TODOS","*",$F$6))) -> 0 | F52: =IF(B52="","",SUMIFS('📈 Datos Completos'!$O$7:$O$5000, '📈 Datos Completos'!$C$7:$C$5000, B52, '📈 Datos Completos'!$Q$7:$Q$5000, IF($C$6="TODOS","*",$C$6), '📈 Datos Completos'!$D$7:$D$5000, IF($F$6="TODOS","*",$F$6))) -> 0 | G52: =IF(B52="","",IF(D52=0,0,F52/D52)) -> 0
B53: =IFERROR(INDEX('📦 Precios Proforma'!$B$5:$B$104, 34), "") -> 3 Pack Pepsi + Rojita + Toronja 3 Lts | C53: =IF(B53="","",SUMIFS('📈 Datos Completos'!$E$7:$E$5000, '📈 Datos Completos'!$C$7:$C$5000, B53, '📈 Datos Completos'!$Q$7:$Q$5000, IF($C$6="TODOS","*",$C$6), '📈 Datos Completos'!$D$7:$D$5000, IF($F$6="TODOS","*",$F$6))) -> 60 | D53: =IF(B53="","",SUMIFS('📈 Datos Completos'!$K$7:$K$5000, '📈 Datos Completos'!$C$7:$C$5000, B53, '📈 Datos Completos'!$Q$7:$Q$5000, IF($C$6="TODOS","*",$C$6), '📈 Datos Completos'!$D$7:$D$5000, IF($F$6="TODOS","*",$F$6))) -> 513.6 | E53: =IF(B53="","",SUMIFS('📈 Datos Completos'!$N$7:$N$5000, '📈 Datos Completos'!$C$7:$C$5000, B53, '📈 Datos Completos'!$Q$7:$Q$5000, IF($C$6="TODOS","*",$C$6), '📈 Datos Completos'!$D$7:$D$5000, IF($F$6="TODOS","*",$F$6))) -> 186.09621 | F53: =IF(B53="","",SUMIFS('📈 Datos Completos'!$O$7:$O$5000, '📈 Datos Completos'!$C$7:$C$5000, B53, '📈 Datos Completos'!$Q$7:$Q$5000, IF($C$6="TODOS","*",$C$6), '📈 Datos Completos'!$D$7:$D$5000, IF($F$6="TODOS","*",$F$6))) -> 327.50379 | G53: =IF(B53="","",IF(D53=0,0,F53/D53)) -> 0.63766315
B54: =IFERROR(INDEX('📦 Precios Proforma'!$B$5:$B$104, 35), "") -> 3 Pack Pepsi + Rojita + Ensa Toronja 3 Lts | C54: =IF(B54="","",SUMIFS('📈 Datos Completos'!$E$7:$E$5000, '📈 Datos Completos'!$C$7:$C$5000, B54, '📈 Datos Completos'!$Q$7:$Q$5000, IF($C$6="TODOS","*",$C$6), '📈 Datos Completos'!$D$7:$D$5000, IF($F$6="TODOS","*",$F$6))) -> 160 | D54: =IF(B54="","",SUMIFS('📈 Datos Completos'!$K$7:$K$5000, '📈 Datos Completos'!$C$7:$C$5000, B54, '📈 Datos Completos'!$Q$7:$Q$5000, IF($C$6="TODOS","*",$C$6), '📈 Datos Completos'!$D$7:$D$5000, IF($F$6="TODOS","*",$F$6))) -> 1369.6 | E54: =IF(B54="","",SUMIFS('📈 Datos Completos'!$N$7:$N$5000, '📈 Datos Completos'!$C$7:$C$5000, B54, '📈 Datos Completos'!$Q$7:$Q$5000, IF($C$6="TODOS","*",$C$6), '📈 Datos Completos'!$D$7:$D$5000, IF($F$6="TODOS","*",$F$6))) -> 1255.1194 | F54: =IF(B54="","",SUMIFS('📈 Datos Completos'!$O$7:$O$5000, '📈 Datos Completos'!$C$7:$C$5000, B54, '📈 Datos Completos'!$Q$7:$Q$5000, IF($C$6="TODOS","*",$C$6), '📈 Datos Completos'!$D$7:$D$5000, IF($F$6="TODOS","*",$F$6))) -> 114.48063 | G54: =IF(B54="","",IF(D54=0,0,F54/D54)) -> 0.083586911
B55: =IFERROR(INDEX('📦 Precios Proforma'!$B$5:$B$104, 36), "") -> 4 Pack Gatorade Surtido 500 ML | C55: =IF(B55="","",SUMIFS('📈 Datos Completos'!$E$7:$E$5000, '📈 Datos Completos'!$C$7:$C$5000, B55, '📈 Datos Completos'!$Q$7:$Q$5000, IF($C$6="TODOS","*",$C$6), '📈 Datos Completos'!$D$7:$D$5000, IF($F$6="TODOS","*",$F$6))) -> 873 | D55: =IF(B55="","",SUMIFS('📈 Datos Completos'!$K$7:$K$5000, '📈 Datos Completos'!$C$7:$C$5000, B55, '📈 Datos Completos'!$Q$7:$Q$5000, IF($C$6="TODOS","*",$C$6), '📈 Datos Completos'!$D$7:$D$5000, IF($F$6="TODOS","*",$F$6))) -> 6246.27 | E55: =IF(B55="","",SUMIFS('📈 Datos Completos'!$N$7:$N$5000, '📈 Datos Completos'!$C$7:$C$5000, B55, '📈 Datos Completos'!$Q$7:$Q$5000, IF($C$6="TODOS","*",$C$6), '📈 Datos Completos'!$D$7:$D$5000, IF($F$6="TODOS","*",$F$6))) -> 6562.863 | F55: =IF(B55="","",SUMIFS('📈 Datos Completos'!$O$7:$O$5000, '📈 Datos Completos'!$C$7:$C$5000, B55, '📈 Datos Completos'!$Q$7:$Q$5000, IF($C$6="TODOS","*",$C$6), '📈 Datos Completos'!$D$7:$D$5000, IF($F$6="TODOS","*",$F$6))) -> -316.59297 | G55: =IF(B55="","",IF(D55=0,0,F55/D55)) -> -0.050685124
B56: =IFERROR(INDEX('📦 Precios Proforma'!$B$5:$B$104, 37), "") -> 4 Pack Pepsi + Roja | C56: =IF(B56="","",SUMIFS('📈 Datos Completos'!$E$7:$E$5000, '📈 Datos Completos'!$C$7:$C$5000, B56, '📈 Datos Completos'!$Q$7:$Q$5000, IF($C$6="TODOS","*",$C$6), '📈 Datos Completos'!$D$7:$D$5000, IF($F$6="TODOS","*",$F$6))) -> 165 | D56: =IF(B56="","",SUMIFS('📈 Datos Completos'!$K$7:$K$5000, '📈 Datos Completos'!$C$7:$C$5000, B56, '📈 Datos Completos'!$Q$7:$Q$5000, IF($C$6="TODOS","*",$C$6), '📈 Datos Completos'!$D$7:$D$5000, IF($F$6="TODOS","*",$F$6))) -> 2108.7 | E56: =IF(B56="","",SUMIFS('📈 Datos Completos'!$N$7:$N$5000, '📈 Datos Completos'!$C$7:$C$5000, B56, '📈 Datos Completos'!$Q$7:$Q$5000, IF($C$6="TODOS","*",$C$6), '📈 Datos Completos'!$D$7:$D$5000, IF($F$6="TODOS","*",$F$6))) -> 782.96262 | F56: =IF(B56="","",SUMIFS('📈 Datos Completos'!$O$7:$O$5000, '📈 Datos Completos'!$C$7:$C$5000, B56, '📈 Datos Completos'!$Q$7:$Q$5000, IF($C$6="TODOS","*",$C$6), '📈 Datos Completos'!$D$7:$D$5000, IF($F$6="TODOS","*",$F$6))) -> 1325.7374 | G56: =IF(B56="","",IF(D56=0,0,F56/D56)) -> 0.6286989
B57: =IFERROR(INDEX('📦 Precios Proforma'!$B$5:$B$104, 38), "") -> 4 Pack Pepsi + Roja + Toronja | C57: =IF(B57="","",SUMIFS('📈 Datos Completos'!$E$7:$E$5000, '📈 Datos Completos'!$C$7:$C$5000, B57, '📈 Datos Completos'!$Q$7:$Q$5000, IF($C$6="TODOS","*",$C$6), '📈 Datos Completos'!$D$7:$D$5000, IF($F$6="TODOS","*",$F$6))) -> 6597 | D57: =IF(B57="","",SUMIFS('📈 Datos Completos'!$K$7:$K$5000, '📈 Datos Completos'!$C$7:$C$5000, B57, '📈 Datos Completos'!$Q$7:$Q$5000, IF($C$6="TODOS","*",$C$6), '📈 Datos Completos'!$D$7:$D$5000, IF($F$6="TODOS","*",$F$6))) -> 85485.66 | E57: =IF(B57="","",SUMIFS('📈 Datos Completos'!$N$7:$N$5000, '📈 Datos Completos'!$C$7:$C$5000, B57, '📈 Datos Completos'!$Q$7:$Q$5000, IF($C$6="TODOS","*",$C$6), '📈 Datos Completos'!$D$7:$D$5000, IF($F$6="TODOS","*",$F$6))) -> 54519.363 | F57: =IF(B57="","",SUMIFS('📈 Datos Completos'!$O$7:$O$5000, '📈 Datos Completos'!$C$7:$C$5000, B57, '📈 Datos Completos'!$Q$7:$Q$5000, IF($C$6="TODOS","*",$C$6), '📈 Datos Completos'!$D$7:$D$5000, IF($F$6="TODOS","*",$F$6))) -> 31872.078 | G57: =IF(B57="","",IF(D57=0,0,F57/D57)) -> 0.37283537
B58: =IFERROR(INDEX('📦 Precios Proforma'!$B$5:$B$104, 39), "") -> 4 Pack Pepsi + Rojita + Toronja 3 lts | C58: =IF(B58="","",SUMIFS('📈 Datos Completos'!$E$7:$E$5000, '📈 Datos Completos'!$C$7:$C$5000, B58, '📈 Datos Completos'!$Q$7:$Q$5000, IF($C$6="TODOS","*",$C$6), '📈 Datos Completos'!$D$7:$D$5000, IF($F$6="TODOS","*",$F$6))) -> 1007 | D58: =IF(B58="","",SUMIFS('📈 Datos Completos'!$K$7:$K$5000, '📈 Datos Completos'!$C$7:$C$5000, B58, '📈 Datos Completos'!$Q$7:$Q$5000, IF($C$6="TODOS","*",$C$6), '📈 Datos Completos'!$D$7:$D$5000, IF($F$6="TODOS","*",$F$6))) -> 11328.66 | E58: =IF(B58="","",SUMIFS('📈 Datos Completos'!$N$7:$N$5000, '📈 Datos Completos'!$C$7:$C$5000, B58, '📈 Datos Completos'!$Q$7:$Q$5000, IF($C$6="TODOS","*",$C$6), '📈 Datos Completos'!$D$7:$D$5000, IF($F$6="TODOS","*",$F$6))) -> 8522.3572 | F58: =IF(B58="","",SUMIFS('📈 Datos Completos'!$O$7:$O$5000, '📈 Datos Completos'!$C$7:$C$5000, B58, '📈 Datos Completos'!$Q$7:$Q$5000, IF($C$6="TODOS","*",$C$6), '📈 Datos Completos'!$D$7:$D$5000, IF($F$6="TODOS","*",$F$6))) -> 2806.3028 | G58: =IF(B58="","",IF(D58=0,0,F58/D58)) -> 0.2477171
B59: =IFERROR(INDEX('📦 Precios Proforma'!$B$5:$B$104, 40), "") -> 6 Pack Lipton 250ml Tetra | C59: =IF(B59="","",SUMIFS('📈 Datos Completos'!$E$7:$E$5000, '📈 Datos Completos'!$C$7:$C$5000, B59, '📈 Datos Completos'!$Q$7:$Q$5000, IF($C$6="TODOS","*",$C$6), '📈 Datos Completos'!$D$7:$D$5000, IF($F$6="TODOS","*",$F$6))) -> 0 | D59: =IF(B59="","",SUMIFS('📈 Datos Completos'!$K$7:$K$5000, '📈 Datos Completos'!$C$7:$C$5000, B59, '📈 Datos Completos'!$Q$7:$Q$5000, IF($C$6="TODOS","*",$C$6), '📈 Datos Completos'!$D$7:$D$5000, IF($F$6="TODOS","*",$F$6))) -> 0 | E59: =IF(B59="","",SUMIFS('📈 Datos Completos'!$N$7:$N$5000, '📈 Datos Completos'!$C$7:$C$5000, B59, '📈 Datos Completos'!$Q$7:$Q$5000, IF($C$6="TODOS","*",$C$6), '📈 Datos Completos'!$D$7:$D$5000, IF($F$6="TODOS","*",$F$6))) -> 0 | F59: =IF(B59="","",SUMIFS('📈 Datos Completos'!$O$7:$O$5000, '📈 Datos Completos'!$C$7:$C$5000, B59, '📈 Datos Completos'!$Q$7:$Q$5000, IF($C$6="TODOS","*",$C$6), '📈 Datos Completos'!$D$7:$D$5000, IF($F$6="TODOS","*",$F$6))) -> 0 | G59: =IF(B59="","",IF(D59=0,0,F59/D59)) -> 0
B60: =IFERROR(INDEX('📦 Precios Proforma'!$B$5:$B$104, 41), "") -> 8 Pack Pepsi Black | C60: =IF(B60="","",SUMIFS('📈 Datos Completos'!$E$7:$E$5000, '📈 Datos Completos'!$C$7:$C$5000, B60, '📈 Datos Completos'!$Q$7:$Q$5000, IF($C$6="TODOS","*",$C$6), '📈 Datos Completos'!$D$7:$D$5000, IF($F$6="TODOS","*",$F$6))) -> 1798 | D60: =IF(B60="","",SUMIFS('📈 Datos Completos'!$K$7:$K$5000, '📈 Datos Completos'!$C$7:$C$5000, B60, '📈 Datos Completos'!$Q$7:$Q$5000, IF($C$6="TODOS","*",$C$6), '📈 Datos Completos'!$D$7:$D$5000, IF($F$6="TODOS","*",$F$6))) -> 18069.06 | E60: =IF(B60="","",SUMIFS('📈 Datos Completos'!$N$7:$N$5000, '📈 Datos Completos'!$C$7:$C$5000, B60, '📈 Datos Completos'!$Q$7:$Q$5000, IF($C$6="TODOS","*",$C$6), '📈 Datos Completos'!$D$7:$D$5000, IF($F$6="TODOS","*",$F$6))) -> 19356.643 | F60: =IF(B60="","",SUMIFS('📈 Datos Completos'!$O$7:$O$5000, '📈 Datos Completos'!$C$7:$C$5000, B60, '📈 Datos Completos'!$Q$7:$Q$5000, IF($C$6="TODOS","*",$C$6), '📈 Datos Completos'!$D$7:$D$5000, IF($F$6="TODOS","*",$F$6))) -> -1287.5825 | G60: =IF(B60="","",IF(D60=0,0,F60/D60)) -> -0.071258966
B61: =IFERROR(INDEX('📦 Precios Proforma'!$B$5:$B$104, 42), "") -> 8 Pack Pepsi Black 355Ml Lata | C61: =IF(B61="","",SUMIFS('📈 Datos Completos'!$E$7:$E$5000, '📈 Datos Completos'!$C$7:$C$5000, B61, '📈 Datos Completos'!$Q$7:$Q$5000, IF($C$6="TODOS","*",$C$6), '📈 Datos Completos'!$D$7:$D$5000, IF($F$6="TODOS","*",$F$6))) -> 984 | D61: =IF(B61="","",SUMIFS('📈 Datos Completos'!$K$7:$K$5000, '📈 Datos Completos'!$C$7:$C$5000, B61, '📈 Datos Completos'!$Q$7:$Q$5000, IF($C$6="TODOS","*",$C$6), '📈 Datos Completos'!$D$7:$D$5000, IF($F$6="TODOS","*",$F$6))) -> 12338.82 | E61: =IF(B61="","",SUMIFS('📈 Datos Completos'!$N$7:$N$5000, '📈 Datos Completos'!$C$7:$C$5000, B61, '📈 Datos Completos'!$Q$7:$Q$5000, IF($C$6="TODOS","*",$C$6), '📈 Datos Completos'!$D$7:$D$5000, IF($F$6="TODOS","*",$F$6))) -> 8839.119 | F61: =IF(B61="","",SUMIFS('📈 Datos Completos'!$O$7:$O$5000, '📈 Datos Completos'!$C$7:$C$5000, B61, '📈 Datos Completos'!$Q$7:$Q$5000, IF($C$6="TODOS","*",$C$6), '📈 Datos Completos'!$D$7:$D$5000, IF($F$6="TODOS","*",$F$6))) -> 3499.701 | G61: =IF(B61="","",IF(D61=0,0,F61/D61)) -> 0.28363336
B62: =IFERROR(INDEX('📦 Precios Proforma'!$B$5:$B$104, 43), "") -> AMP 600 ML | C62: =IF(B62="","",SUMIFS('📈 Datos Completos'!$E$7:$E$5000, '📈 Datos Completos'!$C$7:$C$5000, B62, '📈 Datos Completos'!$Q$7:$Q$5000, IF($C$6="TODOS","*",$C$6), '📈 Datos Completos'!$D$7:$D$5000, IF($F$6="TODOS","*",$F$6))) -> 1104 | D62: =IF(B62="","",SUMIFS('📈 Datos Completos'!$K$7:$K$5000, '📈 Datos Completos'!$C$7:$C$5000, B62, '📈 Datos Completos'!$Q$7:$Q$5000, IF($C$6="TODOS","*",$C$6), '📈 Datos Completos'!$D$7:$D$5000, IF($F$6="TODOS","*",$F$6))) -> 23930.64 | E62: =IF(B62="","",SUMIFS('📈 Datos Completos'!$N$7:$N$5000, '📈 Datos Completos'!$C$7:$C$5000, B62, '📈 Datos Completos'!$Q$7:$Q$5000, IF($C$6="TODOS","*",$C$6), '📈 Datos Completos'!$D$7:$D$5000, IF($F$6="TODOS","*",$F$6))) -> 16992.612 | F62: =IF(B62="","",SUMIFS('📈 Datos Completos'!$O$7:$O$5000, '📈 Datos Completos'!$C$7:$C$5000, B62, '📈 Datos Completos'!$Q$7:$Q$5000, IF($C$6="TODOS","*",$C$6), '📈 Datos Completos'!$D$7:$D$5000, IF($F$6="TODOS","*",$F$6))) -> 7394.4701 | G62: =IF(B62="","",IF(D62=0,0,F62/D62)) -> 0.30899592
B63: =IFERROR(INDEX('📦 Precios Proforma'!$B$5:$B$104, 44), "") -> Armado de Polines Walmart | C63: =IF(B63="","",SUMIFS('📈 Datos Completos'!$E$7:$E$5000, '📈 Datos Completos'!$C$7:$C$5000, B63, '📈 Datos Completos'!$Q$7:$Q$5000, IF($C$6="TODOS","*",$C$6), '📈 Datos Completos'!$D$7:$D$5000, IF($F$6="TODOS","*",$F$6))) -> 0 | D63: =IF(B63="","",SUMIFS('📈 Datos Completos'!$K$7:$K$5000, '📈 Datos Completos'!$C$7:$C$5000, B63, '📈 Datos Completos'!$Q$7:$Q$5000, IF($C$6="TODOS","*",$C$6), '📈 Datos Completos'!$D$7:$D$5000, IF($F$6="TODOS","*",$F$6))) -> 0 | E63: =IF(B63="","",SUMIFS('📈 Datos Completos'!$N$7:$N$5000, '📈 Datos Completos'!$C$7:$C$5000, B63, '📈 Datos Completos'!$Q$7:$Q$5000, IF($C$6="TODOS","*",$C$6), '📈 Datos Completos'!$D$7:$D$5000, IF($F$6="TODOS","*",$F$6))) -> 0 | F63: =IF(B63="","",SUMIFS('📈 Datos Completos'!$O$7:$O$5000, '📈 Datos Completos'!$C$7:$C$5000, B63, '📈 Datos Completos'!$Q$7:$Q$5000, IF($C$6="TODOS","*",$C$6), '📈 Datos Completos'!$D$7:$D$5000, IF($F$6="TODOS","*",$F$6))) -> 0 | G63: =IF(B63="","",IF(D63=0,0,F63/D63)) -> 0
B64: =IFERROR(INDEX('📦 Precios Proforma'!$B$5:$B$104, 45), "") -> GRANEL | C64: =IF(B64="","",SUMIFS('📈 Datos Completos'!$E$7:$E$5000, '📈 Datos Completos'!$C$7:$C$5000, B64, '📈 Datos Completos'!$Q$7:$Q$5000, IF($C$6="TODOS","*",$C$6), '📈 Datos Completos'!$D$7:$D$5000, IF($F$6="TODOS","*",$F$6))) -> 2010 | D64: =IF(B64="","",SUMIFS('📈 Datos Completos'!$K$7:$K$5000, '📈 Datos Completos'!$C$7:$C$5000, B64, '📈 Datos Completos'!$Q$7:$Q$5000, IF($C$6="TODOS","*",$C$6), '📈 Datos Completos'!$D$7:$D$5000, IF($F$6="TODOS","*",$F$6))) -> 91950 | E64: =IF(B64="","",SUMIFS('📈 Datos Completos'!$N$7:$N$5000, '📈 Datos Completos'!$C$7:$C$5000, B64, '📈 Datos Completos'!$Q$7:$Q$5000, IF($C$6="TODOS","*",$C$6), '📈 Datos Completos'!$D$7:$D$5000, IF($F$6="TODOS","*",$F$6))) -> 28587.773 | F64: =IF(B64="","",SUMIFS('📈 Datos Completos'!$O$7:$O$5000, '📈 Datos Completos'!$C$7:$C$5000, B64, '📈 Datos Completos'!$Q$7:$Q$5000, IF($C$6="TODOS","*",$C$6), '📈 Datos Completos'!$D$7:$D$5000, IF($F$6="TODOS","*",$F$6))) -> 63362.227 | G64: =IF(B64="","",IF(D64=0,0,F64/D64)) -> 0.68909437
B65: =IFERROR(INDEX('📦 Precios Proforma'!$B$5:$B$104, 46), "") -> PRECIO BASE (sin coincidencia) | C65: =IF(B65="","",SUMIFS('📈 Datos Completos'!$E$7:$E$5000, '📈 Datos Completos'!$C$7:$C$5000, B65, '📈 Datos Completos'!$Q$7:$Q$5000, IF($C$6="TODOS","*",$C$6), '📈 Datos Completos'!$D$7:$D$5000, IF($F$6="TODOS","*",$F$6))) -> 0 | D65: =IF(B65="","",SUMIFS('📈 Datos Completos'!$K$7:$K$5000, '📈 Datos Completos'!$C$7:$C$5000, B65, '📈 Datos Completos'!$Q$7:$Q$5000, IF($C$6="TODOS","*",$C$6), '📈 Datos Completos'!$D$7:$D$5000, IF($F$6="TODOS","*",$F$6))) -> 0 | E65: =IF(B65="","",SUMIFS('📈 Datos Completos'!$N$7:$N$5000, '📈 Datos Completos'!$C$7:$C$5000, B65, '📈 Datos Completos'!$Q$7:$Q$5000, IF($C$6="TODOS","*",$C$6), '📈 Datos Completos'!$D$7:$D$5000, IF($F$6="TODOS","*",$F$6))) -> 0 | F65: =IF(B65="","",SUMIFS('📈 Datos Completos'!$O$7:$O$5000, '📈 Datos Completos'!$C$7:$C$5000, B65, '📈 Datos Completos'!$Q$7:$Q$5000, IF($C$6="TODOS","*",$C$6), '📈 Datos Completos'!$D$7:$D$5000, IF($F$6="TODOS","*",$F$6))) -> 0 | G65: =IF(B65="","",IF(D65=0,0,F65/D65)) -> 0
B66: =IFERROR(INDEX('📦 Precios Proforma'!$B$5:$B$104, 47), "") -> TRASIEGO MANTICA | C66: =IF(B66="","",SUMIFS('📈 Datos Completos'!$E$7:$E$5000, '📈 Datos Completos'!$C$7:$C$5000, B66, '📈 Datos Completos'!$Q$7:$Q$5000, IF($C$6="TODOS","*",$C$6), '📈 Datos Completos'!$D$7:$D$5000, IF($F$6="TODOS","*",$F$6))) -> 5 | D66: =IF(B66="","",SUMIFS('📈 Datos Completos'!$K$7:$K$5000, '📈 Datos Completos'!$C$7:$C$5000, B66, '📈 Datos Completos'!$Q$7:$Q$5000, IF($C$6="TODOS","*",$C$6), '📈 Datos Completos'!$D$7:$D$5000, IF($F$6="TODOS","*",$F$6))) -> 300 | E66: =IF(B66="","",SUMIFS('📈 Datos Completos'!$N$7:$N$5000, '📈 Datos Completos'!$C$7:$C$5000, B66, '📈 Datos Completos'!$Q$7:$Q$5000, IF($C$6="TODOS","*",$C$6), '📈 Datos Completos'!$D$7:$D$5000, IF($F$6="TODOS","*",$F$6))) -> 63.134471 | F66: =IF(B66="","",SUMIFS('📈 Datos Completos'!$O$7:$O$5000, '📈 Datos Completos'!$C$7:$C$5000, B66, '📈 Datos Completos'!$Q$7:$Q$5000, IF($C$6="TODOS","*",$C$6), '📈 Datos Completos'!$D$7:$D$5000, IF($F$6="TODOS","*",$F$6))) -> 236.86553 | G66: =IF(B66="","",IF(D66=0,0,F66/D66)) -> 0.78955176
B67: =IFERROR(INDEX('📦 Precios Proforma'!$B$5:$B$104, 48), "") -> TRASIEGO PRICESMART | C67: =IF(B67="","",SUMIFS('📈 Datos Completos'!$E$7:$E$5000, '📈 Datos Completos'!$C$7:$C$5000, B67, '📈 Datos Completos'!$Q$7:$Q$5000, IF($C$6="TODOS","*",$C$6), '📈 Datos Completos'!$D$7:$D$5000, IF($F$6="TODOS","*",$F$6))) -> 72 | D67: =IF(B67="","",SUMIFS('📈 Datos Completos'!$K$7:$K$5000, '📈 Datos Completos'!$C$7:$C$5000, B67, '📈 Datos Completos'!$Q$7:$Q$5000, IF($C$6="TODOS","*",$C$6), '📈 Datos Completos'!$D$7:$D$5000, IF($F$6="TODOS","*",$F$6))) -> 6049.3 | E67: =IF(B67="","",SUMIFS('📈 Datos Completos'!$N$7:$N$5000, '📈 Datos Completos'!$C$7:$C$5000, B67, '📈 Datos Completos'!$Q$7:$Q$5000, IF($C$6="TODOS","*",$C$6), '📈 Datos Completos'!$D$7:$D$5000, IF($F$6="TODOS","*",$F$6))) -> 1301.5313 | F67: =IF(B67="","",SUMIFS('📈 Datos Completos'!$O$7:$O$5000, '📈 Datos Completos'!$C$7:$C$5000, B67, '📈 Datos Completos'!$Q$7:$Q$5000, IF($C$6="TODOS","*",$C$6), '📈 Datos Completos'!$D$7:$D$5000, IF($F$6="TODOS","*",$F$6))) -> 4747.7687 | G67: =IF(B67="","",IF(D67=0,0,F67/D67)) -> 0.78484596
B68: =IFERROR(INDEX('📦 Precios Proforma'!$B$5:$B$104, 49), "") -> TRASIEGO WM | C68: =IF(B68="","",SUMIFS('📈 Datos Completos'!$E$7:$E$5000, '📈 Datos Completos'!$C$7:$C$5000, B68, '📈 Datos Completos'!$Q$7:$Q$5000, IF($C$6="TODOS","*",$C$6), '📈 Datos Completos'!$D$7:$D$5000, IF($F$6="TODOS","*",$F$6))) -> 732.3 | D68: =IF(B68="","",SUMIFS('📈 Datos Completos'!$K$7:$K$5000, '📈 Datos Completos'!$C$7:$C$5000, B68, '📈 Datos Completos'!$Q$7:$Q$5000, IF($C$6="TODOS","*",$C$6), '📈 Datos Completos'!$D$7:$D$5000, IF($F$6="TODOS","*",$F$6))) -> 36922 | E68: =IF(B68="","",SUMIFS('📈 Datos Completos'!$N$7:$N$5000, '📈 Datos Completos'!$C$7:$C$5000, B68, '📈 Datos Completos'!$Q$7:$Q$5000, IF($C$6="TODOS","*",$C$6), '📈 Datos Completos'!$D$7:$D$5000, IF($F$6="TODOS","*",$F$6))) -> 14275.963 | F68: =IF(B68="","",SUMIFS('📈 Datos Completos'!$O$7:$O$5000, '📈 Datos Completos'!$C$7:$C$5000, B68, '📈 Datos Completos'!$Q$7:$Q$5000, IF($C$6="TODOS","*",$C$6), '📈 Datos Completos'!$D$7:$D$5000, IF($F$6="TODOS","*",$F$6))) -> 23395.509 | G68: =IF(B68="","",IF(D68=0,0,F68/D68)) -> 0.63364686
B69: =IFERROR(INDEX('📦 Precios Proforma'!$B$5:$B$104, 50), "") -> 0 | C69: =IF(B69="","",SUMIFS('📈 Datos Completos'!$E$7:$E$5000, '📈 Datos Completos'!$C$7:$C$5000, B69, '📈 Datos Completos'!$Q$7:$Q$5000, IF($C$6="TODOS","*",$C$6), '📈 Datos Completos'!$D$7:$D$5000, IF($F$6="TODOS","*",$F$6))) -> 0 | D69: =IF(B69="","",SUMIFS('📈 Datos Completos'!$K$7:$K$5000, '📈 Datos Completos'!$C$7:$C$5000, B69, '📈 Datos Completos'!$Q$7:$Q$5000, IF($C$6="TODOS","*",$C$6), '📈 Datos Completos'!$D$7:$D$5000, IF($F$6="TODOS","*",$F$6))) -> 0 | E69: =IF(B69="","",SUMIFS('📈 Datos Completos'!$N$7:$N$5000, '📈 Datos Completos'!$C$7:$C$5000, B69, '📈 Datos Completos'!$Q$7:$Q$5000, IF($C$6="TODOS","*",$C$6), '📈 Datos Completos'!$D$7:$D$5000, IF($F$6="TODOS","*",$F$6))) -> 0 | F69: =IF(B69="","",SUMIFS('📈 Datos Completos'!$O$7:$O$5000, '📈 Datos Completos'!$C$7:$C$5000, B69, '📈 Datos Completos'!$Q$7:$Q$5000, IF($C$6="TODOS","*",$C$6), '📈 Datos Completos'!$D$7:$D$5000, IF($F$6="TODOS","*",$F$6))) -> 0 | G69: =IF(B69="","",IF(D69=0,0,F69/D69)) -> 0
B70: TOTAL FILTRADO | C70: =SUM(C20:C69) -> 53232.3 | D70: =SUM(D20:D69) -> 647038.09 | E70: =SUM(E20:E69) -> 435080.7 | F70: =SUM(F20:F69) -> 224377.39 | G70: =IF(D70=0,0,F70/D70) -> 0.34677617
B72: 📖 GUÍA RÁPIDA DE USO
B73: 1️⃣ Ingresa los datos de producción en la hoja "📈 Datos Completos" (columnas B a G)
B74: 2️⃣ Registra la asistencia en "👥 Asistencia" (fecha, ID, nombre, entrada, salida, horas extras)
B75: 3️⃣ Completa recursos y tarimas en "📋 Detalle Diario" (fecha, turno, tarimas, paletizante)
B76: 4️⃣ Ajusta precios en "📦 Precios Proforma" y supuestos de costo en "⚙️ Supuestos"
B77: 5️⃣ El Dashboard Ejecutivo se actualiza automáticamente con filtros por Mes y Turno
B78: 6️⃣ Usa los colores de alerta: 🔴 Rojo = Pérdida | 🟡 Amarillo = Margen bajo | 🟢 Verde = Rentable

Sheet 📦 Rentabilidad por Producto
B1: 📦 RENTABILIDAD DETALLADA POR PRODUCTO (COSTEO POR ABSORCIÓN PROPORCIONAL)
B2: Análisis de costos desagregado: Ingresos, Costos Laborales, Materiales y Rentabilidad por SKU
B4: Producto | C4: Unidades Producidas (Packs) | D4: Total Etiquetas | E4: Ingreso Empaque (C$) | F4: Ingreso Etiquetas (C$) | G4: Ingreso Total (C$) | H4: Costo Laboral Asignado (C$) | I4: Costo Material Etiquetas (C$) | J4: Costo Total Asignado (C$) | K4: Ganancia Neta (C$) | L4: Margen Neto %
B5: =IFERROR(INDEX('📦 Precios Proforma'!$B$5:$B$104, 1), "") -> 12 pack 12 oz pepsi +sabores | C5: =IF(B5="","",SUMIF('📈 Datos Completos'!$C$7:$C$5000, B5, '📈 Datos Completos'!$E$7:$E$5000)) -> 252 | D5: =IF(B5="","",SUMIF('📈 Datos Completos'!$C$7:$C$5000, B5, '📈 Datos Completos'!$H$7:$H$5000)) -> 252 | E5: =IF(B5="","",SUMIF('📈 Datos Completos'!$C$7:$C$5000, B5, '📈 Datos Completos'!$I$7:$I$5000)) -> 1093.68 | F5: =IF(B5="","",SUMIF('📈 Datos Completos'!$C$7:$C$5000, B5, '📈 Datos Completos'!$J$7:$J$5000)) -> 254.52 | G5: =IF(B5="","",SUMIF('📈 Datos Completos'!$C$7:$C$5000, B5, '📈 Datos Completos'!$K$7:$K$5000)) -> 1348.2 | H5: =IF(B5="","",SUMIF('📈 Datos Completos'!$C$7:$C$5000, B5, '📈 Datos Completos'!$L$7:$L$5000)) -> 1326.1284 | I5: =IF(B5="","",SUMIF('📈 Datos Completos'!$C$7:$C$5000, B5, '📈 Datos Completos'!$M$7:$M$5000)) -> 22.68 | J5: =IF(B5="","",SUMIF('📈 Datos Completos'!$C$7:$C$5000, B5, '📈 Datos Completos'!$N$7:$N$5000)) -> 1348.8084 | K5: =IF(B5="","",SUMIF('📈 Datos Completos'!$C$7:$C$5000, B5, '📈 Datos Completos'!$O$7:$O$5000)) -> -0.60839975 | L5: =IF(B5="","",IF(G5=0, 0, K5/G5)) -> -0.00045126817
B6: =IFERROR(INDEX('📦 Precios Proforma'!$B$5:$B$104, 2), "") -> 12 Pack Adrenalina Rush 16 Onz | C6: =IF(B6="","",SUMIF('📈 Datos Completos'!$C$7:$C$5000, B6, '📈 Datos Completos'!$E$7:$E$5000)) -> 0 | D6: =IF(B6="","",SUMIF('📈 Datos Completos'!$C$7:$C$5000, B6, '📈 Datos Completos'!$H$7:$H$5000)) -> 0 | E6: =IF(B6="","",SUMIF('📈 Datos Completos'!$C$7:$C$5000, B6, '📈 Datos Completos'!$I$7:$I$5000)) -> 0 | F6: =IF(B6="","",SUMIF('📈 Datos Completos'!$C$7:$C$5000, B6, '📈 Datos Completos'!$J$7:$J$5000)) -> 0 | G6: =IF(B6="","",SUMIF('📈 Datos Completos'!$C$7:$C$5000, B6, '📈 Datos Completos'!$K$7:$K$5000)) -> 0 | H6: =IF(B6="","",SUMIF('📈 Datos Completos'!$C$7:$C$5000, B6, '📈 Datos Completos'!$L$7:$L$5000)) -> 0 | I6: =IF(B6="","",SUMIF('📈 Datos Completos'!$C$7:$C$5000, B6, '📈 Datos Completos'!$M$7:$M$5000)) -> 0 | J6: =IF(B6="","",SUMIF('📈 Datos Completos'!$C$7:$C$5000, B6, '📈 Datos Completos'!$N$7:$N$5000)) -> 0 | K6: =IF(B6="","",SUMIF('📈 Datos Completos'!$C$7:$C$5000, B6, '📈 Datos Completos'!$O$7:$O$5000)) -> 0 | L6: =IF(B6="","",IF(G6=0, 0, K6/G6)) -> 0
B7: =IFERROR(INDEX('📦 Precios Proforma'!$B$5:$B$104, 3), "") -> 12 PACK AMP 600 ML | C7: =IF(B7="","",SUMIF('📈 Datos Completos'!$C$7:$C$5000, B7, '📈 Datos Completos'!$E$7:$E$5000)) -> 974 | D7: =IF(B7="","",SUMIF('📈 Datos Completos'!$C$7:$C$5000, B7, '📈 Datos Completos'!$H$7:$H$5000)) -> 11648 | E7: =IF(B7="","",SUMIF('📈 Datos Completos'!$C$7:$C$5000, B7, '📈 Datos Completos'!$I$7:$I$5000)) -> 6018.54 | F7: =IF(B7="","",SUMIF('📈 Datos Completos'!$C$7:$C$5000, B7, '📈 Datos Completos'!$J$7:$J$5000)) -> 13094.56 | G7: =IF(B7="","",SUMIF('📈 Datos Completos'!$C$7:$C$5000, B7, '📈 Datos Completos'!$K$7:$K$5000)) -> 19113.1 | H7: =IF(B7="","",SUMIF('📈 Datos Completos'!$C$7:$C$5000, B7, '📈 Datos Completos'!$L$7:$L$5000)) -> 11129.054 | I7: =IF(B7="","",SUMIF('📈 Datos Completos'!$C$7:$C$5000, B7, '📈 Datos Completos'!$M$7:$M$5000)) -> 1048.32 | J7: =IF(B7="","",SUMIF('📈 Datos Completos'!$C$7:$C$5000, B7, '📈 Datos Completos'!$N$7:$N$5000)) -> 12177.374 | K7: =IF(B7="","",SUMIF('📈 Datos Completos'!$C$7:$C$5000, B7, '📈 Datos Completos'!$O$7:$O$5000)) -> 6935.7255 | L7: =IF(B7="","",IF(G7=0, 0, K7/G7)) -> 0.36287811
B8: =IFERROR(INDEX('📦 Precios Proforma'!$B$5:$B$104, 4), "") -> 12 Pack California Surtido 400 ML | C8: =IF(B8="","",SUMIF('📈 Datos Completos'!$C$7:$C$5000, B8, '📈 Datos Completos'!$E$7:$E$5000)) -> 1192 | D8: =IF(B8="","",SUMIF('📈 Datos Completos'!$C$7:$C$5000, B8, '📈 Datos Completos'!$H$7:$H$5000)) -> 1236 | E8: =IF(B8="","",SUMIF('📈 Datos Completos'!$C$7:$C$5000, B8, '📈 Datos Completos'!$I$7:$I$5000)) -> 6233.44 | F8: =IF(B8="","",SUMIF('📈 Datos Completos'!$C$7:$C$5000, B8, '📈 Datos Completos'!$J$7:$J$5000)) -> 1438.76 | G8: =IF(B8="","",SUMIF('📈 Datos Completos'!$C$7:$C$5000, B8, '📈 Datos Completos'!$K$7:$K$5000)) -> 7672.2 | H8: =IF(B8="","",SUMIF('📈 Datos Completos'!$C$7:$C$5000, B8, '📈 Datos Completos'!$L$7:$L$5000)) -> 9728.2312 | I8: =IF(B8="","",SUMIF('📈 Datos Completos'!$C$7:$C$5000, B8, '📈 Datos Completos'!$M$7:$M$5000)) -> 111.24 | J8: =IF(B8="","",SUMIF('📈 Datos Completos'!$C$7:$C$5000, B8, '📈 Datos Completos'!$N$7:$N$5000)) -> 9839.4712 | K8: =IF(B8="","",SUMIF('📈 Datos Completos'!$C$7:$C$5000, B8, '📈 Datos Completos'!$O$7:$O$5000)) -> -2167.2712 | L8: =IF(B8="","",IF(G8=0, 0, K8/G8)) -> -0.28248367
B9: =IFERROR(INDEX('📦 Precios Proforma'!$B$5:$B$104, 5), "") -> 12 Pack CSD 500 ML PET | C9: =IF(B9="","",SUMIF('📈 Datos Completos'!$C$7:$C$5000, B9, '📈 Datos Completos'!$E$7:$E$5000)) -> 0 | D9: =IF(B9="","",SUMIF('📈 Datos Completos'!$C$7:$C$5000, B9, '📈 Datos Completos'!$H$7:$H$5000)) -> 0 | E9: =IF(B9="","",SUMIF('📈 Datos Completos'!$C$7:$C$5000, B9, '📈 Datos Completos'!$I$7:$I$5000)) -> 0 | F9: =IF(B9="","",SUMIF('📈 Datos Completos'!$C$7:$C$5000, B9, '📈 Datos Completos'!$J$7:$J$5000)) -> 0 | G9: =IF(B9="","",SUMIF('📈 Datos Completos'!$C$7:$C$5000, B9, '📈 Datos Completos'!$K$7:$K$5000)) -> 0 | H9: =IF(B9="","",SUMIF('📈 Datos Completos'!$C$7:$C$5000, B9, '📈 Datos Completos'!$L$7:$L$5000)) -> 0 | I9: =IF(B9="","",SUMIF('📈 Datos Completos'!$C$7:$C$5000, B9, '📈 Datos Completos'!$M$7:$M$5000)) -> 0 | J9: =IF(B9="","",SUMIF('📈 Datos Completos'!$C$7:$C$5000, B9, '📈 Datos Completos'!$N$7:$N$5000)) -> 0 | K9: =IF(B9="","",SUMIF('📈 Datos Completos'!$C$7:$C$5000, B9, '📈 Datos Completos'!$O$7:$O$5000)) -> 0 | L9: =IF(B9="","",IF(G9=0, 0, K9/G9)) -> 0
B10: =IFERROR(INDEX('📦 Precios Proforma'!$B$5:$B$104, 6), "") -> 12 Pack Ensa Soda 500ml Pet | C10: =IF(B10="","",SUMIF('📈 Datos Completos'!$C$7:$C$5000, B10, '📈 Datos Completos'!$E$7:$E$5000)) -> 438 | D10: =IF(B10="","",SUMIF('📈 Datos Completos'!$C$7:$C$5000, B10, '📈 Datos Completos'!$H$7:$H$5000)) -> 5694 | E10: =IF(B10="","",SUMIF('📈 Datos Completos'!$C$7:$C$5000, B10, '📈 Datos Completos'!$I$7:$I$5000)) -> 2641.14 | F10: =IF(B10="","",SUMIF('📈 Datos Completos'!$C$7:$C$5000, B10, '📈 Datos Completos'!$J$7:$J$5000)) -> 7686.9 | G10: =IF(B10="","",SUMIF('📈 Datos Completos'!$C$7:$C$5000, B10, '📈 Datos Completos'!$K$7:$K$5000)) -> 10328.04 | H10: =IF(B10="","",SUMIF('📈 Datos Completos'!$C$7:$C$5000, B10, '📈 Datos Completos'!$L$7:$L$5000)) -> 5681.8109 | I10: =IF(B10="","",SUMIF('📈 Datos Completos'!$C$7:$C$5000, B10, '📈 Datos Completos'!$M$7:$M$5000)) -> 512.46 | J10: =IF(B10="","",SUMIF('📈 Datos Completos'!$C$7:$C$5000, B10, '📈 Datos Completos'!$N$7:$N$5000)) -> 6194.2709 | K10: =IF(B10="","",SUMIF('📈 Datos Completos'!$C$7:$C$5000, B10, '📈 Datos Completos'!$O$7:$O$5000)) -> 4133.7691 | L10: =IF(B10="","",IF(G10=0, 0, K10/G10)) -> 0.4002472
B11: =IFERROR(INDEX('📦 Precios Proforma'!$B$5:$B$104, 7), "") -> 12 Pack Jugazzo Lata Surtido | C11: =IF(B11="","",SUMIF('📈 Datos Completos'!$C$7:$C$5000, B11, '📈 Datos Completos'!$E$7:$E$5000)) -> 820 | D11: =IF(B11="","",SUMIF('📈 Datos Completos'!$C$7:$C$5000, B11, '📈 Datos Completos'!$H$7:$H$5000)) -> 700 | E11: =IF(B11="","",SUMIF('📈 Datos Completos'!$C$7:$C$5000, B11, '📈 Datos Completos'!$I$7:$I$5000)) -> 4051.8 | F11: =IF(B11="","",SUMIF('📈 Datos Completos'!$C$7:$C$5000, B11, '📈 Datos Completos'!$J$7:$J$5000)) -> 822.6 | G11: =IF(B11="","",SUMIF('📈 Datos Completos'!$C$7:$C$5000, B11, '📈 Datos Completos'!$K$7:$K$5000)) -> 4874.4 | H11: =IF(B11="","",SUMIF('📈 Datos Completos'!$C$7:$C$5000, B11, '📈 Datos Completos'!$L$7:$L$5000)) -> 12908.833 | I11: =IF(B11="","",SUMIF('📈 Datos Completos'!$C$7:$C$5000, B11, '📈 Datos Completos'!$M$7:$M$5000)) -> 63 | J11: =IF(B11="","",SUMIF('📈 Datos Completos'!$C$7:$C$5000, B11, '📈 Datos Completos'!$N$7:$N$5000)) -> 12971.833 | K11: =IF(B11="","",SUMIF('📈 Datos Completos'!$C$7:$C$5000, B11, '📈 Datos Completos'!$O$7:$O$5000)) -> -6383.1478 | L11: =IF(B11="","",IF(G11=0, 0, K11/G11)) -> -1.3095248
B12: =IFERROR(INDEX('📦 Precios Proforma'!$B$5:$B$104, 8), "") -> 12 Pack LIPTON TE 500 ML | C12: =IF(B12="","",SUMIF('📈 Datos Completos'!$C$7:$C$5000, B12, '📈 Datos Completos'!$E$7:$E$5000)) -> 0 | D12: =IF(B12="","",SUMIF('📈 Datos Completos'!$C$7:$C$5000, B12, '📈 Datos Completos'!$H$7:$H$5000)) -> 0 | E12: =IF(B12="","",SUMIF('📈 Datos Completos'!$C$7:$C$5000, B12, '📈 Datos Completos'!$I$7:$I$5000)) -> 0 | F12: =IF(B12="","",SUMIF('📈 Datos Completos'!$C$7:$C$5000, B12, '📈 Datos Completos'!$J$7:$J$5000)) -> 0 | G12: =IF(B12="","",SUMIF('📈 Datos Completos'!$C$7:$C$5000, B12, '📈 Datos Completos'!$K$7:$K$5000)) -> 0 | H12: =IF(B12="","",SUMIF('📈 Datos Completos'!$C$7:$C$5000, B12, '📈 Datos Completos'!$L$7:$L$5000)) -> 0 | I12: =IF(B12="","",SUMIF('📈 Datos Completos'!$C$7:$C$5000, B12, '📈 Datos Completos'!$M$7:$M$5000)) -> 0 | J12: =IF(B12="","",SUMIF('📈 Datos Completos'!$C$7:$C$5000, B12, '📈 Datos Completos'!$N$7:$N$5000)) -> 0 | K12: =IF(B12="","",SUMIF('📈 Datos Completos'!$C$7:$C$5000, B12, '📈 Datos Completos'!$O$7:$O$5000)) -> 0 | L12: =IF(B12="","",IF(G12=0, 0, K12/G12)) -> 0
B13: =IFERROR(INDEX('📦 Precios Proforma'!$B$5:$B$104, 9), "") -> 12 Pack pepsi + sabores 12 onza | C13: =IF(B13="","",SUMIF('📈 Datos Completos'!$C$7:$C$5000, B13, '📈 Datos Completos'!$E$7:$E$5000)) -> 924 | D13: =IF(B13="","",SUMIF('📈 Datos Completos'!$C$7:$C$5000, B13, '📈 Datos Completos'!$H$7:$H$5000)) -> 924 | E13: =IF(B13="","",SUMIF('📈 Datos Completos'!$C$7:$C$5000, B13, '📈 Datos Completos'!$I$7:$I$5000)) -> 4537.96 | F13: =IF(B13="","",SUMIF('📈 Datos Completos'!$C$7:$C$5000, B13, '📈 Datos Completos'!$J$7:$J$5000)) -> 1057 | G13: =IF(B13="","",SUMIF('📈 Datos Completos'!$C$7:$C$5000, B13, '📈 Datos Completos'!$K$7:$K$5000)) -> 5594.96 | H13: =IF(B13="","",SUMIF('📈 Datos Completos'!$C$7:$C$5000, B13, '📈 Datos Completos'!$L$7:$L$5000)) -> 12416.959 | I13: =IF(B13="","",SUMIF('📈 Datos Completos'!$C$7:$C$5000, B13, '📈 Datos Completos'!$M$7:$M$5000)) -> 83.16 | J13: =IF(B13="","",SUMIF('📈 Datos Completos'!$C$7:$C$5000, B13, '📈 Datos Completos'!$N$7:$N$5000)) -> 12500.119 | K13: =IF(B13="","",SUMIF('📈 Datos Completos'!$C$7:$C$5000, B13, '📈 Datos Completos'!$O$7:$O$5000)) -> -3525.1592 | L13: =IF(B13="","",IF(G13=0, 0, K13/G13)) -> -0.63005976
B14: =IFERROR(INDEX('📦 Precios Proforma'!$B$5:$B$104, 10), "") -> 12 Pack pepsi 1.5 ltr | C14: =IF(B14="","",SUMIF('📈 Datos Completos'!$C$7:$C$5000, B14, '📈 Datos Completos'!$E$7:$E$5000)) -> 0 | D14: =IF(B14="","",SUMIF('📈 Datos Completos'!$C$7:$C$5000, B14, '📈 Datos Completos'!$H$7:$H$5000)) -> 0 | E14: =IF(B14="","",SUMIF('📈 Datos Completos'!$C$7:$C$5000, B14, '📈 Datos Completos'!$I$7:$I$5000)) -> 0 | F14: =IF(B14="","",SUMIF('📈 Datos Completos'!$C$7:$C$5000, B14, '📈 Datos Completos'!$J$7:$J$5000)) -> 0 | G14: =IF(B14="","",SUMIF('📈 Datos Completos'!$C$7:$C$5000, B14, '📈 Datos Completos'!$K$7:$K$5000)) -> 0 | H14: =IF(B14="","",SUMIF('📈 Datos Completos'!$C$7:$C$5000, B14, '📈 Datos Completos'!$L$7:$L$5000)) -> 0 | I14: =IF(B14="","",SUMIF('📈 Datos Completos'!$C$7:$C$5000, B14, '📈 Datos Completos'!$M$7:$M$5000)) -> 0 | J14: =IF(B14="","",SUMIF('📈 Datos Completos'!$C$7:$C$5000, B14, '📈 Datos Completos'!$N$7:$N$5000)) -> 0 | K14: =IF(B14="","",SUMIF('📈 Datos Completos'!$C$7:$C$5000, B14, '📈 Datos Completos'!$O$7:$O$5000)) -> 0 | L14: =IF(B14="","",IF(G14=0, 0, K14/G14)) -> 0
B15: =IFERROR(INDEX('📦 Precios Proforma'!$B$5:$B$104, 11), "") -> 12 Pack Pepsi 500 ML | C15: =IF(B15="","",SUMIF('📈 Datos Completos'!$C$7:$C$5000, B15, '📈 Datos Completos'!$E$7:$E$5000)) -> 48 | D15: =IF(B15="","",SUMIF('📈 Datos Completos'!$C$7:$C$5000, B15, '📈 Datos Completos'!$H$7:$H$5000)) -> 624 | E15: =IF(B15="","",SUMIF('📈 Datos Completos'!$C$7:$C$5000, B15, '📈 Datos Completos'!$I$7:$I$5000)) -> 216.96 | F15: =IF(B15="","",SUMIF('📈 Datos Completos'!$C$7:$C$5000, B15, '📈 Datos Completos'!$J$7:$J$5000)) -> 630.24 | G15: =IF(B15="","",SUMIF('📈 Datos Completos'!$C$7:$C$5000, B15, '📈 Datos Completos'!$K$7:$K$5000)) -> 847.2 | H15: =IF(B15="","",SUMIF('📈 Datos Completos'!$C$7:$C$5000, B15, '📈 Datos Completos'!$L$7:$L$5000)) -> 1087.3099 | I15: =IF(B15="","",SUMIF('📈 Datos Completos'!$C$7:$C$5000, B15, '📈 Datos Completos'!$M$7:$M$5000)) -> 56.16 | J15: =IF(B15="","",SUMIF('📈 Datos Completos'!$C$7:$C$5000, B15, '📈 Datos Completos'!$N$7:$N$5000)) -> 1143.4699 | K15: =IF(B15="","",SUMIF('📈 Datos Completos'!$C$7:$C$5000, B15, '📈 Datos Completos'!$O$7:$O$5000)) -> -296.26994 | L15: =IF(B15="","",IF(G15=0, 0, K15/G15)) -> -0.34970484
B16: =IFERROR(INDEX('📦 Precios Proforma'!$B$5:$B$104, 12), "") -> 12 Pack Soda Ensa 500 ML | C16: =IF(B16="","",SUMIF('📈 Datos Completos'!$C$7:$C$5000, B16, '📈 Datos Completos'!$E$7:$E$5000)) -> 640 | D16: =IF(B16="","",SUMIF('📈 Datos Completos'!$C$7:$C$5000, B16, '📈 Datos Completos'!$H$7:$H$5000)) -> 6862 | E16: =IF(B16="","",SUMIF('📈 Datos Completos'!$C$7:$C$5000, B16, '📈 Datos Completos'!$I$7:$I$5000)) -> 3421.3 | F16: =IF(B16="","",SUMIF('📈 Datos Completos'!$C$7:$C$5000, B16, '📈 Datos Completos'!$J$7:$J$5000)) -> 8471.5 | G16: =IF(B16="","",SUMIF('📈 Datos Completos'!$C$7:$C$5000, B16, '📈 Datos Completos'!$K$7:$K$5000)) -> 11892.8 | H16: =IF(B16="","",SUMIF('📈 Datos Completos'!$C$7:$C$5000, B16, '📈 Datos Completos'!$L$7:$L$5000)) -> 6653.76 | I16: =IF(B16="","",SUMIF('📈 Datos Completos'!$C$7:$C$5000, B16, '📈 Datos Completos'!$M$7:$M$5000)) -> 617.58 | J16: =IF(B16="","",SUMIF('📈 Datos Completos'!$C$7:$C$5000, B16, '📈 Datos Completos'!$N$7:$N$5000)) -> 7271.34 | K16: =IF(B16="","",SUMIF('📈 Datos Completos'!$C$7:$C$5000, B16, '📈 Datos Completos'!$O$7:$O$5000)) -> 4621.46 | L16: =IF(B16="","",IF(G16=0, 0, K16/G16)) -> 0.3885931
B17: =IFERROR(INDEX('📦 Precios Proforma'!$B$5:$B$104, 13), "") -> 16 Pack Adrenaline 12 oz | C17: =IF(B17="","",SUMIF('📈 Datos Completos'!$C$7:$C$5000, B17, '📈 Datos Completos'!$E$7:$E$5000)) -> 0 | D17: =IF(B17="","",SUMIF('📈 Datos Completos'!$C$7:$C$5000, B17, '📈 Datos Completos'!$H$7:$H$5000)) -> 0 | E17: =IF(B17="","",SUMIF('📈 Datos Completos'!$C$7:$C$5000, B17, '📈 Datos Completos'!$I$7:$I$5000)) -> 0 | F17: =IF(B17="","",SUMIF('📈 Datos Completos'!$C$7:$C$5000, B17, '📈 Datos Completos'!$J$7:$J$5000)) -> 0 | G17: =IF(B17="","",SUMIF('📈 Datos Completos'!$C$7:$C$5000, B17, '📈 Datos Completos'!$K$7:$K$5000)) -> 0 | H17: =IF(B17="","",SUMIF('📈 Datos Completos'!$C$7:$C$5000, B17, '📈 Datos Completos'!$L$7:$L$5000)) -> 0 | I17: =IF(B17="","",SUMIF('📈 Datos Completos'!$C$7:$C$5000, B17, '📈 Datos Completos'!$M$7:$M$5000)) -> 0 | J17: =IF(B17="","",SUMIF('📈 Datos Completos'!$C$7:$C$5000, B17, '📈 Datos Completos'!$N$7:$N$5000)) -> 0 | K17: =IF(B17="","",SUMIF('📈 Datos Completos'!$C$7:$C$5000, B17, '📈 Datos Completos'!$O$7:$O$5000)) -> 0 | L17: =IF(B17="","",IF(G17=0, 0, K17/G17)) -> 0
B18: =IFERROR(INDEX('📦 Precios Proforma'!$B$5:$B$104, 14), "") -> 18 Pack 500 ml (pepsi,rojita) | C18: =IF(B18="","",SUMIF('📈 Datos Completos'!$C$7:$C$5000, B18, '📈 Datos Completos'!$E$7:$E$5000)) -> 680 | D18: =IF(B18="","",SUMIF('📈 Datos Completos'!$C$7:$C$5000, B18, '📈 Datos Completos'!$H$7:$H$5000)) -> 680 | E18: =IF(B18="","",SUMIF('📈 Datos Completos'!$C$7:$C$5000, B18, '📈 Datos Completos'!$I$7:$I$5000)) -> 4703.6 | F18: =IF(B18="","",SUMIF('📈 Datos Completos'!$C$7:$C$5000, B18, '📈 Datos Completos'!$J$7:$J$5000)) -> 768.4 | G18: =IF(B18="","",SUMIF('📈 Datos Completos'!$C$7:$C$5000, B18, '📈 Datos Completos'!$K$7:$K$5000)) -> 5472 | H18: =IF(B18="","",SUMIF('📈 Datos Completos'!$C$7:$C$5000, B18, '📈 Datos Completos'!$L$7:$L$5000)) -> 8685.5261 | I18: =IF(B18="","",SUMIF('📈 Datos Completos'!$C$7:$C$5000, B18, '📈 Datos Completos'!$M$7:$M$5000)) -> 61.2 | J18: =IF(B18="","",SUMIF('📈 Datos Completos'!$C$7:$C$5000, B18, '📈 Datos Completos'!$N$7:$N$5000)) -> 8746.7261 | K18: =IF(B18="","",SUMIF('📈 Datos Completos'!$C$7:$C$5000, B18, '📈 Datos Completos'!$O$7:$O$5000)) -> -3274.7261 | L18: =IF(B18="","",IF(G18=0, 0, K18/G18)) -> -0.59845141
B19: =IFERROR(INDEX('📦 Precios Proforma'!$B$5:$B$104, 15), "") -> 18 PACK 500 ML PET SURTIDO | C19: =IF(B19="","",SUMIF('📈 Datos Completos'!$C$7:$C$5000, B19, '📈 Datos Completos'!$E$7:$E$5000)) -> 0 | D19: =IF(B19="","",SUMIF('📈 Datos Completos'!$C$7:$C$5000, B19, '📈 Datos Completos'!$H$7:$H$5000)) -> 0 | E19: =IF(B19="","",SUMIF('📈 Datos Completos'!$C$7:$C$5000, B19, '📈 Datos Completos'!$I$7:$I$5000)) -> 0 | F19: =IF(B19="","",SUMIF('📈 Datos Completos'!$C$7:$C$5000, B19, '📈 Datos Completos'!$J$7:$J$5000)) -> 0 | G19: =IF(B19="","",SUMIF('📈 Datos Completos'!$C$7:$C$5000, B19, '📈 Datos Completos'!$K$7:$K$5000)) -> 0 | H19: =IF(B19="","",SUMIF('📈 Datos Completos'!$C$7:$C$5000, B19, '📈 Datos Completos'!$L$7:$L$5000)) -> 0 | I19: =IF(B19="","",SUMIF('📈 Datos Completos'!$C$7:$C$5000, B19, '📈 Datos Completos'!$M$7:$M$5000)) -> 0 | J19: =IF(B19="","",SUMIF('📈 Datos Completos'!$C$7:$C$5000, B19, '📈 Datos Completos'!$N$7:$N$5000)) -> 0 | K19: =IF(B19="","",SUMIF('📈 Datos Completos'!$C$7:$C$5000, B19, '📈 Datos Completos'!$O$7:$O$5000)) -> 0 | L19: =IF(B19="","",IF(G19=0, 0, K19/G19)) -> 0
B20: =IFERROR(INDEX('📦 Precios Proforma'!$B$5:$B$104, 16), "") -> 18 Pack Be Light Surtido | C20: =IF(B20="","",SUMIF('📈 Datos Completos'!$C$7:$C$5000, B20, '📈 Datos Completos'!$E$7:$E$5000)) -> 240 | D20: =IF(B20="","",SUMIF('📈 Datos Completos'!$C$7:$C$5000, B20, '📈 Datos Completos'!$H$7:$H$5000)) -> 240 | E20: =IF(B20="","",SUMIF('📈 Datos Completos'!$C$7:$C$5000, B20, '📈 Datos Completos'!$I$7:$I$5000)) -> 1485.6 | F20: =IF(B20="","",SUMIF('📈 Datos Completos'!$C$7:$C$5000, B20, '📈 Datos Completos'!$J$7:$J$5000)) -> 242.4 | G20: =IF(B20="","",SUMIF('📈 Datos Completos'!$C$7:$C$5000, B20, '📈 Datos Completos'!$K$7:$K$5000)) -> 1728 | H20: =IF(B20="","",SUMIF('📈 Datos Completos'!$C$7:$C$5000, B20, '📈 Datos Completos'!$L$7:$L$5000)) -> 2031.2185 | I20: =IF(B20="","",SUMIF('📈 Datos Completos'!$C$7:$C$5000, B20, '📈 Datos Completos'!$M$7:$M$5000)) -> 21.6 | J20: =IF(B20="","",SUMIF('📈 Datos Completos'!$C$7:$C$5000, B20, '📈 Datos Completos'!$N$7:$N$5000)) -> 2052.8185 | K20: =IF(B20="","",SUMIF('📈 Datos Completos'!$C$7:$C$5000, B20, '📈 Datos Completos'!$O$7:$O$5000)) -> -324.81849 | L20: =IF(B20="","",IF(G20=0, 0, K20/G20)) -> -0.18797366
B21: =IFERROR(INDEX('📦 Precios Proforma'!$B$5:$B$104, 17), "") -> 18 Pack Pepsi + Roja 500 ML | C21: =IF(B21="","",SUMIF('📈 Datos Completos'!$C$7:$C$5000, B21, '📈 Datos Completos'!$E$7:$E$5000)) -> 1080 | D21: =IF(B21="","",SUMIF('📈 Datos Completos'!$C$7:$C$5000, B21, '📈 Datos Completos'!$H$7:$H$5000)) -> 1080 | E21: =IF(B21="","",SUMIF('📈 Datos Completos'!$C$7:$C$5000, B21, '📈 Datos Completos'!$I$7:$I$5000)) -> 7303.2 | F21: =IF(B21="","",SUMIF('📈 Datos Completos'!$C$7:$C$5000, B21, '📈 Datos Completos'!$J$7:$J$5000)) -> 1192.8 | G21: =IF(B21="","",SUMIF('📈 Datos Completos'!$C$7:$C$5000, B21, '📈 Datos Completos'!$K$7:$K$5000)) -> 8496 | H21: =IF(B21="","",SUMIF('📈 Datos Completos'!$C$7:$C$5000, B21, '📈 Datos Completos'!$L$7:$L$5000)) -> 19126.251 | I21: =IF(B21="","",SUMIF('📈 Datos Completos'!$C$7:$C$5000, B21, '📈 Datos Completos'!$M$7:$M$5000)) -> 97.2 | J21: =IF(B21="","",SUMIF('📈 Datos Completos'!$C$7:$C$5000, B21, '📈 Datos Completos'!$N$7:$N$5000)) -> 19223.451 | K21: =IF(B21="","",SUMIF('📈 Datos Completos'!$C$7:$C$5000, B21, '📈 Datos Completos'!$O$7:$O$5000)) -> -10727.451 | L21: =IF(B21="","",IF(G21=0, 0, K21/G21)) -> -1.2626472
B22: =IFERROR(INDEX('📦 Precios Proforma'!$B$5:$B$104, 18), "") -> 2 Pack Pepsi + Ensa Toronja 3 Lts | C22: =IF(B22="","",SUMIF('📈 Datos Completos'!$C$7:$C$5000, B22, '📈 Datos Completos'!$E$7:$E$5000)) -> 0 | D22: =IF(B22="","",SUMIF('📈 Datos Completos'!$C$7:$C$5000, B22, '📈 Datos Completos'!$H$7:$H$5000)) -> 0 | E22: =IF(B22="","",SUMIF('📈 Datos Completos'!$C$7:$C$5000, B22, '📈 Datos Completos'!$I$7:$I$5000)) -> 0 | F22: =IF(B22="","",SUMIF('📈 Datos Completos'!$C$7:$C$5000, B22, '📈 Datos Completos'!$J$7:$J$5000)) -> 0 | G22: =IF(B22="","",SUMIF('📈 Datos Completos'!$C$7:$C$5000, B22, '📈 Datos Completos'!$K$7:$K$5000)) -> 0 | H22: =IF(B22="","",SUMIF('📈 Datos Completos'!$C$7:$C$5000, B22, '📈 Datos Completos'!$L$7:$L$5000)) -> 0 | I22: =IF(B22="","",SUMIF('📈 Datos Completos'!$C$7:$C$5000, B22, '📈 Datos Completos'!$M$7:$M$5000)) -> 0 | J22: =IF(B22="","",SUMIF('📈 Datos Completos'!$C$7:$C$5000, B22, '📈 Datos Completos'!$N$7:$N$5000)) -> 0 | K22: =IF(B22="","",SUMIF('📈 Datos Completos'!$C$7:$C$5000, B22, '📈 Datos Completos'!$O$7:$O$5000)) -> 0 | L22: =IF(B22="","",IF(G22=0, 0, K22/G22)) -> 0
B23: =IFERROR(INDEX('📦 Precios Proforma'!$B$5:$B$104, 19), "") -> 2 Pack Pepsi + Mirinda 3 Litro | C23: =IF(B23="","",SUMIF('📈 Datos Completos'!$C$7:$C$5000, B23, '📈 Datos Completos'!$E$7:$E$5000)) -> 54 | D23: =IF(B23="","",SUMIF('📈 Datos Completos'!$C$7:$C$5000, B23, '📈 Datos Completos'!$H$7:$H$5000)) -> 162 | E23: =IF(B23="","",SUMIF('📈 Datos Completos'!$C$7:$C$5000, B23, '📈 Datos Completos'!$I$7:$I$5000)) -> 293.91 | F23: =IF(B23="","",SUMIF('📈 Datos Completos'!$C$7:$C$5000, B23, '📈 Datos Completos'!$J$7:$J$5000)) -> 197.28 | G23: =IF(B23="","",SUMIF('📈 Datos Completos'!$C$7:$C$5000, B23, '📈 Datos Completos'!$K$7:$K$5000)) -> 491.19 | H23: =IF(B23="","",SUMIF('📈 Datos Completos'!$C$7:$C$5000, B23, '📈 Datos Completos'!$L$7:$L$5000)) -> 4013.9886 | I23: =IF(B23="","",SUMIF('📈 Datos Completos'!$C$7:$C$5000, B23, '📈 Datos Completos'!$M$7:$M$5000)) -> 14.58 | J23: =IF(B23="","",SUMIF('📈 Datos Completos'!$C$7:$C$5000, B23, '📈 Datos Completos'!$N$7:$N$5000)) -> 4028.5686 | K23: =IF(B23="","",SUMIF('📈 Datos Completos'!$C$7:$C$5000, B23, '📈 Datos Completos'!$O$7:$O$5000)) -> -3253.8786 | L23: =IF(B23="","",IF(G23=0, 0, K23/G23)) -> -6.6244806
B24: =IFERROR(INDEX('📦 Precios Proforma'!$B$5:$B$104, 20), "") -> 2 Pack Pepsi + Mirinda 3 lts | C24: =IF(B24="","",SUMIF('📈 Datos Completos'!$C$7:$C$5000, B24, '📈 Datos Completos'!$E$7:$E$5000)) -> 0 | D24: =IF(B24="","",SUMIF('📈 Datos Completos'!$C$7:$C$5000, B24, '📈 Datos Completos'!$H$7:$H$5000)) -> 0 | E24: =IF(B24="","",SUMIF('📈 Datos Completos'!$C$7:$C$5000, B24, '📈 Datos Completos'!$I$7:$I$5000)) -> 0 | F24: =IF(B24="","",SUMIF('📈 Datos Completos'!$C$7:$C$5000, B24, '📈 Datos Completos'!$J$7:$J$5000)) -> 0 | G24: =IF(B24="","",SUMIF('📈 Datos Completos'!$C$7:$C$5000, B24, '📈 Datos Completos'!$K$7:$K$5000)) -> 0 | H24: =IF(B24="","",SUMIF('📈 Datos Completos'!$C$7:$C$5000, B24, '📈 Datos Completos'!$L$7:$L$5000)) -> 0 | I24: =IF(B24="","",SUMIF('📈 Datos Completos'!$C$7:$C$5000, B24, '📈 Datos Completos'!$M$7:$M$5000)) -> 0 | J24: =IF(B24="","",SUMIF('📈 Datos Completos'!$C$7:$C$5000, B24, '📈 Datos Completos'!$N$7:$N$5000)) -> 0 | K24: =IF(B24="","",SUMIF('📈 Datos Completos'!$C$7:$C$5000, B24, '📈 Datos Completos'!$O$7:$O$5000)) -> 0 | L24: =IF(B24="","",IF(G24=0, 0, K24/G24)) -> 0
B25: =IFERROR(INDEX('📦 Precios Proforma'!$B$5:$B$104, 21), "") -> 2 Pack Pepsi + Roja 3 Litro | C25: =IF(B25="","",SUMIF('📈 Datos Completos'!$C$7:$C$5000, B25, '📈 Datos Completos'!$E$7:$E$5000)) -> 14919 | D25: =IF(B25="","",SUMIF('📈 Datos Completos'!$C$7:$C$5000, B25, '📈 Datos Completos'!$H$7:$H$5000)) -> 44487 | E25: =IF(B25="","",SUMIF('📈 Datos Completos'!$C$7:$C$5000, B25, '📈 Datos Completos'!$I$7:$I$5000)) -> 82154.87 | F25: =IF(B25="","",SUMIF('📈 Datos Completos'!$C$7:$C$5000, B25, '📈 Datos Completos'!$J$7:$J$5000)) -> 54784.05 | G25: =IF(B25="","",SUMIF('📈 Datos Completos'!$C$7:$C$5000, B25, '📈 Datos Completos'!$K$7:$K$5000)) -> 136938.92 | H25: =IF(B25="","",SUMIF('📈 Datos Completos'!$C$7:$C$5000, B25, '📈 Datos Completos'!$L$7:$L$5000)) -> 73531.921 | I25: =IF(B25="","",SUMIF('📈 Datos Completos'!$C$7:$C$5000, B25, '📈 Datos Completos'!$M$7:$M$5000)) -> 4003.83 | J25: =IF(B25="","",SUMIF('📈 Datos Completos'!$C$7:$C$5000, B25, '📈 Datos Completos'!$N$7:$N$5000)) -> 77535.751 | K25: =IF(B25="","",SUMIF('📈 Datos Completos'!$C$7:$C$5000, B25, '📈 Datos Completos'!$O$7:$O$5000)) -> 59653.316 | L25: =IF(B25="","",IF(G25=0, 0, K25/G25)) -> 0.43561988
B26: =IFERROR(INDEX('📦 Precios Proforma'!$B$5:$B$104, 22), "") -> 2 Pack Pepsi + Rojita 3 Lts | C26: =IF(B26="","",SUMIF('📈 Datos Completos'!$C$7:$C$5000, B26, '📈 Datos Completos'!$E$7:$E$5000)) -> 1788 | D26: =IF(B26="","",SUMIF('📈 Datos Completos'!$C$7:$C$5000, B26, '📈 Datos Completos'!$H$7:$H$5000)) -> 5364 | E26: =IF(B26="","",SUMIF('📈 Datos Completos'!$C$7:$C$5000, B26, '📈 Datos Completos'!$I$7:$I$5000)) -> 9508.71 | F26: =IF(B26="","",SUMIF('📈 Datos Completos'!$C$7:$C$5000, B26, '📈 Datos Completos'!$J$7:$J$5000)) -> 6381.54 | G26: =IF(B26="","",SUMIF('📈 Datos Completos'!$C$7:$C$5000, B26, '📈 Datos Completos'!$K$7:$K$5000)) -> 15890.25 | H26: =IF(B26="","",SUMIF('📈 Datos Completos'!$C$7:$C$5000, B26, '📈 Datos Completos'!$L$7:$L$5000)) -> 10597.592 | I26: =IF(B26="","",SUMIF('📈 Datos Completos'!$C$7:$C$5000, B26, '📈 Datos Completos'!$M$7:$M$5000)) -> 482.76 | J26: =IF(B26="","",SUMIF('📈 Datos Completos'!$C$7:$C$5000, B26, '📈 Datos Completos'!$N$7:$N$5000)) -> 11080.352 | K26: =IF(B26="","",SUMIF('📈 Datos Completos'!$C$7:$C$5000, B26, '📈 Datos Completos'!$O$7:$O$5000)) -> 4809.8976 | L26: =IF(B26="","",IF(G26=0, 0, K26/G26)) -> 0.3026949
B27: =IFERROR(INDEX('📦 Precios Proforma'!$B$5:$B$104, 23), "") -> 2 Pack Pepsi + Toronja 3 Litro | C27: =IF(B27="","",SUMIF('📈 Datos Completos'!$C$7:$C$5000, B27, '📈 Datos Completos'!$E$7:$E$5000)) -> 1620 | D27: =IF(B27="","",SUMIF('📈 Datos Completos'!$C$7:$C$5000, B27, '📈 Datos Completos'!$H$7:$H$5000)) -> 4860 | E27: =IF(B27="","",SUMIF('📈 Datos Completos'!$C$7:$C$5000, B27, '📈 Datos Completos'!$I$7:$I$5000)) -> 8137.8 | F27: =IF(B27="","",SUMIF('📈 Datos Completos'!$C$7:$C$5000, B27, '📈 Datos Completos'!$J$7:$J$5000)) -> 5459.4 | G27: =IF(B27="","",SUMIF('📈 Datos Completos'!$C$7:$C$5000, B27, '📈 Datos Completos'!$K$7:$K$5000)) -> 13597.2 | H27: =IF(B27="","",SUMIF('📈 Datos Completos'!$C$7:$C$5000, B27, '📈 Datos Completos'!$L$7:$L$5000)) -> 16092.429 | I27: =IF(B27="","",SUMIF('📈 Datos Completos'!$C$7:$C$5000, B27, '📈 Datos Completos'!$M$7:$M$5000)) -> 437.4 | J27: =IF(B27="","",SUMIF('📈 Datos Completos'!$C$7:$C$5000, B27, '📈 Datos Completos'!$N$7:$N$5000)) -> 16529.829 | K27: =IF(B27="","",SUMIF('📈 Datos Completos'!$C$7:$C$5000, B27, '📈 Datos Completos'!$O$7:$O$5000)) -> -2932.6286 | L27: =IF(B27="","",IF(G27=0, 0, K27/G27)) -> -0.21567886
B28: =IFERROR(INDEX('📦 Precios Proforma'!$B$5:$B$104, 24), "") -> 24 Pack Gatorade Surtido | C28: =IF(B28="","",SUMIF('📈 Datos Completos'!$C$7:$C$5000, B28, '📈 Datos Completos'!$E$7:$E$5000)) -> 2570 | D28: =IF(B28="","",SUMIF('📈 Datos Completos'!$C$7:$C$5000, B28, '📈 Datos Completos'!$H$7:$H$5000)) -> 2570 | E28: =IF(B28="","",SUMIF('📈 Datos Completos'!$C$7:$C$5000, B28, '📈 Datos Completos'!$I$7:$I$5000)) -> 17556.3 | F28: =IF(B28="","",SUMIF('📈 Datos Completos'!$C$7:$C$5000, B28, '📈 Datos Completos'!$J$7:$J$5000)) -> 2867.7 | G28: =IF(B28="","",SUMIF('📈 Datos Completos'!$C$7:$C$5000, B28, '📈 Datos Completos'!$K$7:$K$5000)) -> 20424 | H28: =IF(B28="","",SUMIF('📈 Datos Completos'!$C$7:$C$5000, B28, '📈 Datos Completos'!$L$7:$L$5000)) -> 15901.717 | I28: =IF(B28="","",SUMIF('📈 Datos Completos'!$C$7:$C$5000, B28, '📈 Datos Completos'!$M$7:$M$5000)) -> 231.3 | J28: =IF(B28="","",SUMIF('📈 Datos Completos'!$C$7:$C$5000, B28, '📈 Datos Completos'!$N$7:$N$5000)) -> 16133.017 | K28: =IF(B28="","",SUMIF('📈 Datos Completos'!$C$7:$C$5000, B28, '📈 Datos Completos'!$O$7:$O$5000)) -> 4290.9832 | L28: =IF(B28="","",IF(G28=0, 0, K28/G28)) -> 0.21009514
B29: =IFERROR(INDEX('📦 Precios Proforma'!$B$5:$B$104, 25), "") -> 24 PACK GATORADE SURTIDO 500ML | C29: =IF(B29="","",SUMIF('📈 Datos Completos'!$C$7:$C$5000, B29, '📈 Datos Completos'!$E$7:$E$5000)) -> 0 | D29: =IF(B29="","",SUMIF('📈 Datos Completos'!$C$7:$C$5000, B29, '📈 Datos Completos'!$H$7:$H$5000)) -> 0 | E29: =IF(B29="","",SUMIF('📈 Datos Completos'!$C$7:$C$5000, B29, '📈 Datos Completos'!$I$7:$I$5000)) -> 0 | F29: =IF(B29="","",SUMIF('📈 Datos Completos'!$C$7:$C$5000, B29, '📈 Datos Completos'!$J$7:$J$5000)) -> 0 | G29: =IF(B29="","",SUMIF('📈 Datos Completos'!$C$7:$C$5000, B29, '📈 Datos Completos'!$K$7:$K$5000)) -> 0 | H29: =IF(B29="","",SUMIF('📈 Datos Completos'!$C$7:$C$5000, B29, '📈 Datos Completos'!$L$7:$L$5000)) -> 0 | I29: =IF(B29="","",SUMIF('📈 Datos Completos'!$C$7:$C$5000, B29, '📈 Datos Completos'!$M$7:$M$5000)) -> 0 | J29: =IF(B29="","",SUMIF('📈 Datos Completos'!$C$7:$C$5000, B29, '📈 Datos Completos'!$N$7:$N$5000)) -> 0 | K29: =IF(B29="","",SUMIF('📈 Datos Completos'!$C$7:$C$5000, B29, '📈 Datos Completos'!$O$7:$O$5000)) -> 0 | L29: =IF(B29="","",IF(G29=0, 0, K29/G29)) -> 0
B30: =IFERROR(INDEX('📦 Precios Proforma'!$B$5:$B$104, 26), "") -> 24 Pack Gatorade Surtido 600 ML | C30: =IF(B30="","",SUMIF('📈 Datos Completos'!$C$7:$C$5000, B30, '📈 Datos Completos'!$E$7:$E$5000)) -> 720 | D30: =IF(B30="","",SUMIF('📈 Datos Completos'!$C$7:$C$5000, B30, '📈 Datos Completos'!$H$7:$H$5000)) -> 720 | E30: =IF(B30="","",SUMIF('📈 Datos Completos'!$C$7:$C$5000, B30, '📈 Datos Completos'!$I$7:$I$5000)) -> 5445.6 | F30: =IF(B30="","",SUMIF('📈 Datos Completos'!$C$7:$C$5000, B30, '📈 Datos Completos'!$J$7:$J$5000)) -> 890.4 | G30: =IF(B30="","",SUMIF('📈 Datos Completos'!$C$7:$C$5000, B30, '📈 Datos Completos'!$K$7:$K$5000)) -> 6336 | H30: =IF(B30="","",SUMIF('📈 Datos Completos'!$C$7:$C$5000, B30, '📈 Datos Completos'!$L$7:$L$5000)) -> 6320.1742 | I30: =IF(B30="","",SUMIF('📈 Datos Completos'!$C$7:$C$5000, B30, '📈 Datos Completos'!$M$7:$M$5000)) -> 64.8 | J30: =IF(B30="","",SUMIF('📈 Datos Completos'!$C$7:$C$5000, B30, '📈 Datos Completos'!$N$7:$N$5000)) -> 6384.9742 | K30: =IF(B30="","",SUMIF('📈 Datos Completos'!$C$7:$C$5000, B30, '📈 Datos Completos'!$O$7:$O$5000)) -> -48.974161 | L30: =IF(B30="","",IF(G30=0, 0, K30/G30)) -> -0.0077295078
B31: =IFERROR(INDEX('📦 Precios Proforma'!$B$5:$B$104, 27), "") -> 24 PACK PEPSI BLACK + SABORES 355ML LATA | C31: =IF(B31="","",SUMIF('📈 Datos Completos'!$C$7:$C$5000, B31, '📈 Datos Completos'!$E$7:$E$5000)) -> 0 | D31: =IF(B31="","",SUMIF('📈 Datos Completos'!$C$7:$C$5000, B31, '📈 Datos Completos'!$H$7:$H$5000)) -> 0 | E31: =IF(B31="","",SUMIF('📈 Datos Completos'!$C$7:$C$5000, B31, '📈 Datos Completos'!$I$7:$I$5000)) -> 0 | F31: =IF(B31="","",SUMIF('📈 Datos Completos'!$C$7:$C$5000, B31, '📈 Datos Completos'!$J$7:$J$5000)) -> 0 | G31: =IF(B31="","",SUMIF('📈 Datos Completos'!$C$7:$C$5000, B31, '📈 Datos Completos'!$K$7:$K$5000)) -> 0 | H31: =IF(B31="","",SUMIF('📈 Datos Completos'!$C$7:$C$5000, B31, '📈 Datos Completos'!$L$7:$L$5000)) -> 0 | I31: =IF(B31="","",SUMIF('📈 Datos Completos'!$C$7:$C$5000, B31, '📈 Datos Completos'!$M$7:$M$5000)) -> 0 | J31: =IF(B31="","",SUMIF('📈 Datos Completos'!$C$7:$C$5000, B31, '📈 Datos Completos'!$N$7:$N$5000)) -> 0 | K31: =IF(B31="","",SUMIF('📈 Datos Completos'!$C$7:$C$5000, B31, '📈 Datos Completos'!$O$7:$O$5000)) -> 0 | L31: =IF(B31="","",IF(G31=0, 0, K31/G31)) -> 0
B32: =IFERROR(INDEX('📦 Precios Proforma'!$B$5:$B$104, 28), "") -> 24 Pack pepsi Black lata | C32: =IF(B32="","",SUMIF('📈 Datos Completos'!$C$7:$C$5000, B32, '📈 Datos Completos'!$E$7:$E$5000)) -> 0 | D32: =IF(B32="","",SUMIF('📈 Datos Completos'!$C$7:$C$5000, B32, '📈 Datos Completos'!$H$7:$H$5000)) -> 0 | E32: =IF(B32="","",SUMIF('📈 Datos Completos'!$C$7:$C$5000, B32, '📈 Datos Completos'!$I$7:$I$5000)) -> 0 | F32: =IF(B32="","",SUMIF('📈 Datos Completos'!$C$7:$C$5000, B32, '📈 Datos Completos'!$J$7:$J$5000)) -> 0 | G32: =IF(B32="","",SUMIF('📈 Datos Completos'!$C$7:$C$5000, B32, '📈 Datos Completos'!$K$7:$K$5000)) -> 0 | H32: =IF(B32="","",SUMIF('📈 Datos Completos'!$C$7:$C$5000, B32, '📈 Datos Completos'!$L$7:$L$5000)) -> 0 | I32: =IF(B32="","",SUMIF('📈 Datos Completos'!$C$7:$C$5000, B32, '📈 Datos Completos'!$M$7:$M$5000)) -> 0 | J32: =IF(B32="","",SUMIF('📈 Datos Completos'!$C$7:$C$5000, B32, '📈 Datos Completos'!$N$7:$N$5000)) -> 0 | K32: =IF(B32="","",SUMIF('📈 Datos Completos'!$C$7:$C$5000, B32, '📈 Datos Completos'!$O$7:$O$5000)) -> 0 | L32: =IF(B32="","",IF(G32=0, 0, K32/G32)) -> 0
B33: =IFERROR(INDEX('📦 Precios Proforma'!$B$5:$B$104, 29), "") -> 24 Pack Soda Ensa Lata | C33: =IF(B33="","",SUMIF('📈 Datos Completos'!$C$7:$C$5000, B33, '📈 Datos Completos'!$E$7:$E$5000)) -> 0 | D33: =IF(B33="","",SUMIF('📈 Datos Completos'!$C$7:$C$5000, B33, '📈 Datos Completos'!$H$7:$H$5000)) -> 0 | E33: =IF(B33="","",SUMIF('📈 Datos Completos'!$C$7:$C$5000, B33, '📈 Datos Completos'!$I$7:$I$5000)) -> 0 | F33: =IF(B33="","",SUMIF('📈 Datos Completos'!$C$7:$C$5000, B33, '📈 Datos Completos'!$J$7:$J$5000)) -> 0 | G33: =IF(B33="","",SUMIF('📈 Datos Completos'!$C$7:$C$5000, B33, '📈 Datos Completos'!$K$7:$K$5000)) -> 0 | H33: =IF(B33="","",SUMIF('📈 Datos Completos'!$C$7:$C$5000, B33, '📈 Datos Completos'!$L$7:$L$5000)) -> 0 | I33: =IF(B33="","",SUMIF('📈 Datos Completos'!$C$7:$C$5000, B33, '📈 Datos Completos'!$M$7:$M$5000)) -> 0 | J33: =IF(B33="","",SUMIF('📈 Datos Completos'!$C$7:$C$5000, B33, '📈 Datos Completos'!$N$7:$N$5000)) -> 0 | K33: =IF(B33="","",SUMIF('📈 Datos Completos'!$C$7:$C$5000, B33, '📈 Datos Completos'!$O$7:$O$5000)) -> 0 | L33: =IF(B33="","",IF(G33=0, 0, K33/G33)) -> 0
B34: =IFERROR(INDEX('📦 Precios Proforma'!$B$5:$B$104, 30), "") -> 3 Pack Pepsi + Ensa Toronja 3 Lts | C34: =IF(B34="","",SUMIF('📈 Datos Completos'!$C$7:$C$5000, B34, '📈 Datos Completos'!$E$7:$E$5000)) -> 0 | D34: =IF(B34="","",SUMIF('📈 Datos Completos'!$C$7:$C$5000, B34, '📈 Datos Completos'!$H$7:$H$5000)) -> 0 | E34: =IF(B34="","",SUMIF('📈 Datos Completos'!$C$7:$C$5000, B34, '📈 Datos Completos'!$I$7:$I$5000)) -> 0 | F34: =IF(B34="","",SUMIF('📈 Datos Completos'!$C$7:$C$5000, B34, '📈 Datos Completos'!$J$7:$J$5000)) -> 0 | G34: =IF(B34="","",SUMIF('📈 Datos Completos'!$C$7:$C$5000, B34, '📈 Datos Completos'!$K$7:$K$5000)) -> 0 | H34: =IF(B34="","",SUMIF('📈 Datos Completos'!$C$7:$C$5000, B34, '📈 Datos Completos'!$L$7:$L$5000)) -> 0 | I34: =IF(B34="","",SUMIF('📈 Datos Completos'!$C$7:$C$5000, B34, '📈 Datos Completos'!$M$7:$M$5000)) -> 0 | J34: =IF(B34="","",SUMIF('📈 Datos Completos'!$C$7:$C$5000, B34, '📈 Datos Completos'!$N$7:$N$5000)) -> 0 | K34: =IF(B34="","",SUMIF('📈 Datos Completos'!$C$7:$C$5000, B34, '📈 Datos Completos'!$O$7:$O$5000)) -> 0 | L34: =IF(B34="","",IF(G34=0, 0, K34/G34)) -> 0
B35: =IFERROR(INDEX('📦 Precios Proforma'!$B$5:$B$104, 31), "") -> 3 Pack Pepsi + Roja + Campestre | C35: =IF(B35="","",SUMIF('📈 Datos Completos'!$C$7:$C$5000, B35, '📈 Datos Completos'!$E$7:$E$5000)) -> 6776 | D35: =IF(B35="","",SUMIF('📈 Datos Completos'!$C$7:$C$5000, B35, '📈 Datos Completos'!$H$7:$H$5000)) -> 27030 | E35: =IF(B35="","",SUMIF('📈 Datos Completos'!$C$7:$C$5000, B35, '📈 Datos Completos'!$I$7:$I$5000)) -> 32575.42 | F35: =IF(B35="","",SUMIF('📈 Datos Completos'!$C$7:$C$5000, B35, '📈 Datos Completos'!$J$7:$J$5000)) -> 29251.9 | G35: =IF(B35="","",SUMIF('📈 Datos Completos'!$C$7:$C$5000, B35, '📈 Datos Completos'!$K$7:$K$5000)) -> 61827.32 | H35: =IF(B35="","",SUMIF('📈 Datos Completos'!$C$7:$C$5000, B35, '📈 Datos Completos'!$L$7:$L$5000)) -> 36031.131 | I35: =IF(B35="","",SUMIF('📈 Datos Completos'!$C$7:$C$5000, B35, '📈 Datos Completos'!$M$7:$M$5000)) -> 2432.7 | J35: =IF(B35="","",SUMIF('📈 Datos Completos'!$C$7:$C$5000, B35, '📈 Datos Completos'!$N$7:$N$5000)) -> 38463.831 | K35: =IF(B35="","",SUMIF('📈 Datos Completos'!$C$7:$C$5000, B35, '📈 Datos Completos'!$O$7:$O$5000)) -> 28043.862 | L35: =IF(B35="","",IF(G35=0, 0, K35/G35)) -> 0.45358366
B36: =IFERROR(INDEX('📦 Precios Proforma'!$B$5:$B$104, 32), "") -> 3 Pack Pepsi + Roja + Campestre 3 Litro | C36: =IF(B36="","",SUMIF('📈 Datos Completos'!$C$7:$C$5000, B36, '📈 Datos Completos'!$E$7:$E$5000)) -> 1930 | D36: =IF(B36="","",SUMIF('📈 Datos Completos'!$C$7:$C$5000, B36, '📈 Datos Completos'!$H$7:$H$5000)) -> 7720 | E36: =IF(B36="","",SUMIF('📈 Datos Completos'!$C$7:$C$5000, B36, '📈 Datos Completos'!$I$7:$I$5000)) -> 9267.2 | F36: =IF(B36="","",SUMIF('📈 Datos Completos'!$C$7:$C$5000, B36, '📈 Datos Completos'!$J$7:$J$5000)) -> 8286.8 | G36: =IF(B36="","",SUMIF('📈 Datos Completos'!$C$7:$C$5000, B36, '📈 Datos Completos'!$K$7:$K$5000)) -> 17554 | H36: =IF(B36="","",SUMIF('📈 Datos Completos'!$C$7:$C$5000, B36, '📈 Datos Completos'!$L$7:$L$5000)) -> 9514.3562 | I36: =IF(B36="","",SUMIF('📈 Datos Completos'!$C$7:$C$5000, B36, '📈 Datos Completos'!$M$7:$M$5000)) -> 694.8 | J36: =IF(B36="","",SUMIF('📈 Datos Completos'!$C$7:$C$5000, B36, '📈 Datos Completos'!$N$7:$N$5000)) -> 10209.156 | K36: =IF(B36="","",SUMIF('📈 Datos Completos'!$C$7:$C$5000, B36, '📈 Datos Completos'!$O$7:$O$5000)) -> 7344.8438 | L36: =IF(B36="","",IF(G36=0, 0, K36/G36)) -> 0.41841425
B37: =IFERROR(INDEX('📦 Precios Proforma'!$B$5:$B$104, 33), "") -> 3 Pack Pepsi + Roja 3 Litro | C37: =IF(B37="","",SUMIF('📈 Datos Completos'!$C$7:$C$5000, B37, '📈 Datos Completos'!$E$7:$E$5000)) -> 0 | D37: =IF(B37="","",SUMIF('📈 Datos Completos'!$C$7:$C$5000, B37, '📈 Datos Completos'!$H$7:$H$5000)) -> 0 | E37: =IF(B37="","",SUMIF('📈 Datos Completos'!$C$7:$C$5000, B37, '📈 Datos Completos'!$I$7:$I$5000)) -> 0 | F37: =IF(B37="","",SUMIF('📈 Datos Completos'!$C$7:$C$5000, B37, '📈 Datos Completos'!$J$7:$J$5000)) -> 0 | G37: =IF(B37="","",SUMIF('📈 Datos Completos'!$C$7:$C$5000, B37, '📈 Datos Completos'!$K$7:$K$5000)) -> 0 | H37: =IF(B37="","",SUMIF('📈 Datos Completos'!$C$7:$C$5000, B37, '📈 Datos Completos'!$L$7:$L$5000)) -> 0 | I37: =IF(B37="","",SUMIF('📈 Datos Completos'!$C$7:$C$5000, B37, '📈 Datos Completos'!$M$7:$M$5000)) -> 0 | J37: =IF(B37="","",SUMIF('📈 Datos Completos'!$C$7:$C$5000, B37, '📈 Datos Completos'!$N$7:$N$5000)) -> 0 | K37: =IF(B37="","",SUMIF('📈 Datos Completos'!$C$7:$C$5000, B37, '📈 Datos Completos'!$O$7:$O$5000)) -> 0 | L37: =IF(B37="","",IF(G37=0, 0, K37/G37)) -> 0
B38: =IFERROR(INDEX('📦 Precios Proforma'!$B$5:$B$104, 34), "") -> 3 Pack Pepsi + Rojita + Toronja 3 Lts | C38: =IF(B38="","",SUMIF('📈 Datos Completos'!$C$7:$C$5000, B38, '📈 Datos Completos'!$E$7:$E$5000)) -> 60 | D38: =IF(B38="","",SUMIF('📈 Datos Completos'!$C$7:$C$5000, B38, '📈 Datos Completos'!$H$7:$H$5000)) -> 240 | E38: =IF(B38="","",SUMIF('📈 Datos Completos'!$C$7:$C$5000, B38, '📈 Datos Completos'!$I$7:$I$5000)) -> 271.2 | F38: =IF(B38="","",SUMIF('📈 Datos Completos'!$C$7:$C$5000, B38, '📈 Datos Completos'!$J$7:$J$5000)) -> 242.4 | G38: =IF(B38="","",SUMIF('📈 Datos Completos'!$C$7:$C$5000, B38, '📈 Datos Completos'!$K$7:$K$5000)) -> 513.6 | H38: =IF(B38="","",SUMIF('📈 Datos Completos'!$C$7:$C$5000, B38, '📈 Datos Completos'!$L$7:$L$5000)) -> 164.49621 | I38: =IF(B38="","",SUMIF('📈 Datos Completos'!$C$7:$C$5000, B38, '📈 Datos Completos'!$M$7:$M$5000)) -> 21.6 | J38: =IF(B38="","",SUMIF('📈 Datos Completos'!$C$7:$C$5000, B38, '📈 Datos Completos'!$N$7:$N$5000)) -> 186.09621 | K38: =IF(B38="","",SUMIF('📈 Datos Completos'!$C$7:$C$5000, B38, '📈 Datos Completos'!$O$7:$O$5000)) -> 327.50379 | L38: =IF(B38="","",IF(G38=0, 0, K38/G38)) -> 0.63766315
B39: =IFERROR(INDEX('📦 Precios Proforma'!$B$5:$B$104, 35), "") -> 3 Pack Pepsi + Rojita + Ensa Toronja 3 Lts | C39: =IF(B39="","",SUMIF('📈 Datos Completos'!$C$7:$C$5000, B39, '📈 Datos Completos'!$E$7:$E$5000)) -> 160 | D39: =IF(B39="","",SUMIF('📈 Datos Completos'!$C$7:$C$5000, B39, '📈 Datos Completos'!$H$7:$H$5000)) -> 640 | E39: =IF(B39="","",SUMIF('📈 Datos Completos'!$C$7:$C$5000, B39, '📈 Datos Completos'!$I$7:$I$5000)) -> 723.2 | F39: =IF(B39="","",SUMIF('📈 Datos Completos'!$C$7:$C$5000, B39, '📈 Datos Completos'!$J$7:$J$5000)) -> 646.4 | G39: =IF(B39="","",SUMIF('📈 Datos Completos'!$C$7:$C$5000, B39, '📈 Datos Completos'!$K$7:$K$5000)) -> 1369.6 | H39: =IF(B39="","",SUMIF('📈 Datos Completos'!$C$7:$C$5000, B39, '📈 Datos Completos'!$L$7:$L$5000)) -> 1197.5194 | I39: =IF(B39="","",SUMIF('📈 Datos Completos'!$C$7:$C$5000, B39, '📈 Datos Completos'!$M$7:$M$5000)) -> 57.6 | J39: =IF(B39="","",SUMIF('📈 Datos Completos'!$C$7:$C$5000, B39, '📈 Datos Completos'!$N$7:$N$5000)) -> 1255.1194 | K39: =IF(B39="","",SUMIF('📈 Datos Completos'!$C$7:$C$5000, B39, '📈 Datos Completos'!$O$7:$O$5000)) -> 114.48063 | L39: =IF(B39="","",IF(G39=0, 0, K39/G39)) -> 0.083586911
B40: =IFERROR(INDEX('📦 Precios Proforma'!$B$5:$B$104, 36), "") -> 4 Pack Gatorade Surtido 500 ML | C40: =IF(B40="","",SUMIF('📈 Datos Completos'!$C$7:$C$5000, B40, '📈 Datos Completos'!$E$7:$E$5000)) -> 873 | D40: =IF(B40="","",SUMIF('📈 Datos Completos'!$C$7:$C$5000, B40, '📈 Datos Completos'!$H$7:$H$5000)) -> 813 | E40: =IF(B40="","",SUMIF('📈 Datos Completos'!$C$7:$C$5000, B40, '📈 Datos Completos'!$I$7:$I$5000)) -> 5214 | F40: =IF(B40="","",SUMIF('📈 Datos Completos'!$C$7:$C$5000, B40, '📈 Datos Completos'!$J$7:$J$5000)) -> 1032.27 | G40: =IF(B40="","",SUMIF('📈 Datos Completos'!$C$7:$C$5000, B40, '📈 Datos Completos'!$K$7:$K$5000)) -> 6246.27 | H40: =IF(B40="","",SUMIF('📈 Datos Completos'!$C$7:$C$5000, B40, '📈 Datos Completos'!$L$7:$L$5000)) -> 6489.693 | I40: =IF(B40="","",SUMIF('📈 Datos Completos'!$C$7:$C$5000, B40, '📈 Datos Completos'!$M$7:$M$5000)) -> 73.17 | J40: =IF(B40="","",SUMIF('📈 Datos Completos'!$C$7:$C$5000, B40, '📈 Datos Completos'!$N$7:$N$5000)) -> 6562.863 | K40: =IF(B40="","",SUMIF('📈 Datos Completos'!$C$7:$C$5000, B40, '📈 Datos Completos'!$O$7:$O$5000)) -> -316.59297 | L40: =IF(B40="","",IF(G40=0, 0, K40/G40)) -> -0.050685124
B41: =IFERROR(INDEX('📦 Precios Proforma'!$B$5:$B$104, 37), "") -> 4 Pack Pepsi + Roja | C41: =IF(B41="","",SUMIF('📈 Datos Completos'!$C$7:$C$5000, B41, '📈 Datos Completos'!$E$7:$E$5000)) -> 165 | D41: =IF(B41="","",SUMIF('📈 Datos Completos'!$C$7:$C$5000, B41, '📈 Datos Completos'!$H$7:$H$5000)) -> 825 | E41: =IF(B41="","",SUMIF('📈 Datos Completos'!$C$7:$C$5000, B41, '📈 Datos Completos'!$I$7:$I$5000)) -> 994.95 | F41: =IF(B41="","",SUMIF('📈 Datos Completos'!$C$7:$C$5000, B41, '📈 Datos Completos'!$J$7:$J$5000)) -> 1113.75 | G41: =IF(B41="","",SUMIF('📈 Datos Completos'!$C$7:$C$5000, B41, '📈 Datos Completos'!$K$7:$K$5000)) -> 2108.7 | H41: =IF(B41="","",SUMIF('📈 Datos Completos'!$C$7:$C$5000, B41, '📈 Datos Completos'!$L$7:$L$5000)) -> 708.71262 | I41: =IF(B41="","",SUMIF('📈 Datos Completos'!$C$7:$C$5000, B41, '📈 Datos Completos'!$M$7:$M$5000)) -> 74.25 | J41: =IF(B41="","",SUMIF('📈 Datos Completos'!$C$7:$C$5000, B41, '📈 Datos Completos'!$N$7:$N$5000)) -> 782.96262 | K41: =IF(B41="","",SUMIF('📈 Datos Completos'!$C$7:$C$5000, B41, '📈 Datos Completos'!$O$7:$O$5000)) -> 1325.7374 | L41: =IF(B41="","",IF(G41=0, 0, K41/G41)) -> 0.6286989
B42: =IFERROR(INDEX('📦 Precios Proforma'!$B$5:$B$104, 38), "") -> 4 Pack Pepsi + Roja + Toronja | C42: =IF(B42="","",SUMIF('📈 Datos Completos'!$C$7:$C$5000, B42, '📈 Datos Completos'!$E$7:$E$5000)) -> 6597 | D42: =IF(B42="","",SUMIF('📈 Datos Completos'!$C$7:$C$5000, B42, '📈 Datos Completos'!$H$7:$H$5000)) -> 36757 | E42: =IF(B42="","",SUMIF('📈 Datos Completos'!$C$7:$C$5000, B42, '📈 Datos Completos'!$I$7:$I$5000)) -> 37937.71 | F42: =IF(B42="","",SUMIF('📈 Datos Completos'!$C$7:$C$5000, B42, '📈 Datos Completos'!$J$7:$J$5000)) -> 47547.95 | G42: =IF(B42="","",SUMIF('📈 Datos Completos'!$C$7:$C$5000, B42, '📈 Datos Completos'!$K$7:$K$5000)) -> 85485.66 | H42: =IF(B42="","",SUMIF('📈 Datos Completos'!$C$7:$C$5000, B42, '📈 Datos Completos'!$L$7:$L$5000)) -> 51211.233 | I42: =IF(B42="","",SUMIF('📈 Datos Completos'!$C$7:$C$5000, B42, '📈 Datos Completos'!$M$7:$M$5000)) -> 3308.13 | J42: =IF(B42="","",SUMIF('📈 Datos Completos'!$C$7:$C$5000, B42, '📈 Datos Completos'!$N$7:$N$5000)) -> 54519.363 | K42: =IF(B42="","",SUMIF('📈 Datos Completos'!$C$7:$C$5000, B42, '📈 Datos Completos'!$O$7:$O$5000)) -> 31872.078 | L42: =IF(B42="","",IF(G42=0, 0, K42/G42)) -> 0.37283537
B43: =IFERROR(INDEX('📦 Precios Proforma'!$B$5:$B$104, 39), "") -> 4 Pack Pepsi + Rojita + Toronja 3 lts | C43: =IF(B43="","",SUMIF('📈 Datos Completos'!$C$7:$C$5000, B43, '📈 Datos Completos'!$E$7:$E$5000)) -> 1007 | D43: =IF(B43="","",SUMIF('📈 Datos Completos'!$C$7:$C$5000, B43, '📈 Datos Completos'!$H$7:$H$5000)) -> 5035 | E43: =IF(B43="","",SUMIF('📈 Datos Completos'!$C$7:$C$5000, B43, '📈 Datos Completos'!$I$7:$I$5000)) -> 5347.41 | F43: =IF(B43="","",SUMIF('📈 Datos Completos'!$C$7:$C$5000, B43, '📈 Datos Completos'!$J$7:$J$5000)) -> 5981.25 | G43: =IF(B43="","",SUMIF('📈 Datos Completos'!$C$7:$C$5000, B43, '📈 Datos Completos'!$K$7:$K$5000)) -> 11328.66 | H43: =IF(B43="","",SUMIF('📈 Datos Completos'!$C$7:$C$5000, B43, '📈 Datos Completos'!$L$7:$L$5000)) -> 8069.2072 | I43: =IF(B43="","",SUMIF('📈 Datos Completos'!$C$7:$C$5000, B43, '📈 Datos Completos'!$M$7:$M$5000)) -> 453.15 | J43: =IF(B43="","",SUMIF('📈 Datos Completos'!$C$7:$C$5000, B43, '📈 Datos Completos'!$N$7:$N$5000)) -> 8522.3572 | K43: =IF(B43="","",SUMIF('📈 Datos Completos'!$C$7:$C$5000, B43, '📈 Datos Completos'!$O$7:$O$5000)) -> 2806.3028 | L43: =IF(B43="","",IF(G43=0, 0, K43/G43)) -> 0.2477171
B44: =IFERROR(INDEX('📦 Precios Proforma'!$B$5:$B$104, 40), "") -> 6 Pack Lipton 250ml Tetra | C44: =IF(B44="","",SUMIF('📈 Datos Completos'!$C$7:$C$5000, B44, '📈 Datos Completos'!$E$7:$E$5000)) -> 0 | D44: =IF(B44="","",SUMIF('📈 Datos Completos'!$C$7:$C$5000, B44, '📈 Datos Completos'!$H$7:$H$5000)) -> 0 | E44: =IF(B44="","",SUMIF('📈 Datos Completos'!$C$7:$C$5000, B44, '📈 Datos Completos'!$I$7:$I$5000)) -> 0 | F44: =IF(B44="","",SUMIF('📈 Datos Completos'!$C$7:$C$5000, B44, '📈 Datos Completos'!$J$7:$J$5000)) -> 0 | G44: =IF(B44="","",SUMIF('📈 Datos Completos'!$C$7:$C$5000, B44, '📈 Datos Completos'!$K$7:$K$5000)) -> 0 | H44: =IF(B44="","",SUMIF('📈 Datos Completos'!$C$7:$C$5000, B44, '📈 Datos Completos'!$L$7:$L$5000)) -> 0 | I44: =IF(B44="","",SUMIF('📈 Datos Completos'!$C$7:$C$5000, B44, '📈 Datos Completos'!$M$7:$M$5000)) -> 0 | J44: =IF(B44="","",SUMIF('📈 Datos Completos'!$C$7:$C$5000, B44, '📈 Datos Completos'!$N$7:$N$5000)) -> 0 | K44: =IF(B44="","",SUMIF('📈 Datos Completos'!$C$7:$C$5000, B44, '📈 Datos Completos'!$O$7:$O$5000)) -> 0 | L44: =IF(B44="","",IF(G44=0, 0, K44/G44)) -> 0
B45: =IFERROR(INDEX('📦 Precios Proforma'!$B$5:$B$104, 41), "") -> 8 Pack Pepsi Black | C45: =IF(B45="","",SUMIF('📈 Datos Completos'!$C$7:$C$5000, B45, '📈 Datos Completos'!$E$7:$E$5000)) -> 1798 | D45: =IF(B45="","",SUMIF('📈 Datos Completos'!$C$7:$C$5000, B45, '📈 Datos Completos'!$H$7:$H$5000)) -> 7180 | E45: =IF(B45="","",SUMIF('📈 Datos Completos'!$C$7:$C$5000, B45, '📈 Datos Completos'!$I$7:$I$5000)) -> 9881.58 | F45: =IF(B45="","",SUMIF('📈 Datos Completos'!$C$7:$C$5000, B45, '📈 Datos Completos'!$J$7:$J$5000)) -> 8187.48 | G45: =IF(B45="","",SUMIF('📈 Datos Completos'!$C$7:$C$5000, B45, '📈 Datos Completos'!$K$7:$K$5000)) -> 18069.06 | H45: =IF(B45="","",SUMIF('📈 Datos Completos'!$C$7:$C$5000, B45, '📈 Datos Completos'!$L$7:$L$5000)) -> 18710.443 | I45: =IF(B45="","",SUMIF('📈 Datos Completos'!$C$7:$C$5000, B45, '📈 Datos Completos'!$M$7:$M$5000)) -> 646.2 | J45: =IF(B45="","",SUMIF('📈 Datos Completos'!$C$7:$C$5000, B45, '📈 Datos Completos'!$N$7:$N$5000)) -> 19356.643 | K45: =IF(B45="","",SUMIF('📈 Datos Completos'!$C$7:$C$5000, B45, '📈 Datos Completos'!$O$7:$O$5000)) -> -1287.5825 | L45: =IF(B45="","",IF(G45=0, 0, K45/G45)) -> -0.071258966
B46: =IFERROR(INDEX('📦 Precios Proforma'!$B$5:$B$104, 42), "") -> 8 Pack Pepsi Black 355Ml Lata | C46: =IF(B46="","",SUMIF('📈 Datos Completos'!$C$7:$C$5000, B46, '📈 Datos Completos'!$E$7:$E$5000)) -> 984 | D46: =IF(B46="","",SUMIF('📈 Datos Completos'!$C$7:$C$5000, B46, '📈 Datos Completos'!$H$7:$H$5000)) -> 5354 | E46: =IF(B46="","",SUMIF('📈 Datos Completos'!$C$7:$C$5000, B46, '📈 Datos Completos'!$I$7:$I$5000)) -> 5661.72 | F46: =IF(B46="","",SUMIF('📈 Datos Completos'!$C$7:$C$5000, B46, '📈 Datos Completos'!$J$7:$J$5000)) -> 6677.1 | G46: =IF(B46="","",SUMIF('📈 Datos Completos'!$C$7:$C$5000, B46, '📈 Datos Completos'!$K$7:$K$5000)) -> 12338.82 | H46: =IF(B46="","",SUMIF('📈 Datos Completos'!$C$7:$C$5000, B46, '📈 Datos Completos'!$L$7:$L$5000)) -> 8357.259 | I46: =IF(B46="","",SUMIF('📈 Datos Completos'!$C$7:$C$5000, B46, '📈 Datos Completos'!$M$7:$M$5000)) -> 481.86 | J46: =IF(B46="","",SUMIF('📈 Datos Completos'!$C$7:$C$5000, B46, '📈 Datos Completos'!$N$7:$N$5000)) -> 8839.119 | K46: =IF(B46="","",SUMIF('📈 Datos Completos'!$C$7:$C$5000, B46, '📈 Datos Completos'!$O$7:$O$5000)) -> 3499.701 | L46: =IF(B46="","",IF(G46=0, 0, K46/G46)) -> 0.28363336
B47: =IFERROR(INDEX('📦 Precios Proforma'!$B$5:$B$104, 43), "") -> AMP 600 ML | C47: =IF(B47="","",SUMIF('📈 Datos Completos'!$C$7:$C$5000, B47, '📈 Datos Completos'!$E$7:$E$5000)) -> 1104 | D47: =IF(B47="","",SUMIF('📈 Datos Completos'!$C$7:$C$5000, B47, '📈 Datos Completos'!$H$7:$H$5000)) -> 13248 | E47: =IF(B47="","",SUMIF('📈 Datos Completos'!$C$7:$C$5000, B47, '📈 Datos Completos'!$I$7:$I$5000)) -> 7514.64 | F47: =IF(B47="","",SUMIF('📈 Datos Completos'!$C$7:$C$5000, B47, '📈 Datos Completos'!$J$7:$J$5000)) -> 16416 | G47: =IF(B47="","",SUMIF('📈 Datos Completos'!$C$7:$C$5000, B47, '📈 Datos Completos'!$K$7:$K$5000)) -> 23930.64 | H47: =IF(B47="","",SUMIF('📈 Datos Completos'!$C$7:$C$5000, B47, '📈 Datos Completos'!$L$7:$L$5000)) -> 15800.292 | I47: =IF(B47="","",SUMIF('📈 Datos Completos'!$C$7:$C$5000, B47, '📈 Datos Completos'!$M$7:$M$5000)) -> 1192.32 | J47: =IF(B47="","",SUMIF('📈 Datos Completos'!$C$7:$C$5000, B47, '📈 Datos Completos'!$N$7:$N$5000)) -> 16992.612 | K47: =IF(B47="","",SUMIF('📈 Datos Completos'!$C$7:$C$5000, B47, '📈 Datos Completos'!$O$7:$O$5000)) -> 7394.4701 | L47: =IF(B47="","",IF(G47=0, 0, K47/G47)) -> 0.30899592
B48: =IFERROR(INDEX('📦 Precios Proforma'!$B$5:$B$104, 44), "") -> Armado de Polines Walmart | C48: =IF(B48="","",SUMIF('📈 Datos Completos'!$C$7:$C$5000, B48, '📈 Datos Completos'!$E$7:$E$5000)) -> 0 | D48: =IF(B48="","",SUMIF('📈 Datos Completos'!$C$7:$C$5000, B48, '📈 Datos Completos'!$H$7:$H$5000)) -> 0 | E48: =IF(B48="","",SUMIF('📈 Datos Completos'!$C$7:$C$5000, B48, '📈 Datos Completos'!$I$7:$I$5000)) -> 0 | F48: =IF(B48="","",SUMIF('📈 Datos Completos'!$C$7:$C$5000, B48, '📈 Datos Completos'!$J$7:$J$5000)) -> 0 | G48: =IF(B48="","",SUMIF('📈 Datos Completos'!$C$7:$C$5000, B48, '📈 Datos Completos'!$K$7:$K$5000)) -> 0 | H48: =IF(B48="","",SUMIF('📈 Datos Completos'!$C$7:$C$5000, B48, '📈 Datos Completos'!$L$7:$L$5000)) -> 0 | I48: =IF(B48="","",SUMIF('📈 Datos Completos'!$C$7:$C$5000, B48, '📈 Datos Completos'!$M$7:$M$5000)) -> 0 | J48: =IF(B48="","",SUMIF('📈 Datos Completos'!$C$7:$C$5000, B48, '📈 Datos Completos'!$N$7:$N$5000)) -> 0 | K48: =IF(B48="","",SUMIF('📈 Datos Completos'!$C$7:$C$5000, B48, '📈 Datos Completos'!$O$7:$O$5000)) -> 0 | L48: =IF(B48="","",IF(G48=0, 0, K48/G48)) -> 0
B49: =IFERROR(INDEX('📦 Precios Proforma'!$B$5:$B$104, 45), "") -> GRANEL | C49: =IF(B49="","",SUMIF('📈 Datos Completos'!$C$7:$C$5000, B49, '📈 Datos Completos'!$E$7:$E$5000)) -> 2010 | D49: =IF(B49="","",SUMIF('📈 Datos Completos'!$C$7:$C$5000, B49, '📈 Datos Completos'!$H$7:$H$5000)) -> 0 | E49: =IF(B49="","",SUMIF('📈 Datos Completos'!$C$7:$C$5000, B49, '📈 Datos Completos'!$I$7:$I$5000)) -> 91950 | F49: =IF(B49="","",SUMIF('📈 Datos Completos'!$C$7:$C$5000, B49, '📈 Datos Completos'!$J$7:$J$5000)) -> 0 | G49: =IF(B49="","",SUMIF('📈 Datos Completos'!$C$7:$C$5000, B49, '📈 Datos Completos'!$K$7:$K$5000)) -> 91950 | H49: =IF(B49="","",SUMIF('📈 Datos Completos'!$C$7:$C$5000, B49, '📈 Datos Completos'!$L$7:$L$5000)) -> 28587.773 | I49: =IF(B49="","",SUMIF('📈 Datos Completos'!$C$7:$C$5000, B49, '📈 Datos Completos'!$M$7:$M$5000)) -> 0 | J49: =IF(B49="","",SUMIF('📈 Datos Completos'!$C$7:$C$5000, B49, '📈 Datos Completos'!$N$7:$N$5000)) -> 28587.773 | K49: =IF(B49="","",SUMIF('📈 Datos Completos'!$C$7:$C$5000, B49, '📈 Datos Completos'!$O$7:$O$5000)) -> 63362.227 | L49: =IF(B49="","",IF(G49=0, 0, K49/G49)) -> 0.68909437
B50: =IFERROR(INDEX('📦 Precios Proforma'!$B$5:$B$104, 46), "") -> PRECIO BASE (sin coincidencia) | C50: =IF(B50="","",SUMIF('📈 Datos Completos'!$C$7:$C$5000, B50, '📈 Datos Completos'!$E$7:$E$5000)) -> 0 | D50: =IF(B50="","",SUMIF('📈 Datos Completos'!$C$7:$C$5000, B50, '📈 Datos Completos'!$H$7:$H$5000)) -> 0 | E50: =IF(B50="","",SUMIF('📈 Datos Completos'!$C$7:$C$5000, B50, '📈 Datos Completos'!$I$7:$I$5000)) -> 0 | F50: =IF(B50="","",SUMIF('📈 Datos Completos'!$C$7:$C$5000, B50, '📈 Datos Completos'!$J$7:$J$5000)) -> 0 | G50: =IF(B50="","",SUMIF('📈 Datos Completos'!$C$7:$C$5000, B50, '📈 Datos Completos'!$K$7:$K$5000)) -> 0 | H50: =IF(B50="","",SUMIF('📈 Datos Completos'!$C$7:$C$5000, B50, '📈 Datos Completos'!$L$7:$L$5000)) -> 0 | I50: =IF(B50="","",SUMIF('📈 Datos Completos'!$C$7:$C$5000, B50, '📈 Datos Completos'!$M$7:$M$5000)) -> 0 | J50: =IF(B50="","",SUMIF('📈 Datos Completos'!$C$7:$C$5000, B50, '📈 Datos Completos'!$N$7:$N$5000)) -> 0 | K50: =IF(B50="","",SUMIF('📈 Datos Completos'!$C$7:$C$5000, B50, '📈 Datos Completos'!$O$7:$O$5000)) -> 0 | L50: =IF(B50="","",IF(G50=0, 0, K50/G50)) -> 0
B51: =IFERROR(INDEX('📦 Precios Proforma'!$B$5:$B$104, 47), "") -> TRASIEGO MANTICA | C51: =IF(B51="","",SUMIF('📈 Datos Completos'!$C$7:$C$5000, B51, '📈 Datos Completos'!$E$7:$E$5000)) -> 5 | D51: =IF(B51="","",SUMIF('📈 Datos Completos'!$C$7:$C$5000, B51, '📈 Datos Completos'!$H$7:$H$5000)) -> 0 | E51: =IF(B51="","",SUMIF('📈 Datos Completos'!$C$7:$C$5000, B51, '📈 Datos Completos'!$I$7:$I$5000)) -> 300 | F51: =IF(B51="","",SUMIF('📈 Datos Completos'!$C$7:$C$5000, B51, '📈 Datos Completos'!$J$7:$J$5000)) -> 0 | G51: =IF(B51="","",SUMIF('📈 Datos Completos'!$C$7:$C$5000, B51, '📈 Datos Completos'!$K$7:$K$5000)) -> 300 | H51: =IF(B51="","",SUMIF('📈 Datos Completos'!$C$7:$C$5000, B51, '📈 Datos Completos'!$L$7:$L$5000)) -> 63.134471 | I51: =IF(B51="","",SUMIF('📈 Datos Completos'!$C$7:$C$5000, B51, '📈 Datos Completos'!$M$7:$M$5000)) -> 0 | J51: =IF(B51="","",SUMIF('📈 Datos Completos'!$C$7:$C$5000, B51, '📈 Datos Completos'!$N$7:$N$5000)) -> 63.134471 | K51: =IF(B51="","",SUMIF('📈 Datos Completos'!$C$7:$C$5000, B51, '📈 Datos Completos'!$O$7:$O$5000)) -> 236.86553 | L51: =IF(B51="","",IF(G51=0, 0, K51/G51)) -> 0.78955176
B52: =IFERROR(INDEX('📦 Precios Proforma'!$B$5:$B$104, 48), "") -> TRASIEGO PRICESMART | C52: =IF(B52="","",SUMIF('📈 Datos Completos'!$C$7:$C$5000, B52, '📈 Datos Completos'!$E$7:$E$5000)) -> 72 | D52: =IF(B52="","",SUMIF('📈 Datos Completos'!$C$7:$C$5000, B52, '📈 Datos Completos'!$H$7:$H$5000)) -> 2110 | E52: =IF(B52="","",SUMIF('📈 Datos Completos'!$C$7:$C$5000, B52, '📈 Datos Completos'!$I$7:$I$5000)) -> 3585 | F52: =IF(B52="","",SUMIF('📈 Datos Completos'!$C$7:$C$5000, B52, '📈 Datos Completos'!$J$7:$J$5000)) -> 2464.3 | G52: =IF(B52="","",SUMIF('📈 Datos Completos'!$C$7:$C$5000, B52, '📈 Datos Completos'!$K$7:$K$5000)) -> 6049.3 | H52: =IF(B52="","",SUMIF('📈 Datos Completos'!$C$7:$C$5000, B52, '📈 Datos Completos'!$L$7:$L$5000)) -> 1111.6313 | I52: =IF(B52="","",SUMIF('📈 Datos Completos'!$C$7:$C$5000, B52, '📈 Datos Completos'!$M$7:$M$5000)) -> 189.9 | J52: =IF(B52="","",SUMIF('📈 Datos Completos'!$C$7:$C$5000, B52, '📈 Datos Completos'!$N$7:$N$5000)) -> 1301.5313 | K52: =IF(B52="","",SUMIF('📈 Datos Completos'!$C$7:$C$5000, B52, '📈 Datos Completos'!$O$7:$O$5000)) -> 4747.7687 | L52: =IF(B52="","",IF(G52=0, 0, K52/G52)) -> 0.78484596
B53: =IFERROR(INDEX('📦 Precios Proforma'!$B$5:$B$104, 49), "") -> TRASIEGO WM | C53: =IF(B53="","",SUMIF('📈 Datos Completos'!$C$7:$C$5000, B53, '📈 Datos Completos'!$E$7:$E$5000)) -> 732.3 | D53: =IF(B53="","",SUMIF('📈 Datos Completos'!$C$7:$C$5000, B53, '📈 Datos Completos'!$H$7:$H$5000)) -> 200 | E53: =IF(B53="","",SUMIF('📈 Datos Completos'!$C$7:$C$5000, B53, '📈 Datos Completos'!$I$7:$I$5000)) -> 36720 | F53: =IF(B53="","",SUMIF('📈 Datos Completos'!$C$7:$C$5000, B53, '📈 Datos Completos'!$J$7:$J$5000)) -> 202 | G53: =IF(B53="","",SUMIF('📈 Datos Completos'!$C$7:$C$5000, B53, '📈 Datos Completos'!$K$7:$K$5000)) -> 36922 | H53: =IF(B53="","",SUMIF('📈 Datos Completos'!$C$7:$C$5000, B53, '📈 Datos Completos'!$L$7:$L$5000)) -> 14257.963 | I53: =IF(B53="","",SUMIF('📈 Datos Completos'!$C$7:$C$5000, B53, '📈 Datos Completos'!$M$7:$M$5000)) -> 18 | J53: =IF(B53="","",SUMIF('📈 Datos Completos'!$C$7:$C$5000, B53, '📈 Datos Completos'!$N$7:$N$5000)) -> 14275.963 | K53: =IF(B53="","",SUMIF('📈 Datos Completos'!$C$7:$C$5000, B53, '📈 Datos Completos'!$O$7:$O$5000)) -> 23395.509 | L53: =IF(B53="","",IF(G53=0, 0, K53/G53)) -> 0.63364686
B54: =IFERROR(INDEX('📦 Precios Proforma'!$B$5:$B$104, 50), "") -> 0 | C54: =IF(B54="","",SUMIF('📈 Datos Completos'!$C$7:$C$5000, B54, '📈 Datos Completos'!$E$7:$E$5000)) -> 0 | D54: =IF(B54="","",SUMIF('📈 Datos Completos'!$C$7:$C$5000, B54, '📈 Datos Completos'!$H$7:$H$5000)) -> 0 | E54: =IF(B54="","",SUMIF('📈 Datos Completos'!$C$7:$C$5000, B54, '📈 Datos Completos'!$I$7:$I$5000)) -> 0 | F54: =IF(B54="","",SUMIF('📈 Datos Completos'!$C$7:$C$5000, B54, '📈 Datos Completos'!$J$7:$J$5000)) -> 0 | G54: =IF(B54="","",SUMIF('📈 Datos Completos'!$C$7:$C$5000, B54, '📈 Datos Completos'!$K$7:$K$5000)) -> 0 | H54: =IF(B54="","",SUMIF('📈 Datos Completos'!$C$7:$C$5000, B54, '📈 Datos Completos'!$L$7:$L$5000)) -> 0 | I54: =IF(B54="","",SUMIF('📈 Datos Completos'!$C$7:$C$5000, B54, '📈 Datos Completos'!$M$7:$M$5000)) -> 0 | J54: =IF(B54="","",SUMIF('📈 Datos Completos'!$C$7:$C$5000, B54, '📈 Datos Completos'!$N$7:$N$5000)) -> 0 | K54: =IF(B54="","",SUMIF('📈 Datos Completos'!$C$7:$C$5000, B54, '📈 Datos Completos'!$O$7:$O$5000)) -> 0 | L54: =IF(B54="","",IF(G54=0, 0, K54/G54)) -> 0
B55: TOTAL GENERAL | C55: =SUM(C5:C54) -> 53232.3 | D55: =SUM(D5:D54) -> 195255 | E55: =SUM(E5:E54) -> 412748.44 | F55: =SUM(F5:F54) -> 234289.65 | G55: =SUM(G5:G54) -> 647038.09 | H55: =SUM(H5:H54) -> 417507.75 | I55: =SUM(I5:I54) -> 17572.95 | J55: =SUM(J5:J54) -> 435080.7 | K55: =SUM(K5:K54) -> 224377.39 | L55: =IF(G55=0, 0, K55/G55) -> 0.34677617

Sheet 🗓️ Mapa de Calor
A1: 🗓️ MAPA DE CALOR - RENTABILIDAD DIARIA POR TURNO
B2: Mes Selector: | C2: TODOS | E2: Turno Selector: | F2: TODOS
A3: Semana | B3: Lunes | C3: Martes | D3: Miercoles | E3: Jueves | F3: Viernes | G3: Sabado | H3: Domingo
A5: S18 | B5: =IF(OR($C$2="TODOS",(YEAR(DATE(2026,5,4)+(5-6)*7+(2-2))&"-"&IF(MONTH(DATE(2026,5,4)+(5-6)*7+(2-2))<10,"0","")&MONTH(DATE(2026,5,4)+(5-6)*7+(2-2)))=$C$2),IF(SUMIFS('📅 Resumen Diario'!$J$5:$J$504,'📅 Resumen Diario'!$B$5:$B$504,YEAR(DATE(2026,5,4)+(5-6)*7+(2-2))&"-"&IF(MONTH(DATE(2026,5,4)+(5-6)*7+(2-2))<10,"0","")&MONTH(DATE(2026,5,4)+(5-6)*7+(2-2))&"-"&IF(DAY(DATE(2026,5,4)+(5-6)*7+(2-2))<10,"0","")&DAY(DATE(2026,5,4)+(5-6)*7+(2-2)),'📅 Resumen Diario'!$C$5:$C$504,IF($F$2="TODOS", "*", $F$2))=0,"—",SUMIFS('📅 Resumen Diario'!$Q$5:$Q$504,'📅 Resumen Diario'!$B$5:$B$504,YEAR(DATE(2026,5,4)+(5-6)*7+(2-2))&"-"&IF(MONTH(DATE(2026,5,4)+(5-6)*7+(2-2))<10,"0","")&MONTH(DATE(2026,5,4)+(5-6)*7+(2-2))&"-"&IF(DAY(DATE(2026,5,4)+(5-6)*7+(2-2))<10,"0","")&DAY(DATE(2026,5,4)+(5-6)*7+(2-2)),'📅 Resumen Diario'!$C$5:$C$504,IF($F$2="TODOS", "*", $F$2))/SUMIFS('📅 Resumen Diario'!$J$5:$J$504,'📅 Resumen Diario'!$B$5:$B$504,YEAR(DATE(2026,5,4)+(5-6)*7+(2-2))&"-"&IF(MONTH(DATE(2026,5,4)+(5-6)*7+(2-2))<10,"0","")&MONTH(DATE(2026,5,4)+(5-6)*7+(2-2))&"-"&IF(DAY(DATE(2026,5,4)+(5-6)*7+(2-2))<10,"0","")&DAY(DATE(2026,5,4)+(5-6)*7+(2-2)),'📅 Resumen Diario'!$C$5:$C$504,IF($F$2="TODOS", "*", $F$2))),"—") -> — | C5: =IF(OR($C$2="TODOS",(YEAR(DATE(2026,5,4)+(5-6)*7+(3-2))&"-"&IF(MONTH(DATE(2026,5,4)+(5-6)*7+(3-2))<10,"0","")&MONTH(DATE(2026,5,4)+(5-6)*7+(3-2)))=$C$2),IF(SUMIFS('📅 Resumen Diario'!$J$5:$J$504,'📅 Resumen Diario'!$B$5:$B$504,YEAR(DATE(2026,5,4)+(5-6)*7+(3-2))&"-"&IF(MONTH(DATE(2026,5,4)+(5-6)*7+(3-2))<10,"0","")&MONTH(DATE(2026,5,4)+(5-6)*7+(3-2))&"-"&IF(DAY(DATE(2026,5,4)+(5-6)*7+(3-2))<10,"0","")&DAY(DATE(2026,5,4)+(5-6)*7+(3-2)),'📅 Resumen Diario'!$C$5:$C$504,IF($F$2="TODOS", "*", $F$2))=0,"—",SUMIFS('📅 Resumen Diario'!$Q$5:$Q$504,'📅 Resumen Diario'!$B$5:$B$504,YEAR(DATE(2026,5,4)+(5-6)*7+(3-2))&"-"&IF(MONTH(DATE(2026,5,4)+(5-6)*7+(3-2))<10,"0","")&MONTH(DATE(2026,5,4)+(5-6)*7+(3-2))&"-"&IF(DAY(DATE(2026,5,4)+(5-6)*7+(3-2))<10,"0","")&DAY(DATE(2026,5,4)+(5-6)*7+(3-2)),'📅 Resumen Diario'!$C$5:$C$504,IF($F$2="TODOS", "*", $F$2))/SUMIFS('📅 Resumen Diario'!$J$5:$J$504,'📅 Resumen Diario'!$B$5:$B$504,YEAR(DATE(2026,5,4)+(5-6)*7+(3-2))&"-"&IF(MONTH(DATE(2026,5,4)+(5-6)*7+(3-2))<10,"0","")&MONTH(DATE(2026,5,4)+(5-6)*7+(3-2))&"-"&IF(DAY(DATE(2026,5,4)+(5-6)*7+(3-2))<10,"0","")&DAY(DATE(2026,5,4)+(5-6)*7+(3-2)),'📅 Resumen Diario'!$C$5:$C$504,IF($F$2="TODOS", "*", $F$2))),"—") -> — | D5: =IF(OR($C$2="TODOS",(YEAR(DATE(2026,5,4)+(5-6)*7+(4-2))&"-"&IF(MONTH(DATE(2026,5,4)+(5-6)*7+(4-2))<10,"0","")&MONTH(DATE(2026,5,4)+(5-6)*7+(4-2)))=$C$2),IF(SUMIFS('📅 Resumen Diario'!$J$5:$J$504,'📅 Resumen Diario'!$B$5:$B$504,YEAR(DATE(2026,5,4)+(5-6)*7+(4-2))&"-"&IF(MONTH(DATE(2026,5,4)+(5-6)*7+(4-2))<10,"0","")&MONTH(DATE(2026,5,4)+(5-6)*7+(4-2))&"-"&IF(DAY(DATE(2026,5,4)+(5-6)*7+(4-2))<10,"0","")&DAY(DATE(2026,5,4)+(5-6)*7+(4-2)),'📅 Resumen Diario'!$C$5:$C$504,IF($F$2="TODOS", "*", $F$2))=0,"—",SUMIFS('📅 Resumen Diario'!$Q$5:$Q$504,'📅 Resumen Diario'!$B$5:$B$504,YEAR(DATE(2026,5,4)+(5-6)*7+(4-2))&"-"&IF(MONTH(DATE(2026,5,4)+(5-6)*7+(4-2))<10,"0","")&MONTH(DATE(2026,5,4)+(5-6)*7+(4-2))&"-"&IF(DAY(DATE(2026,5,4)+(5-6)*7+(4-2))<10,"0","")&DAY(DATE(2026,5,4)+(5-6)*7+(4-2)),'📅 Resumen Diario'!$C$5:$C$504,IF($F$2="TODOS", "*", $F$2))/SUMIFS('📅 Resumen Diario'!$J$5:$J$504,'📅 Resumen Diario'!$B$5:$B$504,YEAR(DATE(2026,5,4)+(5-6)*7+(4-2))&"-"&IF(MONTH(DATE(2026,5,4)+(5-6)*7+(4-2))<10,"0","")&MONTH(DATE(2026,5,4)+(5-6)*7+(4-2))&"-"&IF(DAY(DATE(2026,5,4)+(5-6)*7+(4-2))<10,"0","")&DAY(DATE(2026,5,4)+(5-6)*7+(4-2)),'📅 Resumen Diario'!$C$5:$C$504,IF($F$2="TODOS", "*", $F$2))),"—") -> — | E5: =IF(OR($C$2="TODOS",(YEAR(DATE(2026,5,4)+(5-6)*7+(5-2))&"-"&IF(MONTH(DATE(2026,5,4)+(5-6)*7+(5-2))<10,"0","")&MONTH(DATE(2026,5,4)+(5-6)*7+(5-2)))=$C$2),IF(SUMIFS('📅 Resumen Diario'!$J$5:$J$504,'📅 Resumen Diario'!$B$5:$B$504,YEAR(DATE(2026,5,4)+(5-6)*7+(5-2))&"-"&IF(MONTH(DATE(2026,5,4)+(5-6)*7+(5-2))<10,"0","")&MONTH(DATE(2026,5,4)+(5-6)*7+(5-2))&"-"&IF(DAY(DATE(2026,5,4)+(5-6)*7+(5-2))<10,"0","")&DAY(DATE(2026,5,4)+(5-6)*7+(5-2)),'📅 Resumen Diario'!$C$5:$C$504,IF($F$2="TODOS", "*", $F$2))=0,"—",SUMIFS('📅 Resumen Diario'!$Q$5:$Q$504,'📅 Resumen Diario'!$B$5:$B$504,YEAR(DATE(2026,5,4)+(5-6)*7+(5-2))&"-"&IF(MONTH(DATE(2026,5,4)+(5-6)*7+(5-2))<10,"0","")&MONTH(DATE(2026,5,4)+(5-6)*7+(5-2))&"-"&IF(DAY(DATE(2026,5,4)+(5-6)*7+(5-2))<10,"0","")&DAY(DATE(2026,5,4)+(5-6)*7+(5-2)),'📅 Resumen Diario'!$C$5:$C$504,IF($F$2="TODOS", "*", $F$2))/SUMIFS('📅 Resumen Diario'!$J$5:$J$504,'📅 Resumen Diario'!$B$5:$B$504,YEAR(DATE(2026,5,4)+(5-6)*7+(5-2))&"-"&IF(MONTH(DATE(2026,5,4)+(5-6)*7+(5-2))<10,"0","")&MONTH(DATE(2026,5,4)+(5-6)*7+(5-2))&"-"&IF(DAY(DATE(2026,5,4)+(5-6)*7+(5-2))<10,"0","")&DAY(DATE(2026,5,4)+(5-6)*7+(5-2)),'📅 Resumen Diario'!$C$5:$C$504,IF($F$2="TODOS", "*", $F$2))),"—") -> — | F5: =IF(OR($C$2="TODOS",(YEAR(DATE(2026,5,4)+(5-6)*7+(6-2))&"-"&IF(MONTH(DATE(2026,5,4)+(5-6)*7+(6-2))<10,"0","")&MONTH(DATE(2026,5,4)+(5-6)*7+(6-2)))=$C$2),IF(SUMIFS('📅 Resumen Diario'!$J$5:$J$504,'📅 Resumen Diario'!$B$5:$B$504,YEAR(DATE(2026,5,4)+(5-6)*7+(6-2))&"-"&IF(MONTH(DATE(2026,5,4)+(5-6)*7+(6-2))<10,"0","")&MONTH(DATE(2026,5,4)+(5-6)*7+(6-2))&"-"&IF(DAY(DATE(2026,5,4)+(5-6)*7+(6-2))<10,"0","")&DAY(DATE(2026,5,4)+(5-6)*7+(6-2)),'📅 Resumen Diario'!$C$5:$C$504,IF($F$2="TODOS", "*", $F$2))=0,"—",SUMIFS('📅 Resumen Diario'!$Q$5:$Q$504,'📅 Resumen Diario'!$B$5:$B$504,YEAR(DATE(2026,5,4)+(5-6)*7+(6-2))&"-"&IF(MONTH(DATE(2026,5,4)+(5-6)*7+(6-2))<10,"0","")&MONTH(DATE(2026,5,4)+(5-6)*7+(6-2))&"-"&IF(DAY(DATE(2026,5,4)+(5-6)*7+(6-2))<10,"0","")&DAY(DATE(2026,5,4)+(5-6)*7+(6-2)),'📅 Resumen Diario'!$C$5:$C$504,IF($F$2="TODOS", "*", $F$2))/SUMIFS('📅 Resumen Diario'!$J$5:$J$504,'📅 Resumen Diario'!$B$5:$B$504,YEAR(DATE(2026,5,4)+(5-6)*7+(6-2))&"-"&IF(MONTH(DATE(2026,5,4)+(5-6)*7+(6-2))<10,"0","")&MONTH(DATE(2026,5,4)+(5-6)*7+(6-2))&"-"&IF(DAY(DATE(2026,5,4)+(5-6)*7+(6-2))<10,"0","")&DAY(DATE(2026,5,4)+(5-6)*7+(6-2)),'📅 Resumen Diario'!$C$5:$C$504,IF($F$2="TODOS", "*", $F$2))),"—") -> 0.090488165 | G5: =IF(OR($C$2="TODOS",(YEAR(DATE(2026,5,4)+(5-6)*7+(7-2))&"-"&IF(MONTH(DATE(2026,5,4)+(5-6)*7+(7-2))<10,"0","")&MONTH(DATE(2026,5,4)+(5-6)*7+(7-2)))=$C$2),IF(SUMIFS('📅 Resumen Diario'!$J$5:$J$504,'📅 Resumen Diario'!$B$5:$B$504,YEAR(DATE(2026,5,4)+(5-6)*7+(7-2))&"-"&IF(MONTH(DATE(2026,5,4)+(5-6)*7+(7-2))<10,"0","")&MONTH(DATE(2026,5,4)+(5-6)*7+(7-2))&"-"&IF(DAY(DATE(2026,5,4)+(5-6)*7+(7-2))<10,"0","")&DAY(DATE(2026,5,4)+(5-6)*7+(7-2)),'📅 Resumen Diario'!$C$5:$C$504,IF($F$2="TODOS", "*", $F$2))=0,"—",SUMIFS('📅 Resumen Diario'!$Q$5:$Q$504,'📅 Resumen Diario'!$B$5:$B$504,YEAR(DATE(2026,5,4)+(5-6)*7+(7-2))&"-"&IF(MONTH(DATE(2026,5,4)+(5-6)*7+(7-2))<10,"0","")&MONTH(DATE(2026,5,4)+(5-6)*7+(7-2))&"-"&IF(DAY(DATE(2026,5,4)+(5-6)*7+(7-2))<10,"0","")&DAY(DATE(2026,5,4)+(5-6)*7+(7-2)),'📅 Resumen Diario'!$C$5:$C$504,IF($F$2="TODOS", "*", $F$2))/SUMIFS('📅 Resumen Diario'!$J$5:$J$504,'📅 Resumen Diario'!$B$5:$B$504,YEAR(DATE(2026,5,4)+(5-6)*7+(7-2))&"-"&IF(MONTH(DATE(2026,5,4)+(5-6)*7+(7-2))<10,"0","")&MONTH(DATE(2026,5,4)+(5-6)*7+(7-2))&"-"&IF(DAY(DATE(2026,5,4)+(5-6)*7+(7-2))<10,"0","")&DAY(DATE(2026,5,4)+(5-6)*7+(7-2)),'📅 Resumen Diario'!$C$5:$C$504,IF($F$2="TODOS", "*", $F$2))),"—") -> 0.55801388 | H5: =IF(OR($C$2="TODOS",(YEAR(DATE(2026,5,4)+(5-6)*7+(8-2))&"-"&IF(MONTH(DATE(2026,5,4)+(5-6)*7+(8-2))<10,"0","")&MONTH(DATE(2026,5,4)+(5-6)*7+(8-2)))=$C$2),IF(SUMIFS('📅 Resumen Diario'!$J$5:$J$504,'📅 Resumen Diario'!$B$5:$B$504,YEAR(DATE(2026,5,4)+(5-6)*7+(8-2))&"-"&IF(MONTH(DATE(2026,5,4)+(5-6)*7+(8-2))<10,"0","")&MONTH(DATE(2026,5,4)+(5-6)*7+(8-2))&"-"&IF(DAY(DATE(2026,5,4)+(5-6)*7+(8-2))<10,"0","")&DAY(DATE(2026,5,4)+(5-6)*7+(8-2)),'📅 Resumen Diario'!$C$5:$C$504,IF($F$2="TODOS", "*", $F$2))=0,"—",SUMIFS('📅 Resumen Diario'!$Q$5:$Q$504,'📅 Resumen Diario'!$B$5:$B$504,YEAR(DATE(2026,5,4)+(5-6)*7+(8-2))&"-"&IF(MONTH(DATE(2026,5,4)+(5-6)*7+(8-2))<10,"0","")&MONTH(DATE(2026,5,4)+(5-6)*7+(8-2))&"-"&IF(DAY(DATE(2026,5,4)+(5-6)*7+(8-2))<10,"0","")&DAY(DATE(2026,5,4)+(5-6)*7+(8-2)),'📅 Resumen Diario'!$C$5:$C$504,IF($F$2="TODOS", "*", $F$2))/SUMIFS('📅 Resumen Diario'!$J$5:$J$504,'📅 Resumen Diario'!$B$5:$B$504,YEAR(DATE(2026,5,4)+(5-6)*7+(8-2))&"-"&IF(MONTH(DATE(2026,5,4)+(5-6)*7+(8-2))<10,"0","")&MONTH(DATE(2026,5,4)+(5-6)*7+(8-2))&"-"&IF(DAY(DATE(2026,5,4)+(5-6)*7+(8-2))<10,"0","")&DAY(DATE(2026,5,4)+(5-6)*7+(8-2)),'📅 Resumen Diario'!$C$5:$C$504,IF($F$2="TODOS", "*", $F$2))),"—") -> 0.62535769
A6: S19 | B6: =IF(OR($C$2="TODOS",(YEAR(DATE(2026,5,4)+(6-6)*7+(2-2))&"-"&IF(MONTH(DATE(2026,5,4)+(6-6)*7+(2-2))<10,"0","")&MONTH(DATE(2026,5,4)+(6-6)*7+(2-2)))=$C$2),IF(SUMIFS('📅 Resumen Diario'!$J$5:$J$504,'📅 Resumen Diario'!$B$5:$B$504,YEAR(DATE(2026,5,4)+(6-6)*7+(2-2))&"-"&IF(MONTH(DATE(2026,5,4)+(6-6)*7+(2-2))<10,"0","")&MONTH(DATE(2026,5,4)+(6-6)*7+(2-2))&"-"&IF(DAY(DATE(2026,5,4)+(6-6)*7+(2-2))<10,"0","")&DAY(DATE(2026,5,4)+(6-6)*7+(2-2)),'📅 Resumen Diario'!$C$5:$C$504,IF($F$2="TODOS", "*", $F$2))=0,"—",SUMIFS('📅 Resumen Diario'!$Q$5:$Q$504,'📅 Resumen Diario'!$B$5:$B$504,YEAR(DATE(2026,5,4)+(6-6)*7+(2-2))&"-"&IF(MONTH(DATE(2026,5,4)+(6-6)*7+(2-2))<10,"0","")&MONTH(DATE(2026,5,4)+(6-6)*7+(2-2))&"-"&IF(DAY(DATE(2026,5,4)+(6-6)*7+(2-2))<10,"0","")&DAY(DATE(2026,5,4)+(6-6)*7+(2-2)),'📅 Resumen Diario'!$C$5:$C$504,IF($F$2="TODOS", "*", $F$2))/SUMIFS('📅 Resumen Diario'!$J$5:$J$504,'📅 Resumen Diario'!$B$5:$B$504,YEAR(DATE(2026,5,4)+(6-6)*7+(2-2))&"-"&IF(MONTH(DATE(2026,5,4)+(6-6)*7+(2-2))<10,"0","")&MONTH(DATE(2026,5,4)+(6-6)*7+(2-2))&"-"&IF(DAY(DATE(2026,5,4)+(6-6)*7+(2-2))<10,"0","")&DAY(DATE(2026,5,4)+(6-6)*7+(2-2)),'📅 Resumen Diario'!$C$5:$C$504,IF($F$2="TODOS", "*", $F$2))),"—") -> 0.21708884 | C6: =IF(OR($C$2="TODOS",(YEAR(DATE(2026,5,4)+(6-6)*7+(3-2))&"-"&IF(MONTH(DATE(2026,5,4)+(6-6)*7+(3-2))<10,"0","")&MONTH(DATE(2026,5,4)+(6-6)*7+(3-2)))=$C$2),IF(SUMIFS('📅 Resumen Diario'!$J$5:$J$504,'📅 Resumen Diario'!$B$5:$B$504,YEAR(DATE(2026,5,4)+(6-6)*7+(3-2))&"-"&IF(MONTH(DATE(2026,5,4)+(6-6)*7+(3-2))<10,"0","")&MONTH(DATE(2026,5,4)+(6-6)*7+(3-2))&"-"&IF(DAY(DATE(2026,5,4)+(6-6)*7+(3-2))<10,"0","")&DAY(DATE(2026,5,4)+(6-6)*7+(3-2)),'📅 Resumen Diario'!$C$5:$C$504,IF($F$2="TODOS", "*", $F$2))=0,"—",SUMIFS('📅 Resumen Diario'!$Q$5:$Q$504,'📅 Resumen Diario'!$B$5:$B$504,YEAR(DATE(2026,5,4)+(6-6)*7+(3-2))&"-"&IF(MONTH(DATE(2026,5,4)+(6-6)*7+(3-2))<10,"0","")&MONTH(DATE(2026,5,4)+(6-6)*7+(3-2))&"-"&IF(DAY(DATE(2026,5,4)+(6-6)*7+(3-2))<10,"0","")&DAY(DATE(2026,5,4)+(6-6)*7+(3-2)),'📅 Resumen Diario'!$C$5:$C$504,IF($F$2="TODOS", "*", $F$2))/SUMIFS('📅 Resumen Diario'!$J$5:$J$504,'📅 Resumen Diario'!$B$5:$B$504,YEAR(DATE(2026,5,4)+(6-6)*7+(3-2))&"-"&IF(MONTH(DATE(2026,5,4)+(6-6)*7+(3-2))<10,"0","")&MONTH(DATE(2026,5,4)+(6-6)*7+(3-2))&"-"&IF(DAY(DATE(2026,5,4)+(6-6)*7+(3-2))<10,"0","")&DAY(DATE(2026,5,4)+(6-6)*7+(3-2)),'📅 Resumen Diario'!$C$5:$C$504,IF($F$2="TODOS", "*", $F$2))),"—") -> 0.31637987 | D6: =IF(OR($C$2="TODOS",(YEAR(DATE(2026,5,4)+(6-6)*7+(4-2))&"-"&IF(MONTH(DATE(2026,5,4)+(6-6)*7+(4-2))<10,"0","")&MONTH(DATE(2026,5,4)+(6-6)*7+(4-2)))=$C$2),IF(SUMIFS('📅 Resumen Diario'!$J$5:$J$504,'📅 Resumen Diario'!$B$5:$B$504,YEAR(DATE(2026,5,4)+(6-6)*7+(4-2))&"-"&IF(MONTH(DATE(2026,5,4)+(6-6)*7+(4-2))<10,"0","")&MONTH(DATE(2026,5,4)+(6-6)*7+(4-2))&"-"&IF(DAY(DATE(2026,5,4)+(6-6)*7+(4-2))<10,"0","")&DAY(DATE(2026,5,4)+(6-6)*7+(4-2)),'📅 Resumen Diario'!$C$5:$C$504,IF($F$2="TODOS", "*", $F$2))=0,"—",SUMIFS('📅 Resumen Diario'!$Q$5:$Q$504,'📅 Resumen Diario'!$B$5:$B$504,YEAR(DATE(2026,5,4)+(6-6)*7+(4-2))&"-"&IF(MONTH(DATE(2026,5,4)+(6-6)*7+(4-2))<10,"0","")&MONTH(DATE(2026,5,4)+(6-6)*7+(4-2))&"-"&IF(DAY(DATE(2026,5,4)+(6-6)*7+(4-2))<10,"0","")&DAY(DATE(2026,5,4)+(6-6)*7+(4-2)),'📅 Resumen Diario'!$C$5:$C$504,IF($F$2="TODOS", "*", $F$2))/SUMIFS('📅 Resumen Diario'!$J$5:$J$504,'📅 Resumen Diario'!$B$5:$B$504,YEAR(DATE(2026,5,4)+(6-6)*7+(4-2))&"-"&IF(MONTH(DATE(2026,5,4)+(6-6)*7+(4-2))<10,"0","")&MONTH(DATE(2026,5,4)+(6-6)*7+(4-2))&"-"&IF(DAY(DATE(2026,5,4)+(6-6)*7+(4-2))<10,"0","")&DAY(DATE(2026,5,4)+(6-6)*7+(4-2)),'📅 Resumen Diario'!$C$5:$C$504,IF($F$2="TODOS", "*", $F$2))),"—") -> 0.16423189 | E6: =IF(OR($C$2="TODOS",(YEAR(DATE(2026,5,4)+(6-6)*7+(5-2))&"-"&IF(MONTH(DATE(2026,5,4)+(6-6)*7+(5-2))<10,"0","")&MONTH(DATE(2026,5,4)+(6-6)*7+(5-2)))=$C$2),IF(SUMIFS('📅 Resumen Diario'!$J$5:$J$504,'📅 Resumen Diario'!$B$5:$B$504,YEAR(DATE(2026,5,4)+(6-6)*7+(5-2))&"-"&IF(MONTH(DATE(2026,5,4)+(6-6)*7+(5-2))<10,"0","")&MONTH(DATE(2026,5,4)+(6-6)*7+(5-2))&"-"&IF(DAY(DATE(2026,5,4)+(6-6)*7+(5-2))<10,"0","")&DAY(DATE(2026,5,4)+(6-6)*7+(5-2)),'📅 Resumen Diario'!$C$5:$C$504,IF($F$2="TODOS", "*", $F$2))=0,"—",SUMIFS('📅 Resumen Diario'!$Q$5:$Q$504,'📅 Resumen Diario'!$B$5:$B$504,YEAR(DATE(2026,5,4)+(6-6)*7+(5-2))&"-"&IF(MONTH(DATE(2026,5,4)+(6-6)*7+(5-2))<10,"0","")&MONTH(DATE(2026,5,4)+(6-6)*7+(5-2))&"-"&IF(DAY(DATE(2026,5,4)+(6-6)*7+(5-2))<10,"0","")&DAY(DATE(2026,5,4)+(6-6)*7+(5-2)),'📅 Resumen Diario'!$C$5:$C$504,IF($F$2="TODOS", "*", $F$2))/SUMIFS('📅 Resumen Diario'!$J$5:$J$504,'📅 Resumen Diario'!$B$5:$B$504,YEAR(DATE(2026,5,4)+(6-6)*7+(5-2))&"-"&IF(MONTH(DATE(2026,5,4)+(6-6)*7+(5-2))<10,"0","")&MONTH(DATE(2026,5,4)+(6-6)*7+(5-2))&"-"&IF(DAY(DATE(2026,5,4)+(6-6)*7+(5-2))<10,"0","")&DAY(DATE(2026,5,4)+(6-6)*7+(5-2)),'📅 Resumen Diario'!$C$5:$C$504,IF($F$2="TODOS", "*", $F$2))),"—") -> 0.56341612 | F6: =IF(OR($C$2="TODOS",(YEAR(DATE(2026,5,4)+(6-6)*7+(6-2))&"-"&IF(MONTH(DATE(2026,5,4)+(6-6)*7+(6-2))<10,"0","")&MONTH(DATE(2026,5,4)+(6-6)*7+(6-2)))=$C$2),IF(SUMIFS('📅 Resumen Diario'!$J$5:$J$504,'📅 Resumen Diario'!$B$5:$B$504,YEAR(DATE(2026,5,4)+(6-6)*7+(6-2))&"-"&IF(MONTH(DATE(2026,5,4)+(6-6)*7+(6-2))<10,"0","")&MONTH(DATE(2026,5,4)+(6-6)*7+(6-2))&"-"&IF(DAY(DATE(2026,5,4)+(6-6)*7+(6-2))<10,"0","")&DAY(DATE(2026,5,4)+(6-6)*7+(6-2)),'📅 Resumen Diario'!$C$5:$C$504,IF($F$2="TODOS", "*", $F$2))=0,"—",SUMIFS('📅 Resumen Diario'!$Q$5:$Q$504,'📅 Resumen Diario'!$B$5:$B$504,YEAR(DATE(2026,5,4)+(6-6)*7+(6-2))&"-"&IF(MONTH(DATE(2026,5,4)+(6-6)*7+(6-2))<10,"0","")&MONTH(DATE(2026,5,4)+(6-6)*7+(6-2))&"-"&IF(DAY(DATE(2026,5,4)+(6-6)*7+(6-2))<10,"0","")&DAY(DATE(2026,5,4)+(6-6)*7+(6-2)),'📅 Resumen Diario'!$C$5:$C$504,IF($F$2="TODOS", "*", $F$2))/SUMIFS('📅 Resumen Diario'!$J$5:$J$504,'📅 Resumen Diario'!$B$5:$B$504,YEAR(DATE(2026,5,4)+(6-6)*7+(6-2))&"-"&IF(MONTH(DATE(2026,5,4)+(6-6)*7+(6-2))<10,"0","")&MONTH(DATE(2026,5,4)+(6-6)*7+(6-2))&"-"&IF(DAY(DATE(2026,5,4)+(6-6)*7+(6-2))<10,"0","")&DAY(DATE(2026,5,4)+(6-6)*7+(6-2)),'📅 Resumen Diario'!$C$5:$C$504,IF($F$2="TODOS", "*", $F$2))),"—") -> 0.60286305 | G6: =IF(OR($C$2="TODOS",(YEAR(DATE(2026,5,4)+(6-6)*7+(7-2))&"-"&IF(MONTH(DATE(2026,5,4)+(6-6)*7+(7-2))<10,"0","")&MONTH(DATE(2026,5,4)+(6-6)*7+(7-2)))=$C$2),IF(SUMIFS('📅 Resumen Diario'!$J$5:$J$504,'📅 Resumen Diario'!$B$5:$B$504,YEAR(DATE(2026,5,4)+(6-6)*7+(7-2))&"-"&IF(MONTH(DATE(2026,5,4)+(6-6)*7+(7-2))<10,"0","")&MONTH(DATE(2026,5,4)+(6-6)*7+(7-2))&"-"&IF(DAY(DATE(2026,5,4)+(6-6)*7+(7-2))<10,"0","")&DAY(DATE(2026,5,4)+(6-6)*7+(7-2)),'📅 Resumen Diario'!$C$5:$C$504,IF($F$2="TODOS", "*", $F$2))=0,"—",SUMIFS('📅 Resumen Diario'!$Q$5:$Q$504,'📅 Resumen Diario'!$B$5:$B$504,YEAR(DATE(2026,5,4)+(6-6)*7+(7-2))&"-"&IF(MONTH(DATE(2026,5,4)+(6-6)*7+(7-2))<10,"0","")&MONTH(DATE(2026,5,4)+(6-6)*7+(7-2))&"-"&IF(DAY(DATE(2026,5,4)+(6-6)*7+(7-2))<10,"0","")&DAY(DATE(2026,5,4)+(6-6)*7+(7-2)),'📅 Resumen Diario'!$C$5:$C$504,IF($F$2="TODOS", "*", $F$2))/SUMIFS('📅 Resumen Diario'!$J$5:$J$504,'📅 Resumen Diario'!$B$5:$B$504,YEAR(DATE(2026,5,4)+(6-6)*7+(7-2))&"-"&IF(MONTH(DATE(2026,5,4)+(6-6)*7+(7-2))<10,"0","")&MONTH(DATE(2026,5,4)+(6-6)*7+(7-2))&"-"&IF(DAY(DATE(2026,5,4)+(6-6)*7+(7-2))<10,"0","")&DAY(DATE(2026,5,4)+(6-6)*7+(7-2)),'📅 Resumen Diario'!$C$5:$C$504,IF($F$2="TODOS", "*", $F$2))),"—") -> 0.64171973 | H6: =IF(OR($C$2="TODOS",(YEAR(DATE(2026,5,4)+(6-6)*7+(8-2))&"-"&IF(MONTH(DATE(2026,5,4)+(6-6)*7+(8-2))<10,"0","")&MONTH(DATE(2026,5,4)+(6-6)*7+(8-2)))=$C$2),IF(SUMIFS('📅 Resumen Diario'!$J$5:$J$504,'📅 Resumen Diario'!$B$5:$B$504,YEAR(DATE(2026,5,4)+(6-6)*7+(8-2))&"-"&IF(MONTH(DATE(2026,5,4)+(6-6)*7+(8-2))<10,"0","")&MONTH(DATE(2026,5,4)+(6-6)*7+(8-2))&"-"&IF(DAY(DATE(2026,5,4)+(6-6)*7+(8-2))<10,"0","")&DAY(DATE(2026,5,4)+(6-6)*7+(8-2)),'📅 Resumen Diario'!$C$5:$C$504,IF($F$2="TODOS", "*", $F$2))=0,"—",SUMIFS('📅 Resumen Diario'!$Q$5:$Q$504,'📅 Resumen Diario'!$B$5:$B$504,YEAR(DATE(2026,5,4)+(6-6)*7+(8-2))&"-"&IF(MONTH(DATE(2026,5,4)+(6-6)*7+(8-2))<10,"0","")&MONTH(DATE(2026,5,4)+(6-6)*7+(8-2))&"-"&IF(DAY(DATE(2026,5,4)+(6-6)*7+(8-2))<10,"0","")&DAY(DATE(2026,5,4)+(6-6)*7+(8-2)),'📅 Resumen Diario'!$C$5:$C$504,IF($F$2="TODOS", "*", $F$2))/SUMIFS('📅 Resumen Diario'!$J$5:$J$504,'📅 Resumen Diario'!$B$5:$B$504,YEAR(DATE(2026,5,4)+(6-6)*7+(8-2))&"-"&IF(MONTH(DATE(2026,5,4)+(6-6)*7+(8-2))<10,"0","")&MONTH(DATE(2026,5,4)+(6-6)*7+(8-2))&"-"&IF(DAY(DATE(2026,5,4)+(6-6)*7+(8-2))<10,"0","")&DAY(DATE(2026,5,4)+(6-6)*7+(8-2)),'📅 Resumen Diario'!$C$5:$C$504,IF($F$2="TODOS", "*", $F$2))),"—") -> 0.49092681
A7: S20 | B7: =IF(OR($C$2="TODOS",(YEAR(DATE(2026,5,4)+(7-6)*7+(2-2))&"-"&IF(MONTH(DATE(2026,5,4)+(7-6)*7+(2-2))<10,"0","")&MONTH(DATE(2026,5,4)+(7-6)*7+(2-2)))=$C$2),IF(SUMIFS('📅 Resumen Diario'!$J$5:$J$504,'📅 Resumen Diario'!$B$5:$B$504,YEAR(DATE(2026,5,4)+(7-6)*7+(2-2))&"-"&IF(MONTH(DATE(2026,5,4)+(7-6)*7+(2-2))<10,"0","")&MONTH(DATE(2026,5,4)+(7-6)*7+(2-2))&"-"&IF(DAY(DATE(2026,5,4)+(7-6)*7+(2-2))<10,"0","")&DAY(DATE(2026,5,4)+(7-6)*7+(2-2)),'📅 Resumen Diario'!$C$5:$C$504,IF($F$2="TODOS", "*", $F$2))=0,"—",SUMIFS('📅 Resumen Diario'!$Q$5:$Q$504,'📅 Resumen Diario'!$B$5:$B$504,YEAR(DATE(2026,5,4)+(7-6)*7+(2-2))&"-"&IF(MONTH(DATE(2026,5,4)+(7-6)*7+(2-2))<10,"0","")&MONTH(DATE(2026,5,4)+(7-6)*7+(2-2))&"-"&IF(DAY(DATE(2026,5,4)+(7-6)*7+(2-2))<10,"0","")&DAY(DATE(2026,5,4)+(7-6)*7+(2-2)),'📅 Resumen Diario'!$C$5:$C$504,IF($F$2="TODOS", "*", $F$2))/SUMIFS('📅 Resumen Diario'!$J$5:$J$504,'📅 Resumen Diario'!$B$5:$B$504,YEAR(DATE(2026,5,4)+(7-6)*7+(2-2))&"-"&IF(MONTH(DATE(2026,5,4)+(7-6)*7+(2-2))<10,"0","")&MONTH(DATE(2026,5,4)+(7-6)*7+(2-2))&"-"&IF(DAY(DATE(2026,5,4)+(7-6)*7+(2-2))<10,"0","")&DAY(DATE(2026,5,4)+(7-6)*7+(2-2)),'📅 Resumen Diario'!$C$5:$C$504,IF($F$2="TODOS", "*", $F$2))),"—") -> 0.17348871 | C7: =IF(OR($C$2="TODOS",(YEAR(DATE(2026,5,4)+(7-6)*7+(3-2))&"-"&IF(MONTH(DATE(2026,5,4)+(7-6)*7+(3-2))<10,"0","")&MONTH(DATE(2026,5,4)+(7-6)*7+(3-2)))=$C$2),IF(SUMIFS('📅 Resumen Diario'!$J$5:$J$504,'📅 Resumen Diario'!$B$5:$B$504,YEAR(DATE(2026,5,4)+(7-6)*7+(3-2))&"-"&IF(MONTH(DATE(2026,5,4)+(7-6)*7+(3-2))<10,"0","")&MONTH(DATE(2026,5,4)+(7-6)*7+(3-2))&"-"&IF(DAY(DATE(2026,5,4)+(7-6)*7+(3-2))<10,"0","")&DAY(DATE(2026,5,4)+(7-6)*7+(3-2)),'📅 Resumen Diario'!$C$5:$C$504,IF($F$2="TODOS", "*", $F$2))=0,"—",SUMIFS('📅 Resumen Diario'!$Q$5:$Q$504,'📅 Resumen Diario'!$B$5:$B$504,YEAR(DATE(2026,5,4)+(7-6)*7+(3-2))&"-"&IF(MONTH(DATE(2026,5,4)+(7-6)*7+(3-2))<10,"0","")&MONTH(DATE(2026,5,4)+(7-6)*7+(3-2))&"-"&IF(DAY(DATE(2026,5,4)+(7-6)*7+(3-2))<10,"0","")&DAY(DATE(2026,5,4)+(7-6)*7+(3-2)),'📅 Resumen Diario'!$C$5:$C$504,IF($F$2="TODOS", "*", $F$2))/SUMIFS('📅 Resumen Diario'!$J$5:$J$504,'📅 Resumen Diario'!$B$5:$B$504,YEAR(DATE(2026,5,4)+(7-6)*7+(3-2))&"-"&IF(MONTH(DATE(2026,5,4)+(7-6)*7+(3-2))<10,"0","")&MONTH(DATE(2026,5,4)+(7-6)*7+(3-2))&"-"&IF(DAY(DATE(2026,5,4)+(7-6)*7+(3-2))<10,"0","")&DAY(DATE(2026,5,4)+(7-6)*7+(3-2)),'📅 Resumen Diario'!$C$5:$C$504,IF($F$2="TODOS", "*", $F$2))),"—") -> -0.043697796 | D7: =IF(OR($C$2="TODOS",(YEAR(DATE(2026,5,4)+(7-6)*7+(4-2))&"-"&IF(MONTH(DATE(2026,5,4)+(7-6)*7+(4-2))<10,"0","")&MONTH(DATE(2026,5,4)+(7-6)*7+(4-2)))=$C$2),IF(SUMIFS('📅 Resumen Diario'!$J$5:$J$504,'📅 Resumen Diario'!$B$5:$B$504,YEAR(DATE(2026,5,4)+(7-6)*7+(4-2))&"-"&IF(MONTH(DATE(2026,5,4)+(7-6)*7+(4-2))<10,"0","")&MONTH(DATE(2026,5,4)+(7-6)*7+(4-2))&"-"&IF(DAY(DATE(2026,5,4)+(7-6)*7+(4-2))<10,"0","")&DAY(DATE(2026,5,4)+(7-6)*7+(4-2)),'📅 Resumen Diario'!$C$5:$C$504,IF($F$2="TODOS", "*", $F$2))=0,"—",SUMIFS('📅 Resumen Diario'!$Q$5:$Q$504,'📅 Resumen Diario'!$B$5:$B$504,YEAR(DATE(2026,5,4)+(7-6)*7+(4-2))&"-"&IF(MONTH(DATE(2026,5,4)+(7-6)*7+(4-2))<10,"0","")&MONTH(DATE(2026,5,4)+(7-6)*7+(4-2))&"-"&IF(DAY(DATE(2026,5,4)+(7-6)*7+(4-2))<10,"0","")&DAY(DATE(2026,5,4)+(7-6)*7+(4-2)),'📅 Resumen Diario'!$C$5:$C$504,IF($F$2="TODOS", "*", $F$2))/SUMIFS('📅 Resumen Diario'!$J$5:$J$504,'📅 Resumen Diario'!$B$5:$B$504,YEAR(DATE(2026,5,4)+(7-6)*7+(4-2))&"-"&IF(MONTH(DATE(2026,5,4)+(7-6)*7+(4-2))<10,"0","")&MONTH(DATE(2026,5,4)+(7-6)*7+(4-2))&"-"&IF(DAY(DATE(2026,5,4)+(7-6)*7+(4-2))<10,"0","")&DAY(DATE(2026,5,4)+(7-6)*7+(4-2)),'📅 Resumen Diario'!$C$5:$C$504,IF($F$2="TODOS", "*", $F$2))),"—") -> 0.39543594 | E7: =IF(OR($C$2="TODOS",(YEAR(DATE(2026,5,4)+(7-6)*7+(5-2))&"-"&IF(MONTH(DATE(2026,5,4)+(7-6)*7+(5-2))<10,"0","")&MONTH(DATE(2026,5,4)+(7-6)*7+(5-2)))=$C$2),IF(SUMIFS('📅 Resumen Diario'!$J$5:$J$504,'📅 Resumen Diario'!$B$5:$B$504,YEAR(DATE(2026,5,4)+(7-6)*7+(5-2))&"-"&IF(MONTH(DATE(2026,5,4)+(7-6)*7+(5-2))<10,"0","")&MONTH(DATE(2026,5,4)+(7-6)*7+(5-2))&"-"&IF(DAY(DATE(2026,5,4)+(7-6)*7+(5-2))<10,"0","")&DAY(DATE(2026,5,4)+(7-6)*7+(5-2)),'📅 Resumen Diario'!$C$5:$C$504,IF($F$2="TODOS", "*", $F$2))=0,"—",SUMIFS('📅 Resumen Diario'!$Q$5:$Q$504,'📅 Resumen Diario'!$B$5:$B$504,YEAR(DATE(2026,5,4)+(7-6)*7+(5-2))&"-"&IF(MONTH(DATE(2026,5,4)+(7-6)*7+(5-2))<10,"0","")&MONTH(DATE(2026,5,4)+(7-6)*7+(5-2))&"-"&IF(DAY(DATE(2026,5,4)+(7-6)*7+(5-2))<10,"0","")&DAY(DATE(2026,5,4)+(7-6)*7+(5-2)),'📅 Resumen Diario'!$C$5:$C$504,IF($F$2="TODOS", "*", $F$2))/SUMIFS('📅 Resumen Diario'!$J$5:$J$504,'📅 Resumen Diario'!$B$5:$B$504,YEAR(DATE(2026,5,4)+(7-6)*7+(5-2))&"-"&IF(MONTH(DATE(2026,5,4)+(7-6)*7+(5-2))<10,"0","")&MONTH(DATE(2026,5,4)+(7-6)*7+(5-2))&"-"&IF(DAY(DATE(2026,5,4)+(7-6)*7+(5-2))<10,"0","")&DAY(DATE(2026,5,4)+(7-6)*7+(5-2)),'📅 Resumen Diario'!$C$5:$C$504,IF($F$2="TODOS", "*", $F$2))),"—") -> 0.42242801 | F7: =IF(OR($C$2="TODOS",(YEAR(DATE(2026,5,4)+(7-6)*7+(6-2))&"-"&IF(MONTH(DATE(2026,5,4)+(7-6)*7+(6-2))<10,"0","")&MONTH(DATE(2026,5,4)+(7-6)*7+(6-2)))=$C$2),IF(SUMIFS('📅 Resumen Diario'!$J$5:$J$504,'📅 Resumen Diario'!$B$5:$B$504,YEAR(DATE(2026,5,4)+(7-6)*7+(6-2))&"-"&IF(MONTH(DATE(2026,5,4)+(7-6)*7+(6-2))<10,"0","")&MONTH(DATE(2026,5,4)+(7-6)*7+(6-2))&"-"&IF(DAY(DATE(2026,5,4)+(7-6)*7+(6-2))<10,"0","")&DAY(DATE(2026,5,4)+(7-6)*7+(6-2)),'📅 Resumen Diario'!$C$5:$C$504,IF($F$2="TODOS", "*", $F$2))=0,"—",SUMIFS('📅 Resumen Diario'!$Q$5:$Q$504,'📅 Resumen Diario'!$B$5:$B$504,YEAR(DATE(2026,5,4)+(7-6)*7+(6-2))&"-"&IF(MONTH(DATE(2026,5,4)+(7-6)*7+(6-2))<10,"0","")&MONTH(DATE(2026,5,4)+(7-6)*7+(6-2))&"-"&IF(DAY(DATE(2026,5,4)+(7-6)*7+(6-2))<10,"0","")&DAY(DATE(2026,5,4)+(7-6)*7+(6-2)),'📅 Resumen Diario'!$C$5:$C$504,IF($F$2="TODOS", "*", $F$2))/SUMIFS('📅 Resumen Diario'!$J$5:$J$504,'📅 Resumen Diario'!$B$5:$B$504,YEAR(DATE(2026,5,4)+(7-6)*7+(6-2))&"-"&IF(MONTH(DATE(2026,5,4)+(7-6)*7+(6-2))<10,"0","")&MONTH(DATE(2026,5,4)+(7-6)*7+(6-2))&"-"&IF(DAY(DATE(2026,5,4)+(7-6)*7+(6-2))<10,"0","")&DAY(DATE(2026,5,4)+(7-6)*7+(6-2)),'📅 Resumen Diario'!$C$5:$C$504,IF($F$2="TODOS", "*", $F$2))),"—") -> 0.3586454 | G7: =IF(OR($C$2="TODOS",(YEAR(DATE(2026,5,4)+(7-6)*7+(7-2))&"-"&IF(MONTH(DATE(2026,5,4)+(7-6)*7+(7-2))<10,"0","")&MONTH(DATE(2026,5,4)+(7-6)*7+(7-2)))=$C$2),IF(SUMIFS('📅 Resumen Diario'!$J$5:$J$504,'📅 Resumen Diario'!$B$5:$B$504,YEAR(DATE(2026,5,4)+(7-6)*7+(7-2))&"-"&IF(MONTH(DATE(2026,5,4)+(7-6)*7+(7-2))<10,"0","")&MONTH(DATE(2026,5,4)+(7-6)*7+(7-2))&"-"&IF(DAY(DATE(2026,5,4)+(7-6)*7+(7-2))<10,"0","")&DAY(DATE(2026,5,4)+(7-6)*7+(7-2)),'📅 Resumen Diario'!$C$5:$C$504,IF($F$2="TODOS", "*", $F$2))=0,"—",SUMIFS('📅 Resumen Diario'!$Q$5:$Q$504,'📅 Resumen Diario'!$B$5:$B$504,YEAR(DATE(2026,5,4)+(7-6)*7+(7-2))&"-"&IF(MONTH(DATE(2026,5,4)+(7-6)*7+(7-2))<10,"0","")&MONTH(DATE(2026,5,4)+(7-6)*7+(7-2))&"-"&IF(DAY(DATE(2026,5,4)+(7-6)*7+(7-2))<10,"0","")&DAY(DATE(2026,5,4)+(7-6)*7+(7-2)),'📅 Resumen Diario'!$C$5:$C$504,IF($F$2="TODOS", "*", $F$2))/SUMIFS('📅 Resumen Diario'!$J$5:$J$504,'📅 Resumen Diario'!$B$5:$B$504,YEAR(DATE(2026,5,4)+(7-6)*7+(7-2))&"-"&IF(MONTH(DATE(2026,5,4)+(7-6)*7+(7-2))<10,"0","")&MONTH(DATE(2026,5,4)+(7-6)*7+(7-2))&"-"&IF(DAY(DATE(2026,5,4)+(7-6)*7+(7-2))<10,"0","")&DAY(DATE(2026,5,4)+(7-6)*7+(7-2)),'📅 Resumen Diario'!$C$5:$C$504,IF($F$2="TODOS", "*", $F$2))),"—") -> -0.97151944 | H7: =IF(OR($C$2="TODOS",(YEAR(DATE(2026,5,4)+(7-6)*7+(8-2))&"-"&IF(MONTH(DATE(2026,5,4)+(7-6)*7+(8-2))<10,"0","")&MONTH(DATE(2026,5,4)+(7-6)*7+(8-2)))=$C$2),IF(SUMIFS('📅 Resumen Diario'!$J$5:$J$504,'📅 Resumen Diario'!$B$5:$B$504,YEAR(DATE(2026,5,4)+(7-6)*7+(8-2))&"-"&IF(MONTH(DATE(2026,5,4)+(7-6)*7+(8-2))<10,"0","")&MONTH(DATE(2026,5,4)+(7-6)*7+(8-2))&"-"&IF(DAY(DATE(2026,5,4)+(7-6)*7+(8-2))<10,"0","")&DAY(DATE(2026,5,4)+(7-6)*7+(8-2)),'📅 Resumen Diario'!$C$5:$C$504,IF($F$2="TODOS", "*", $F$2))=0,"—",SUMIFS('📅 Resumen Diario'!$Q$5:$Q$504,'📅 Resumen Diario'!$B$5:$B$504,YEAR(DATE(2026,5,4)+(7-6)*7+(8-2))&"-"&IF(MONTH(DATE(2026,5,4)+(7-6)*7+(8-2))<10,"0","")&MONTH(DATE(2026,5,4)+(7-6)*7+(8-2))&"-"&IF(DAY(DATE(2026,5,4)+(7-6)*7+(8-2))<10,"0","")&DAY(DATE(2026,5,4)+(7-6)*7+(8-2)),'📅 Resumen Diario'!$C$5:$C$504,IF($F$2="TODOS", "*", $F$2))/SUMIFS('📅 Resumen Diario'!$J$5:$J$504,'📅 Resumen Diario'!$B$5:$B$504,YEAR(DATE(2026,5,4)+(7-6)*7+(8-2))&"-"&IF(MONTH(DATE(2026,5,4)+(7-6)*7+(8-2))<10,"0","")&MONTH(DATE(2026,5,4)+(7-6)*7+(8-2))&"-"&IF(DAY(DATE(2026,5,4)+(7-6)*7+(8-2))<10,"0","")&DAY(DATE(2026,5,4)+(7-6)*7+(8-2)),'📅 Resumen Diario'!$C$5:$C$504,IF($F$2="TODOS", "*", $F$2))),"—") -> 0.42466724
A8: S21 | B8: =IF(OR($C$2="TODOS",(YEAR(DATE(2026,5,4)+(8-6)*7+(2-2))&"-"&IF(MONTH(DATE(2026,5,4)+(8-6)*7+(2-2))<10,"0","")&MONTH(DATE(2026,5,4)+(8-6)*7+(2-2)))=$C$2),IF(SUMIFS('📅 Resumen Diario'!$J$5:$J$504,'📅 Resumen Diario'!$B$5:$B$504,YEAR(DATE(2026,5,4)+(8-6)*7+(2-2))&"-"&IF(MONTH(DATE(2026,5,4)+(8-6)*7+(2-2))<10,"0","")&MONTH(DATE(2026,5,4)+(8-6)*7+(2-2))&"-"&IF(DAY(DATE(2026,5,4)+(8-6)*7+(2-2))<10,"0","")&DAY(DATE(2026,5,4)+(8-6)*7+(2-2)),'📅 Resumen Diario'!$C$5:$C$504,IF($F$2="TODOS", "*", $F$2))=0,"—",SUMIFS('📅 Resumen Diario'!$Q$5:$Q$504,'📅 Resumen Diario'!$B$5:$B$504,YEAR(DATE(2026,5,4)+(8-6)*7+(2-2))&"-"&IF(MONTH(DATE(2026,5,4)+(8-6)*7+(2-2))<10,"0","")&MONTH(DATE(2026,5,4)+(8-6)*7+(2-2))&"-"&IF(DAY(DATE(2026,5,4)+(8-6)*7+(2-2))<10,"0","")&DAY(DATE(2026,5,4)+(8-6)*7+(2-2)),'📅 Resumen Diario'!$C$5:$C$504,IF($F$2="TODOS", "*", $F$2))/SUMIFS('📅 Resumen Diario'!$J$5:$J$504,'📅 Resumen Diario'!$B$5:$B$504,YEAR(DATE(2026,5,4)+(8-6)*7+(2-2))&"-"&IF(MONTH(DATE(2026,5,4)+(8-6)*7+(2-2))<10,"0","")&MONTH(DATE(2026,5,4)+(8-6)*7+(2-2))&"-"&IF(DAY(DATE(2026,5,4)+(8-6)*7+(2-2))<10,"0","")&DAY(DATE(2026,5,4)+(8-6)*7+(2-2)),'📅 Resumen Diario'!$C$5:$C$504,IF($F$2="TODOS", "*", $F$2))),"—") -> 0.35893686 | C8: =IF(OR($C$2="TODOS",(YEAR(DATE(2026,5,4)+(8-6)*7+(3-2))&"-"&IF(MONTH(DATE(2026,5,4)+(8-6)*7+(3-2))<10,"0","")&MONTH(DATE(2026,5,4)+(8-6)*7+(3-2)))=$C$2),IF(SUMIFS('📅 Resumen Diario'!$J$5:$J$504,'📅 Resumen Diario'!$B$5:$B$504,YEAR(DATE(2026,5,4)+(8-6)*7+(3-2))&"-"&IF(MONTH(DATE(2026,5,4)+(8-6)*7+(3-2))<10,"0","")&MONTH(DATE(2026,5,4)+(8-6)*7+(3-2))&"-"&IF(DAY(DATE(2026,5,4)+(8-6)*7+(3-2))<10,"0","")&DAY(DATE(2026,5,4)+(8-6)*7+(3-2)),'📅 Resumen Diario'!$C$5:$C$504,IF($F$2="TODOS", "*", $F$2))=0,"—",SUMIFS('📅 Resumen Diario'!$Q$5:$Q$504,'📅 Resumen Diario'!$B$5:$B$504,YEAR(DATE(2026,5,4)+(8-6)*7+(3-2))&"-"&IF(MONTH(DATE(2026,5,4)+(8-6)*7+(3-2))<10,"0","")&MONTH(DATE(2026,5,4)+(8-6)*7+(3-2))&"-"&IF(DAY(DATE(2026,5,4)+(8-6)*7+(3-2))<10,"0","")&DAY(DATE(2026,5,4)+(8-6)*7+(3-2)),'📅 Resumen Diario'!$C$5:$C$504,IF($F$2="TODOS", "*", $F$2))/SUMIFS('📅 Resumen Diario'!$J$5:$J$504,'📅 Resumen Diario'!$B$5:$B$504,YEAR(DATE(2026,5,4)+(8-6)*7+(3-2))&"-"&IF(MONTH(DATE(2026,5,4)+(8-6)*7+(3-2))<10,"0","")&MONTH(DATE(2026,5,4)+(8-6)*7+(3-2))&"-"&IF(DAY(DATE(2026,5,4)+(8-6)*7+(3-2))<10,"0","")&DAY(DATE(2026,5,4)+(8-6)*7+(3-2)),'📅 Resumen Diario'!$C$5:$C$504,IF($F$2="TODOS", "*", $F$2))),"—") -> 0.6075232 | D8: =IF(OR($C$2="TODOS",(YEAR(DATE(2026,5,4)+(8-6)*7+(4-2))&"-"&IF(MONTH(DATE(2026,5,4)+(8-6)*7+(4-2))<10,"0","")&MONTH(DATE(2026,5,4)+(8-6)*7+(4-2)))=$C$2),IF(SUMIFS('📅 Resumen Diario'!$J$5:$J$504,'📅 Resumen Diario'!$B$5:$B$504,YEAR(DATE(2026,5,4)+(8-6)*7+(4-2))&"-"&IF(MONTH(DATE(2026,5,4)+(8-6)*7+(4-2))<10,"0","")&MONTH(DATE(2026,5,4)+(8-6)*7+(4-2))&"-"&IF(DAY(DATE(2026,5,4)+(8-6)*7+(4-2))<10,"0","")&DAY(DATE(2026,5,4)+(8-6)*7+(4-2)),'📅 Resumen Diario'!$C$5:$C$504,IF($F$2="TODOS", "*", $F$2))=0,"—",SUMIFS('📅 Resumen Diario'!$Q$5:$Q$504,'📅 Resumen Diario'!$B$5:$B$504,YEAR(DATE(2026,5,4)+(8-6)*7+(4-2))&"-"&IF(MONTH(DATE(2026,5,4)+(8-6)*7+(4-2))<10,"0","")&MONTH(DATE(2026,5,4)+(8-6)*7+(4-2))&"-"&IF(DAY(DATE(2026,5,4)+(8-6)*7+(4-2))<10,"0","")&DAY(DATE(2026,5,4)+(8-6)*7+(4-2)),'📅 Resumen Diario'!$C$5:$C$504,IF($F$2="TODOS", "*", $F$2))/SUMIFS('📅 Resumen Diario'!$J$5:$J$504,'📅 Resumen Diario'!$B$5:$B$504,YEAR(DATE(2026,5,4)+(8-6)*7+(4-2))&"-"&IF(MONTH(DATE(2026,5,4)+(8-6)*7+(4-2))<10,"0","")&MONTH(DATE(2026,5,4)+(8-6)*7+(4-2))&"-"&IF(DAY(DATE(2026,5,4)+(8-6)*7+(4-2))<10,"0","")&DAY(DATE(2026,5,4)+(8-6)*7+(4-2)),'📅 Resumen Diario'!$C$5:$C$504,IF($F$2="TODOS", "*", $F$2))),"—") -> -0.48527438 | E8: =IF(OR($C$2="TODOS",(YEAR(DATE(2026,5,4)+(8-6)*7+(5-2))&"-"&IF(MONTH(DATE(2026,5,4)+(8-6)*7+(5-2))<10,"0","")&MONTH(DATE(2026,5,4)+(8-6)*7+(5-2)))=$C$2),IF(SUMIFS('📅 Resumen Diario'!$J$5:$J$504,'📅 Resumen Diario'!$B$5:$B$504,YEAR(DATE(2026,5,4)+(8-6)*7+(5-2))&"-"&IF(MONTH(DATE(2026,5,4)+(8-6)*7+(5-2))<10,"0","")&MONTH(DATE(2026,5,4)+(8-6)*7+(5-2))&"-"&IF(DAY(DATE(2026,5,4)+(8-6)*7+(5-2))<10,"0","")&DAY(DATE(2026,5,4)+(8-6)*7+(5-2)),'📅 Resumen Diario'!$C$5:$C$504,IF($F$2="TODOS", "*", $F$2))=0,"—",SUMIFS('📅 Resumen Diario'!$Q$5:$Q$504,'📅 Resumen Diario'!$B$5:$B$504,YEAR(DATE(2026,5,4)+(8-6)*7+(5-2))&"-"&IF(MONTH(DATE(2026,5,4)+(8-6)*7+(5-2))<10,"0","")&MONTH(DATE(2026,5,4)+(8-6)*7+(5-2))&"-"&IF(DAY(DATE(2026,5,4)+(8-6)*7+(5-2))<10,"0","")&DAY(DATE(2026,5,4)+(8-6)*7+(5-2)),'📅 Resumen Diario'!$C$5:$C$504,IF($F$2="TODOS", "*", $F$2))/SUMIFS('📅 Resumen Diario'!$J$5:$J$504,'📅 Resumen Diario'!$B$5:$B$504,YEAR(DATE(2026,5,4)+(8-6)*7+(5-2))&"-"&IF(MONTH(DATE(2026,5,4)+(8-6)*7+(5-2))<10,"0","")&MONTH(DATE(2026,5,4)+(8-6)*7+(5-2))&"-"&IF(DAY(DATE(2026,5,4)+(8-6)*7+(5-2))<10,"0","")&DAY(DATE(2026,5,4)+(8-6)*7+(5-2)),'📅 Resumen Diario'!$C$5:$C$504,IF($F$2="TODOS", "*", $F$2))),"—") -> 0.24511118 | F8: =IF(OR($C$2="TODOS",(YEAR(DATE(2026,5,4)+(8-6)*7+(6-2))&"-"&IF(MONTH(DATE(2026,5,4)+(8-6)*7+(6-2))<10,"0","")&MONTH(DATE(2026,5,4)+(8-6)*7+(6-2)))=$C$2),IF(SUMIFS('📅 Resumen Diario'!$J$5:$J$504,'📅 Resumen Diario'!$B$5:$B$504,YEAR(DATE(2026,5,4)+(8-6)*7+(6-2))&"-"&IF(MONTH(DATE(2026,5,4)+(8-6)*7+(6-2))<10,"0","")&MONTH(DATE(2026,5,4)+(8-6)*7+(6-2))&"-"&IF(DAY(DATE(2026,5,4)+(8-6)*7+(6-2))<10,"0","")&DAY(DATE(2026,5,4)+(8-6)*7+(6-2)),'📅 Resumen Diario'!$C$5:$C$504,IF($F$2="TODOS", "*", $F$2))=0,"—",SUMIFS('📅 Resumen Diario'!$Q$5:$Q$504,'📅 Resumen Diario'!$B$5:$B$504,YEAR(DATE(2026,5,4)+(8-6)*7+(6-2))&"-"&IF(MONTH(DATE(2026,5,4)+(8-6)*7+(6-2))<10,"0","")&MONTH(DATE(2026,5,4)+(8-6)*7+(6-2))&"-"&IF(DAY(DATE(2026,5,4)+(8-6)*7+(6-2))<10,"0","")&DAY(DATE(2026,5,4)+(8-6)*7+(6-2)),'📅 Resumen Diario'!$C$5:$C$504,IF($F$2="TODOS", "*", $F$2))/SUMIFS('📅 Resumen Diario'!$J$5:$J$504,'📅 Resumen Diario'!$B$5:$B$504,YEAR(DATE(2026,5,4)+(8-6)*7+(6-2))&"-"&IF(MONTH(DATE(2026,5,4)+(8-6)*7+(6-2))<10,"0","")&MONTH(DATE(2026,5,4)+(8-6)*7+(6-2))&"-"&IF(DAY(DATE(2026,5,4)+(8-6)*7+(6-2))<10,"0","")&DAY(DATE(2026,5,4)+(8-6)*7+(6-2)),'📅 Resumen Diario'!$C$5:$C$504,IF($F$2="TODOS", "*", $F$2))),"—") -> 0.43539184 | G8: =IF(OR($C$2="TODOS",(YEAR(DATE(2026,5,4)+(8-6)*7+(7-2))&"-"&IF(MONTH(DATE(2026,5,4)+(8-6)*7+(7-2))<10,"0","")&MONTH(DATE(2026,5,4)+(8-6)*7+(7-2)))=$C$2),IF(SUMIFS('📅 Resumen Diario'!$J$5:$J$504,'📅 Resumen Diario'!$B$5:$B$504,YEAR(DATE(2026,5,4)+(8-6)*7+(7-2))&"-"&IF(MONTH(DATE(2026,5,4)+(8-6)*7+(7-2))<10,"0","")&MONTH(DATE(2026,5,4)+(8-6)*7+(7-2))&"-"&IF(DAY(DATE(2026,5,4)+(8-6)*7+(7-2))<10,"0","")&DAY(DATE(2026,5,4)+(8-6)*7+(7-2)),'📅 Resumen Diario'!$C$5:$C$504,IF($F$2="TODOS", "*", $F$2))=0,"—",SUMIFS('📅 Resumen Diario'!$Q$5:$Q$504,'📅 Resumen Diario'!$B$5:$B$504,YEAR(DATE(2026,5,4)+(8-6)*7+(7-2))&"-"&IF(MONTH(DATE(2026,5,4)+(8-6)*7+(7-2))<10,"0","")&MONTH(DATE(2026,5,4)+(8-6)*7+(7-2))&"-"&IF(DAY(DATE(2026,5,4)+(8-6)*7+(7-2))<10,"0","")&DAY(DATE(2026,5,4)+(8-6)*7+(7-2)),'📅 Resumen Diario'!$C$5:$C$504,IF($F$2="TODOS", "*", $F$2))/SUMIFS('📅 Resumen Diario'!$J$5:$J$504,'📅 Resumen Diario'!$B$5:$B$504,YEAR(DATE(2026,5,4)+(8-6)*7+(7-2))&"-"&IF(MONTH(DATE(2026,5,4)+(8-6)*7+(7-2))<10,"0","")&MONTH(DATE(2026,5,4)+(8-6)*7+(7-2))&"-"&IF(DAY(DATE(2026,5,4)+(8-6)*7+(7-2))<10,"0","")&DAY(DATE(2026,5,4)+(8-6)*7+(7-2)),'📅 Resumen Diario'!$C$5:$C$504,IF($F$2="TODOS", "*", $F$2))),"—") -> -0.43975445 | H8: =IF(OR($C$2="TODOS",(YEAR(DATE(2026,5,4)+(8-6)*7+(8-2))&"-"&IF(MONTH(DATE(2026,5,4)+(8-6)*7+(8-2))<10,"0","")&MONTH(DATE(2026,5,4)+(8-6)*7+(8-2)))=$C$2),IF(SUMIFS('📅 Resumen Diario'!$J$5:$J$504,'📅 Resumen Diario'!$B$5:$B$504,YEAR(DATE(2026,5,4)+(8-6)*7+(8-2))&"-"&IF(MONTH(DATE(2026,5,4)+(8-6)*7+(8-2))<10,"0","")&MONTH(DATE(2026,5,4)+(8-6)*7+(8-2))&"-"&IF(DAY(DATE(2026,5,4)+(8-6)*7+(8-2))<10,"0","")&DAY(DATE(2026,5,4)+(8-6)*7+(8-2)),'📅 Resumen Diario'!$C$5:$C$504,IF($F$2="TODOS", "*", $F$2))=0,"—",SUMIFS('📅 Resumen Diario'!$Q$5:$Q$504,'📅 Resumen Diario'!$B$5:$B$504,YEAR(DATE(2026,5,4)+(8-6)*7+(8-2))&"-"&IF(MONTH(DATE(2026,5,4)+(8-6)*7+(8-2))<10,"0","")&MONTH(DATE(2026,5,4)+(8-6)*7+(8-2))&"-"&IF(DAY(DATE(2026,5,4)+(8-6)*7+(8-2))<10,"0","")&DAY(DATE(2026,5,4)+(8-6)*7+(8-2)),'📅 Resumen Diario'!$C$5:$C$504,IF($F$2="TODOS", "*", $F$2))/SUMIFS('📅 Resumen Diario'!$J$5:$J$504,'📅 Resumen Diario'!$B$5:$B$504,YEAR(DATE(2026,5,4)+(8-6)*7+(8-2))&"-"&IF(MONTH(DATE(2026,5,4)+(8-6)*7+(8-2))<10,"0","")&MONTH(DATE(2026,5,4)+(8-6)*7+(8-2))&"-"&IF(DAY(DATE(2026,5,4)+(8-6)*7+(8-2))<10,"0","")&DAY(DATE(2026,5,4)+(8-6)*7+(8-2)),'📅 Resumen Diario'!$C$5:$C$504,IF($F$2="TODOS", "*", $F$2))),"—") -> 0.37766613
A9: S22 | B9: =IF(OR($C$2="TODOS",(YEAR(DATE(2026,5,4)+(9-6)*7+(2-2))&"-"&IF(MONTH(DATE(2026,5,4)+(9-6)*7+(2-2))<10,"0","")&MONTH(DATE(2026,5,4)+(9-6)*7+(2-2)))=$C$2),IF(SUMIFS('📅 Resumen Diario'!$J$5:$J$504,'📅 Resumen Diario'!$B$5:$B$504,YEAR(DATE(2026,5,4)+(9-6)*7+(2-2))&"-"&IF(MONTH(DATE(2026,5,4)+(9-6)*7+(2-2))<10,"0","")&MONTH(DATE(2026,5,4)+(9-6)*7+(2-2))&"-"&IF(DAY(DATE(2026,5,4)+(9-6)*7+(2-2))<10,"0","")&DAY(DATE(2026,5,4)+(9-6)*7+(2-2)),'📅 Resumen Diario'!$C$5:$C$504,IF($F$2="TODOS", "*", $F$2))=0,"—",SUMIFS('📅 Resumen Diario'!$Q$5:$Q$504,'📅 Resumen Diario'!$B$5:$B$504,YEAR(DATE(2026,5,4)+(9-6)*7+(2-2))&"-"&IF(MONTH(DATE(2026,5,4)+(9-6)*7+(2-2))<10,"0","")&MONTH(DATE(2026,5,4)+(9-6)*7+(2-2))&"-"&IF(DAY(DATE(2026,5,4)+(9-6)*7+(2-2))<10,"0","")&DAY(DATE(2026,5,4)+(9-6)*7+(2-2)),'📅 Resumen Diario'!$C$5:$C$504,IF($F$2="TODOS", "*", $F$2))/SUMIFS('📅 Resumen Diario'!$J$5:$J$504,'📅 Resumen Diario'!$B$5:$B$504,YEAR(DATE(2026,5,4)+(9-6)*7+(2-2))&"-"&IF(MONTH(DATE(2026,5,4)+(9-6)*7+(2-2))<10,"0","")&MONTH(DATE(2026,5,4)+(9-6)*7+(2-2))&"-"&IF(DAY(DATE(2026,5,4)+(9-6)*7+(2-2))<10,"0","")&DAY(DATE(2026,5,4)+(9-6)*7+(2-2)),'📅 Resumen Diario'!$C$5:$C$504,IF($F$2="TODOS", "*", $F$2))),"—") -> 0.18342793 | C9: =IF(OR($C$2="TODOS",(YEAR(DATE(2026,5,4)+(9-6)*7+(3-2))&"-"&IF(MONTH(DATE(2026,5,4)+(9-6)*7+(3-2))<10,"0","")&MONTH(DATE(2026,5,4)+(9-6)*7+(3-2)))=$C$2),IF(SUMIFS('📅 Resumen Diario'!$J$5:$J$504,'📅 Resumen Diario'!$B$5:$B$504,YEAR(DATE(2026,5,4)+(9-6)*7+(3-2))&"-"&IF(MONTH(DATE(2026,5,4)+(9-6)*7+(3-2))<10,"0","")&MONTH(DATE(2026,5,4)+(9-6)*7+(3-2))&"-"&IF(DAY(DATE(2026,5,4)+(9-6)*7+(3-2))<10,"0","")&DAY(DATE(2026,5,4)+(9-6)*7+(3-2)),'📅 Resumen Diario'!$C$5:$C$504,IF($F$2="TODOS", "*", $F$2))=0,"—",SUMIFS('📅 Resumen Diario'!$Q$5:$Q$504,'📅 Resumen Diario'!$B$5:$B$504,YEAR(DATE(2026,5,4)+(9-6)*7+(3-2))&"-"&IF(MONTH(DATE(2026,5,4)+(9-6)*7+(3-2))<10,"0","")&MONTH(DATE(2026,5,4)+(9-6)*7+(3-2))&"-"&IF(DAY(DATE(2026,5,4)+(9-6)*7+(3-2))<10,"0","")&DAY(DATE(2026,5,4)+(9-6)*7+(3-2)),'📅 Resumen Diario'!$C$5:$C$504,IF($F$2="TODOS", "*", $F$2))/SUMIFS('📅 Resumen Diario'!$J$5:$J$504,'📅 Resumen Diario'!$B$5:$B$504,YEAR(DATE(2026,5,4)+(9-6)*7+(3-2))&"-"&IF(MONTH(DATE(2026,5,4)+(9-6)*7+(3-2))<10,"0","")&MONTH(DATE(2026,5,4)+(9-6)*7+(3-2))&"-"&IF(DAY(DATE(2026,5,4)+(9-6)*7+(3-2))<10,"0","")&DAY(DATE(2026,5,4)+(9-6)*7+(3-2)),'📅 Resumen Diario'!$C$5:$C$504,IF($F$2="TODOS", "*", $F$2))),"—") -> -0.11167819 | D9: =IF(OR($C$2="TODOS",(YEAR(DATE(2026,5,4)+(9-6)*7+(4-2))&"-"&IF(MONTH(DATE(2026,5,4)+(9-6)*7+(4-2))<10,"0","")&MONTH(DATE(2026,5,4)+(9-6)*7+(4-2)))=$C$2),IF(SUMIFS('📅 Resumen Diario'!$J$5:$J$504,'📅 Resumen Diario'!$B$5:$B$504,YEAR(DATE(2026,5,4)+(9-6)*7+(4-2))&"-"&IF(MONTH(DATE(2026,5,4)+(9-6)*7+(4-2))<10,"0","")&MONTH(DATE(2026,5,4)+(9-6)*7+(4-2))&"-"&IF(DAY(DATE(2026,5,4)+(9-6)*7+(4-2))<10,"0","")&DAY(DATE(2026,5,4)+(9-6)*7+(4-2)),'📅 Resumen Diario'!$C$5:$C$504,IF($F$2="TODOS", "*", $F$2))=0,"—",SUMIFS('📅 Resumen Diario'!$Q$5:$Q$504,'📅 Resumen Diario'!$B$5:$B$504,YEAR(DATE(2026,5,4)+(9-6)*7+(4-2))&"-"&IF(MONTH(DATE(2026,5,4)+(9-6)*7+(4-2))<10,"0","")&MONTH(DATE(2026,5,4)+(9-6)*7+(4-2))&"-"&IF(DAY(DATE(2026,5,4)+(9-6)*7+(4-2))<10,"0","")&DAY(DATE(2026,5,4)+(9-6)*7+(4-2)),'📅 Resumen Diario'!$C$5:$C$504,IF($F$2="TODOS", "*", $F$2))/SUMIFS('📅 Resumen Diario'!$J$5:$J$504,'📅 Resumen Diario'!$B$5:$B$504,YEAR(DATE(2026,5,4)+(9-6)*7+(4-2))&"-"&IF(MONTH(DATE(2026,5,4)+(9-6)*7+(4-2))<10,"0","")&MONTH(DATE(2026,5,4)+(9-6)*7+(4-2))&"-"&IF(DAY(DATE(2026,5,4)+(9-6)*7+(4-2))<10,"0","")&DAY(DATE(2026,5,4)+(9-6)*7+(4-2)),'📅 Resumen Diario'!$C$5:$C$504,IF($F$2="TODOS", "*", $F$2))),"—") -> 0.046322274 | E9: =IF(OR($C$2="TODOS",(YEAR(DATE(2026,5,4)+(9-6)*7+(5-2))&"-"&IF(MONTH(DATE(2026,5,4)+(9-6)*7+(5-2))<10,"0","")&MONTH(DATE(2026,5,4)+(9-6)*7+(5-2)))=$C$2),IF(SUMIFS('📅 Resumen Diario'!$J$5:$J$504,'📅 Resumen Diario'!$B$5:$B$504,YEAR(DATE(2026,5,4)+(9-6)*7+(5-2))&"-"&IF(MONTH(DATE(2026,5,4)+(9-6)*7+(5-2))<10,"0","")&MONTH(DATE(2026,5,4)+(9-6)*7+(5-2))&"-"&IF(DAY(DATE(2026,5,4)+(9-6)*7+(5-2))<10,"0","")&DAY(DATE(2026,5,4)+(9-6)*7+(5-2)),'📅 Resumen Diario'!$C$5:$C$504,IF($F$2="TODOS", "*", $F$2))=0,"—",SUMIFS('📅 Resumen Diario'!$Q$5:$Q$504,'📅 Resumen Diario'!$B$5:$B$504,YEAR(DATE(2026,5,4)+(9-6)*7+(5-2))&"-"&IF(MONTH(DATE(2026,5,4)+(9-6)*7+(5-2))<10,"0","")&MONTH(DATE(2026,5,4)+(9-6)*7+(5-2))&"-"&IF(DAY(DATE(2026,5,4)+(9-6)*7+(5-2))<10,"0","")&DAY(DATE(2026,5,4)+(9-6)*7+(5-2)),'📅 Resumen Diario'!$C$5:$C$504,IF($F$2="TODOS", "*", $F$2))/SUMIFS('📅 Resumen Diario'!$J$5:$J$504,'📅 Resumen Diario'!$B$5:$B$504,YEAR(DATE(2026,5,4)+(9-6)*7+(5-2))&"-"&IF(MONTH(DATE(2026,5,4)+(9-6)*7+(5-2))<10,"0","")&MONTH(DATE(2026,5,4)+(9-6)*7+(5-2))&"-"&IF(DAY(DATE(2026,5,4)+(9-6)*7+(5-2))<10,"0","")&DAY(DATE(2026,5,4)+(9-6)*7+(5-2)),'📅 Resumen Diario'!$C$5:$C$504,IF($F$2="TODOS", "*", $F$2))),"—") -> 0.4864692 | F9: =IF(OR($C$2="TODOS",(YEAR(DATE(2026,5,4)+(9-6)*7+(6-2))&"-"&IF(MONTH(DATE(2026,5,4)+(9-6)*7+(6-2))<10,"0","")&MONTH(DATE(2026,5,4)+(9-6)*7+(6-2)))=$C$2),IF(SUMIFS('📅 Resumen Diario'!$J$5:$J$504,'📅 Resumen Diario'!$B$5:$B$504,YEAR(DATE(2026,5,4)+(9-6)*7+(6-2))&"-"&IF(MONTH(DATE(2026,5,4)+(9-6)*7+(6-2))<10,"0","")&MONTH(DATE(2026,5,4)+(9-6)*7+(6-2))&"-"&IF(DAY(DATE(2026,5,4)+(9-6)*7+(6-2))<10,"0","")&DAY(DATE(2026,5,4)+(9-6)*7+(6-2)),'📅 Resumen Diario'!$C$5:$C$504,IF($F$2="TODOS", "*", $F$2))=0,"—",SUMIFS('📅 Resumen Diario'!$Q$5:$Q$504,'📅 Resumen Diario'!$B$5:$B$504,YEAR(DATE(2026,5,4)+(9-6)*7+(6-2))&"-"&IF(MONTH(DATE(2026,5,4)+(9-6)*7+(6-2))<10,"0","")&MONTH(DATE(2026,5,4)+(9-6)*7+(6-2))&"-"&IF(DAY(DATE(2026,5,4)+(9-6)*7+(6-2))<10,"0","")&DAY(DATE(2026,5,4)+(9-6)*7+(6-2)),'📅 Resumen Diario'!$C$5:$C$504,IF($F$2="TODOS", "*", $F$2))/SUMIFS('📅 Resumen Diario'!$J$5:$J$504,'📅 Resumen Diario'!$B$5:$B$504,YEAR(DATE(2026,5,4)+(9-6)*7+(6-2))&"-"&IF(MONTH(DATE(2026,5,4)+(9-6)*7+(6-2))<10,"0","")&MONTH(DATE(2026,5,4)+(9-6)*7+(6-2))&"-"&IF(DAY(DATE(2026,5,4)+(9-6)*7+(6-2))<10,"0","")&DAY(DATE(2026,5,4)+(9-6)*7+(6-2)),'📅 Resumen Diario'!$C$5:$C$504,IF($F$2="TODOS", "*", $F$2))),"—") -> 0.40303071 | G9: =IF(OR($C$2="TODOS",(YEAR(DATE(2026,5,4)+(9-6)*7+(7-2))&"-"&IF(MONTH(DATE(2026,5,4)+(9-6)*7+(7-2))<10,"0","")&MONTH(DATE(2026,5,4)+(9-6)*7+(7-2)))=$C$2),IF(SUMIFS('📅 Resumen Diario'!$J$5:$J$504,'📅 Resumen Diario'!$B$5:$B$504,YEAR(DATE(2026,5,4)+(9-6)*7+(7-2))&"-"&IF(MONTH(DATE(2026,5,4)+(9-6)*7+(7-2))<10,"0","")&MONTH(DATE(2026,5,4)+(9-6)*7+(7-2))&"-"&IF(DAY(DATE(2026,5,4)+(9-6)*7+(7-2))<10,"0","")&DAY(DATE(2026,5,4)+(9-6)*7+(7-2)),'📅 Resumen Diario'!$C$5:$C$504,IF($F$2="TODOS", "*", $F$2))=0,"—",SUMIFS('📅 Resumen Diario'!$Q$5:$Q$504,'📅 Resumen Diario'!$B$5:$B$504,YEAR(DATE(2026,5,4)+(9-6)*7+(7-2))&"-"&IF(MONTH(DATE(2026,5,4)+(9-6)*7+(7-2))<10,"0","")&MONTH(DATE(2026,5,4)+(9-6)*7+(7-2))&"-"&IF(DAY(DATE(2026,5,4)+(9-6)*7+(7-2))<10,"0","")&DAY(DATE(2026,5,4)+(9-6)*7+(7-2)),'📅 Resumen Diario'!$C$5:$C$504,IF($F$2="TODOS", "*", $F$2))/SUMIFS('📅 Resumen Diario'!$J$5:$J$504,'📅 Resumen Diario'!$B$5:$B$504,YEAR(DATE(2026,5,4)+(9-6)*7+(7-2))&"-"&IF(MONTH(DATE(2026,5,4)+(9-6)*7+(7-2))<10,"0","")&MONTH(DATE(2026,5,4)+(9-6)*7+(7-2))&"-"&IF(DAY(DATE(2026,5,4)+(9-6)*7+(7-2))<10,"0","")&DAY(DATE(2026,5,4)+(9-6)*7+(7-2)),'📅 Resumen Diario'!$C$5:$C$504,IF($F$2="TODOS", "*", $F$2))),"—") -> -0.94098587 | H9: =IF(OR($C$2="TODOS",(YEAR(DATE(2026,5,4)+(9-6)*7+(8-2))&"-"&IF(MONTH(DATE(2026,5,4)+(9-6)*7+(8-2))<10,"0","")&MONTH(DATE(2026,5,4)+(9-6)*7+(8-2)))=$C$2),IF(SUMIFS('📅 Resumen Diario'!$J$5:$J$504,'📅 Resumen Diario'!$B$5:$B$504,YEAR(DATE(2026,5,4)+(9-6)*7+(8-2))&"-"&IF(MONTH(DATE(2026,5,4)+(9-6)*7+(8-2))<10,"0","")&MONTH(DATE(2026,5,4)+(9-6)*7+(8-2))&"-"&IF(DAY(DATE(2026,5,4)+(9-6)*7+(8-2))<10,"0","")&DAY(DATE(2026,5,4)+(9-6)*7+(8-2)),'📅 Resumen Diario'!$C$5:$C$504,IF($F$2="TODOS", "*", $F$2))=0,"—",SUMIFS('📅 Resumen Diario'!$Q$5:$Q$504,'📅 Resumen Diario'!$B$5:$B$504,YEAR(DATE(2026,5,4)+(9-6)*7+(8-2))&"-"&IF(MONTH(DATE(2026,5,4)+(9-6)*7+(8-2))<10,"0","")&MONTH(DATE(2026,5,4)+(9-6)*7+(8-2))&"-"&IF(DAY(DATE(2026,5,4)+(9-6)*7+(8-2))<10,"0","")&DAY(DATE(2026,5,4)+(9-6)*7+(8-2)),'📅 Resumen Diario'!$C$5:$C$504,IF($F$2="TODOS", "*", $F$2))/SUMIFS('📅 Resumen Diario'!$J$5:$J$504,'📅 Resumen Diario'!$B$5:$B$504,YEAR(DATE(2026,5,4)+(9-6)*7+(8-2))&"-"&IF(MONTH(DATE(2026,5,4)+(9-6)*7+(8-2))<10,"0","")&MONTH(DATE(2026,5,4)+(9-6)*7+(8-2))&"-"&IF(DAY(DATE(2026,5,4)+(9-6)*7+(8-2))<10,"0","")&DAY(DATE(2026,5,4)+(9-6)*7+(8-2)),'📅 Resumen Diario'!$C$5:$C$504,IF($F$2="TODOS", "*", $F$2))),"—") -> 0.48083048
A10: S23 | B10: =IF(OR($C$2="TODOS",(YEAR(DATE(2026,5,4)+(10-6)*7+(2-2))&"-"&IF(MONTH(DATE(2026,5,4)+(10-6)*7+(2-2))<10,"0","")&MONTH(DATE(2026,5,4)+(10-6)*7+(2-2)))=$C$2),IF(SUMIFS('📅 Resumen Diario'!$J$5:$J$504,'📅 Resumen Diario'!$B$5:$B$504,YEAR(DATE(2026,5,4)+(10-6)*7+(2-2))&"-"&IF(MONTH(DATE(2026,5,4)+(10-6)*7+(2-2))<10,"0","")&MONTH(DATE(2026,5,4)+(10-6)*7+(2-2))&"-"&IF(DAY(DATE(2026,5,4)+(10-6)*7+(2-2))<10,"0","")&DAY(DATE(2026,5,4)+(10-6)*7+(2-2)),'📅 Resumen Diario'!$C$5:$C$504,IF($F$2="TODOS", "*", $F$2))=0,"—",SUMIFS('📅 Resumen Diario'!$Q$5:$Q$504,'📅 Resumen Diario'!$B$5:$B$504,YEAR(DATE(2026,5,4)+(10-6)*7+(2-2))&"-"&IF(MONTH(DATE(2026,5,4)+(10-6)*7+(2-2))<10,"0","")&MONTH(DATE(2026,5,4)+(10-6)*7+(2-2))&"-"&IF(DAY(DATE(2026,5,4)+(10-6)*7+(2-2))<10,"0","")&DAY(DATE(2026,5,4)+(10-6)*7+(2-2)),'📅 Resumen Diario'!$C$5:$C$504,IF($F$2="TODOS", "*", $F$2))/SUMIFS('📅 Resumen Diario'!$J$5:$J$504,'📅 Resumen Diario'!$B$5:$B$504,YEAR(DATE(2026,5,4)+(10-6)*7+(2-2))&"-"&IF(MONTH(DATE(2026,5,4)+(10-6)*7+(2-2))<10,"0","")&MONTH(DATE(2026,5,4)+(10-6)*7+(2-2))&"-"&IF(DAY(DATE(2026,5,4)+(10-6)*7+(2-2))<10,"0","")&DAY(DATE(2026,5,4)+(10-6)*7+(2-2)),'📅 Resumen Diario'!$C$5:$C$504,IF($F$2="TODOS", "*", $F$2))),"—") -> -0.44466871 | C10: =IF(OR($C$2="TODOS",(YEAR(DATE(2026,5,4)+(10-6)*7+(3-2))&"-"&IF(MONTH(DATE(2026,5,4)+(10-6)*7+(3-2))<10,"0","")&MONTH(DATE(2026,5,4)+(10-6)*7+(3-2)))=$C$2),IF(SUMIFS('📅 Resumen Diario'!$J$5:$J$504,'📅 Resumen Diario'!$B$5:$B$504,YEAR(DATE(2026,5,4)+(10-6)*7+(3-2))&"-"&IF(MONTH(DATE(2026,5,4)+(10-6)*7+(3-2))<10,"0","")&MONTH(DATE(2026,5,4)+(10-6)*7+(3-2))&"-"&IF(DAY(DATE(2026,5,4)+(10-6)*7+(3-2))<10,"0","")&DAY(DATE(2026,5,4)+(10-6)*7+(3-2)),'📅 Resumen Diario'!$C$5:$C$504,IF($F$2="TODOS", "*", $F$2))=0,"—",SUMIFS('📅 Resumen Diario'!$Q$5:$Q$504,'📅 Resumen Diario'!$B$5:$B$504,YEAR(DATE(2026,5,4)+(10-6)*7+(3-2))&"-"&IF(MONTH(DATE(2026,5,4)+(10-6)*7+(3-2))<10,"0","")&MONTH(DATE(2026,5,4)+(10-6)*7+(3-2))&"-"&IF(DAY(DATE(2026,5,4)+(10-6)*7+(3-2))<10,"0","")&DAY(DATE(2026,5,4)+(10-6)*7+(3-2)),'📅 Resumen Diario'!$C$5:$C$504,IF($F$2="TODOS", "*", $F$2))/SUMIFS('📅 Resumen Diario'!$J$5:$J$504,'📅 Resumen Diario'!$B$5:$B$504,YEAR(DATE(2026,5,4)+(10-6)*7+(3-2))&"-"&IF(MONTH(DATE(2026,5,4)+(10-6)*7+(3-2))<10,"0","")&MONTH(DATE(2026,5,4)+(10-6)*7+(3-2))&"-"&IF(DAY(DATE(2026,5,4)+(10-6)*7+(3-2))<10,"0","")&DAY(DATE(2026,5,4)+(10-6)*7+(3-2)),'📅 Resumen Diario'!$C$5:$C$504,IF($F$2="TODOS", "*", $F$2))),"—") -> 0.3814771 | D10: =IF(OR($C$2="TODOS",(YEAR(DATE(2026,5,4)+(10-6)*7+(4-2))&"-"&IF(MONTH(DATE(2026,5,4)+(10-6)*7+(4-2))<10,"0","")&MONTH(DATE(2026,5,4)+(10-6)*7+(4-2)))=$C$2),IF(SUMIFS('📅 Resumen Diario'!$J$5:$J$504,'📅 Resumen Diario'!$B$5:$B$504,YEAR(DATE(2026,5,4)+(10-6)*7+(4-2))&"-"&IF(MONTH(DATE(2026,5,4)+(10-6)*7+(4-2))<10,"0","")&MONTH(DATE(2026,5,4)+(10-6)*7+(4-2))&"-"&IF(DAY(DATE(2026,5,4)+(10-6)*7+(4-2))<10,"0","")&DAY(DATE(2026,5,4)+(10-6)*7+(4-2)),'📅 Resumen Diario'!$C$5:$C$504,IF($F$2="TODOS", "*", $F$2))=0,"—",SUMIFS('📅 Resumen Diario'!$Q$5:$Q$504,'📅 Resumen Diario'!$B$5:$B$504,YEAR(DATE(2026,5,4)+(10-6)*7+(4-2))&"-"&IF(MONTH(DATE(2026,5,4)+(10-6)*7+(4-2))<10,"0","")&MONTH(DATE(2026,5,4)+(10-6)*7+(4-2))&"-"&IF(DAY(DATE(2026,5,4)+(10-6)*7+(4-2))<10,"0","")&DAY(DATE(2026,5,4)+(10-6)*7+(4-2)),'📅 Resumen Diario'!$C$5:$C$504,IF($F$2="TODOS", "*", $F$2))/SUMIFS('📅 Resumen Diario'!$J$5:$J$504,'📅 Resumen Diario'!$B$5:$B$504,YEAR(DATE(2026,5,4)+(10-6)*7+(4-2))&"-"&IF(MONTH(DATE(2026,5,4)+(10-6)*7+(4-2))<10,"0","")&MONTH(DATE(2026,5,4)+(10-6)*7+(4-2))&"-"&IF(DAY(DATE(2026,5,4)+(10-6)*7+(4-2))<10,"0","")&DAY(DATE(2026,5,4)+(10-6)*7+(4-2)),'📅 Resumen Diario'!$C$5:$C$504,IF($F$2="TODOS", "*", $F$2))),"—") -> 0.46563376 | E10: =IF(OR($C$2="TODOS",(YEAR(DATE(2026,5,4)+(10-6)*7+(5-2))&"-"&IF(MONTH(DATE(2026,5,4)+(10-6)*7+(5-2))<10,"0","")&MONTH(DATE(2026,5,4)+(10-6)*7+(5-2)))=$C$2),IF(SUMIFS('📅 Resumen Diario'!$J$5:$J$504,'📅 Resumen Diario'!$B$5:$B$504,YEAR(DATE(2026,5,4)+(10-6)*7+(5-2))&"-"&IF(MONTH(DATE(2026,5,4)+(10-6)*7+(5-2))<10,"0","")&MONTH(DATE(2026,5,4)+(10-6)*7+(5-2))&"-"&IF(DAY(DATE(2026,5,4)+(10-6)*7+(5-2))<10,"0","")&DAY(DATE(2026,5,4)+(10-6)*7+(5-2)),'📅 Resumen Diario'!$C$5:$C$504,IF($F$2="TODOS", "*", $F$2))=0,"—",SUMIFS('📅 Resumen Diario'!$Q$5:$Q$504,'📅 Resumen Diario'!$B$5:$B$504,YEAR(DATE(2026,5,4)+(10-6)*7+(5-2))&"-"&IF(MONTH(DATE(2026,5,4)+(10-6)*7+(5-2))<10,"0","")&MONTH(DATE(2026,5,4)+(10-6)*7+(5-2))&"-"&IF(DAY(DATE(2026,5,4)+(10-6)*7+(5-2))<10,"0","")&DAY(DATE(2026,5,4)+(10-6)*7+(5-2)),'📅 Resumen Diario'!$C$5:$C$504,IF($F$2="TODOS", "*", $F$2))/SUMIFS('📅 Resumen Diario'!$J$5:$J$504,'📅 Resumen Diario'!$B$5:$B$504,YEAR(DATE(2026,5,4)+(10-6)*7+(5-2))&"-"&IF(MONTH(DATE(2026,5,4)+(10-6)*7+(5-2))<10,"0","")&MONTH(DATE(2026,5,4)+(10-6)*7+(5-2))&"-"&IF(DAY(DATE(2026,5,4)+(10-6)*7+(5-2))<10,"0","")&DAY(DATE(2026,5,4)+(10-6)*7+(5-2)),'📅 Resumen Diario'!$C$5:$C$504,IF($F$2="TODOS", "*", $F$2))),"—") -> -0.27442447 | F10: =IF(OR($C$2="TODOS",(YEAR(DATE(2026,5,4)+(10-6)*7+(6-2))&"-"&IF(MONTH(DATE(2026,5,4)+(10-6)*7+(6-2))<10,"0","")&MONTH(DATE(2026,5,4)+(10-6)*7+(6-2)))=$C$2),IF(SUMIFS('📅 Resumen Diario'!$J$5:$J$504,'📅 Resumen Diario'!$B$5:$B$504,YEAR(DATE(2026,5,4)+(10-6)*7+(6-2))&"-"&IF(MONTH(DATE(2026,5,4)+(10-6)*7+(6-2))<10,"0","")&MONTH(DATE(2026,5,4)+(10-6)*7+(6-2))&"-"&IF(DAY(DATE(2026,5,4)+(10-6)*7+(6-2))<10,"0","")&DAY(DATE(2026,5,4)+(10-6)*7+(6-2)),'📅 Resumen Diario'!$C$5:$C$504,IF($F$2="TODOS", "*", $F$2))=0,"—",SUMIFS('📅 Resumen Diario'!$Q$5:$Q$504,'📅 Resumen Diario'!$B$5:$B$504,YEAR(DATE(2026,5,4)+(10-6)*7+(6-2))&"-"&IF(MONTH(DATE(2026,5,4)+(10-6)*7+(6-2))<10,"0","")&MONTH(DATE(2026,5,4)+(10-6)*7+(6-2))&"-"&IF(DAY(DATE(2026,5,4)+(10-6)*7+(6-2))<10,"0","")&DAY(DATE(2026,5,4)+(10-6)*7+(6-2)),'📅 Resumen Diario'!$C$5:$C$504,IF($F$2="TODOS", "*", $F$2))/SUMIFS('📅 Resumen Diario'!$J$5:$J$504,'📅 Resumen Diario'!$B$5:$B$504,YEAR(DATE(2026,5,4)+(10-6)*7+(6-2))&"-"&IF(MONTH(DATE(2026,5,4)+(10-6)*7+(6-2))<10,"0","")&MONTH(DATE(2026,5,4)+(10-6)*7+(6-2))&"-"&IF(DAY(DATE(2026,5,4)+(10-6)*7+(6-2))<10,"0","")&DAY(DATE(2026,5,4)+(10-6)*7+(6-2)),'📅 Resumen Diario'!$C$5:$C$504,IF($F$2="TODOS", "*", $F$2))),"—") -> -0.73176332 | G10: =IF(OR($C$2="TODOS",(YEAR(DATE(2026,5,4)+(10-6)*7+(7-2))&"-"&IF(MONTH(DATE(2026,5,4)+(10-6)*7+(7-2))<10,"0","")&MONTH(DATE(2026,5,4)+(10-6)*7+(7-2)))=$C$2),IF(SUMIFS('📅 Resumen Diario'!$J$5:$J$504,'📅 Resumen Diario'!$B$5:$B$504,YEAR(DATE(2026,5,4)+(10-6)*7+(7-2))&"-"&IF(MONTH(DATE(2026,5,4)+(10-6)*7+(7-2))<10,"0","")&MONTH(DATE(2026,5,4)+(10-6)*7+(7-2))&"-"&IF(DAY(DATE(2026,5,4)+(10-6)*7+(7-2))<10,"0","")&DAY(DATE(2026,5,4)+(10-6)*7+(7-2)),'📅 Resumen Diario'!$C$5:$C$504,IF($F$2="TODOS", "*", $F$2))=0,"—",SUMIFS('📅 Resumen Diario'!$Q$5:$Q$504,'📅 Resumen Diario'!$B$5:$B$504,YEAR(DATE(2026,5,4)+(10-6)*7+(7-2))&"-"&IF(MONTH(DATE(2026,5,4)+(10-6)*7+(7-2))<10,"0","")&MONTH(DATE(2026,5,4)+(10-6)*7+(7-2))&"-"&IF(DAY(DATE(2026,5,4)+(10-6)*7+(7-2))<10,"0","")&DAY(DATE(2026,5,4)+(10-6)*7+(7-2)),'📅 Resumen Diario'!$C$5:$C$504,IF($F$2="TODOS", "*", $F$2))/SUMIFS('📅 Resumen Diario'!$J$5:$J$504,'📅 Resumen Diario'!$B$5:$B$504,YEAR(DATE(2026,5,4)+(10-6)*7+(7-2))&"-"&IF(MONTH(DATE(2026,5,4)+(10-6)*7+(7-2))<10,"0","")&MONTH(DATE(2026,5,4)+(10-6)*7+(7-2))&"-"&IF(DAY(DATE(2026,5,4)+(10-6)*7+(7-2))<10,"0","")&DAY(DATE(2026,5,4)+(10-6)*7+(7-2)),'📅 Resumen Diario'!$C$5:$C$504,IF($F$2="TODOS", "*", $F$2))),"—") -> -3.890181 | H10: =IF(OR($C$2="TODOS",(YEAR(DATE(2026,5,4)+(10-6)*7+(8-2))&"-"&IF(MONTH(DATE(2026,5,4)+(10-6)*7+(8-2))<10,"0","")&MONTH(DATE(2026,5,4)+(10-6)*7+(8-2)))=$C$2),IF(SUMIFS('📅 Resumen Diario'!$J$5:$J$504,'📅 Resumen Diario'!$B$5:$B$504,YEAR(DATE(2026,5,4)+(10-6)*7+(8-2))&"-"&IF(MONTH(DATE(2026,5,4)+(10-6)*7+(8-2))<10,"0","")&MONTH(DATE(2026,5,4)+(10-6)*7+(8-2))&"-"&IF(DAY(DATE(2026,5,4)+(10-6)*7+(8-2))<10,"0","")&DAY(DATE(2026,5,4)+(10-6)*7+(8-2)),'📅 Resumen Diario'!$C$5:$C$504,IF($F$2="TODOS", "*", $F$2))=0,"—",SUMIFS('📅 Resumen Diario'!$Q$5:$Q$504,'📅 Resumen Diario'!$B$5:$B$504,YEAR(DATE(2026,5,4)+(10-6)*7+(8-2))&"-"&IF(MONTH(DATE(2026,5,4)+(10-6)*7+(8-2))<10,"0","")&MONTH(DATE(2026,5,4)+(10-6)*7+(8-2))&"-"&IF(DAY(DATE(2026,5,4)+(10-6)*7+(8-2))<10,"0","")&DAY(DATE(2026,5,4)+(10-6)*7+(8-2)),'📅 Resumen Diario'!$C$5:$C$504,IF($F$2="TODOS", "*", $F$2))/SUMIFS('📅 Resumen Diario'!$J$5:$J$504,'📅 Resumen Diario'!$B$5:$B$504,YEAR(DATE(2026,5,4)+(10-6)*7+(8-2))&"-"&IF(MONTH(DATE(2026,5,4)+(10-6)*7+(8-2))<10,"0","")&MONTH(DATE(2026,5,4)+(10-6)*7+(8-2))&"-"&IF(DAY(DATE(2026,5,4)+(10-6)*7+(8-2))<10,"0","")&DAY(DATE(2026,5,4)+(10-6)*7+(8-2)),'📅 Resumen Diario'!$C$5:$C$504,IF($F$2="TODOS", "*", $F$2))),"—") -> 0.53747277
A11: S24 | B11: =IF(OR($C$2="TODOS",(YEAR(DATE(2026,5,4)+(11-6)*7+(2-2))&"-"&IF(MONTH(DATE(2026,5,4)+(11-6)*7+(2-2))<10,"0","")&MONTH(DATE(2026,5,4)+(11-6)*7+(2-2)))=$C$2),IF(SUMIFS('📅 Resumen Diario'!$J$5:$J$504,'📅 Resumen Diario'!$B$5:$B$504,YEAR(DATE(2026,5,4)+(11-6)*7+(2-2))&"-"&IF(MONTH(DATE(2026,5,4)+(11-6)*7+(2-2))<10,"0","")&MONTH(DATE(2026,5,4)+(11-6)*7+(2-2))&"-"&IF(DAY(DATE(2026,5,4)+(11-6)*7+(2-2))<10,"0","")&DAY(DATE(2026,5,4)+(11-6)*7+(2-2)),'📅 Resumen Diario'!$C$5:$C$504,IF($F$2="TODOS", "*", $F$2))=0,"—",SUMIFS('📅 Resumen Diario'!$Q$5:$Q$504,'📅 Resumen Diario'!$B$5:$B$504,YEAR(DATE(2026,5,4)+(11-6)*7+(2-2))&"-"&IF(MONTH(DATE(2026,5,4)+(11-6)*7+(2-2))<10,"0","")&MONTH(DATE(2026,5,4)+(11-6)*7+(2-2))&"-"&IF(DAY(DATE(2026,5,4)+(11-6)*7+(2-2))<10,"0","")&DAY(DATE(2026,5,4)+(11-6)*7+(2-2)),'📅 Resumen Diario'!$C$5:$C$504,IF($F$2="TODOS", "*", $F$2))/SUMIFS('📅 Resumen Diario'!$J$5:$J$504,'📅 Resumen Diario'!$B$5:$B$504,YEAR(DATE(2026,5,4)+(11-6)*7+(2-2))&"-"&IF(MONTH(DATE(2026,5,4)+(11-6)*7+(2-2))<10,"0","")&MONTH(DATE(2026,5,4)+(11-6)*7+(2-2))&"-"&IF(DAY(DATE(2026,5,4)+(11-6)*7+(2-2))<10,"0","")&DAY(DATE(2026,5,4)+(11-6)*7+(2-2)),'📅 Resumen Diario'!$C$5:$C$504,IF($F$2="TODOS", "*", $F$2))),"—") -> 0.27470111 | C11: =IF(OR($C$2="TODOS",(YEAR(DATE(2026,5,4)+(11-6)*7+(3-2))&"-"&IF(MONTH(DATE(2026,5,4)+(11-6)*7+(3-2))<10,"0","")&MONTH(DATE(2026,5,4)+(11-6)*7+(3-2)))=$C$2),IF(SUMIFS('📅 Resumen Diario'!$J$5:$J$504,'📅 Resumen Diario'!$B$5:$B$504,YEAR(DATE(2026,5,4)+(11-6)*7+(3-2))&"-"&IF(MONTH(DATE(2026,5,4)+(11-6)*7+(3-2))<10,"0","")&MONTH(DATE(2026,5,4)+(11-6)*7+(3-2))&"-"&IF(DAY(DATE(2026,5,4)+(11-6)*7+(3-2))<10,"0","")&DAY(DATE(2026,5,4)+(11-6)*7+(3-2)),'📅 Resumen Diario'!$C$5:$C$504,IF($F$2="TODOS", "*", $F$2))=0,"—",SUMIFS('📅 Resumen Diario'!$Q$5:$Q$504,'📅 Resumen Diario'!$B$5:$B$504,YEAR(DATE(2026,5,4)+(11-6)*7+(3-2))&"-"&IF(MONTH(DATE(2026,5,4)+(11-6)*7+(3-2))<10,"0","")&MONTH(DATE(2026,5,4)+(11-6)*7+(3-2))&"-"&IF(DAY(DATE(2026,5,4)+(11-6)*7+(3-2))<10,"0","")&DAY(DATE(2026,5,4)+(11-6)*7+(3-2)),'📅 Resumen Diario'!$C$5:$C$504,IF($F$2="TODOS", "*", $F$2))/SUMIFS('📅 Resumen Diario'!$J$5:$J$504,'📅 Resumen Diario'!$B$5:$B$504,YEAR(DATE(2026,5,4)+(11-6)*7+(3-2))&"-"&IF(MONTH(DATE(2026,5,4)+(11-6)*7+(3-2))<10,"0","")&MONTH(DATE(2026,5,4)+(11-6)*7+(3-2))&"-"&IF(DAY(DATE(2026,5,4)+(11-6)*7+(3-2))<10,"0","")&DAY(DATE(2026,5,4)+(11-6)*7+(3-2)),'📅 Resumen Diario'!$C$5:$C$504,IF($F$2="TODOS", "*", $F$2))),"—") -> 0.57994885 | D11: =IF(OR($C$2="TODOS",(YEAR(DATE(2026,5,4)+(11-6)*7+(4-2))&"-"&IF(MONTH(DATE(2026,5,4)+(11-6)*7+(4-2))<10,"0","")&MONTH(DATE(2026,5,4)+(11-6)*7+(4-2)))=$C$2),IF(SUMIFS('📅 Resumen Diario'!$J$5:$J$504,'📅 Resumen Diario'!$B$5:$B$504,YEAR(DATE(2026,5,4)+(11-6)*7+(4-2))&"-"&IF(MONTH(DATE(2026,5,4)+(11-6)*7+(4-2))<10,"0","")&MONTH(DATE(2026,5,4)+(11-6)*7+(4-2))&"-"&IF(DAY(DATE(2026,5,4)+(11-6)*7+(4-2))<10,"0","")&DAY(DATE(2026,5,4)+(11-6)*7+(4-2)),'📅 Resumen Diario'!$C$5:$C$504,IF($F$2="TODOS", "*", $F$2))=0,"—",SUMIFS('📅 Resumen Diario'!$Q$5:$Q$504,'📅 Resumen Diario'!$B$5:$B$504,YEAR(DATE(2026,5,4)+(11-6)*7+(4-2))&"-"&IF(MONTH(DATE(2026,5,4)+(11-6)*7+(4-2))<10,"0","")&MONTH(DATE(2026,5,4)+(11-6)*7+(4-2))&"-"&IF(DAY(DATE(2026,5,4)+(11-6)*7+(4-2))<10,"0","")&DAY(DATE(2026,5,4)+(11-6)*7+(4-2)),'📅 Resumen Diario'!$C$5:$C$504,IF($F$2="TODOS", "*", $F$2))/SUMIFS('📅 Resumen Diario'!$J$5:$J$504,'📅 Resumen Diario'!$B$5:$B$504,YEAR(DATE(2026,5,4)+(11-6)*7+(4-2))&"-"&IF(MONTH(DATE(2026,5,4)+(11-6)*7+(4-2))<10,"0","")&MONTH(DATE(2026,5,4)+(11-6)*7+(4-2))&"-"&IF(DAY(DATE(2026,5,4)+(11-6)*7+(4-2))<10,"0","")&DAY(DATE(2026,5,4)+(11-6)*7+(4-2)),'📅 Resumen Diario'!$C$5:$C$504,IF($F$2="TODOS", "*", $F$2))),"—") -> 0.48293088 | E11: =IF(OR($C$2="TODOS",(YEAR(DATE(2026,5,4)+(11-6)*7+(5-2))&"-"&IF(MONTH(DATE(2026,5,4)+(11-6)*7+(5-2))<10,"0","")&MONTH(DATE(2026,5,4)+(11-6)*7+(5-2)))=$C$2),IF(SUMIFS('📅 Resumen Diario'!$J$5:$J$504,'📅 Resumen Diario'!$B$5:$B$504,YEAR(DATE(2026,5,4)+(11-6)*7+(5-2))&"-"&IF(MONTH(DATE(2026,5,4)+(11-6)*7+(5-2))<10,"0","")&MONTH(DATE(2026,5,4)+(11-6)*7+(5-2))&"-"&IF(DAY(DATE(2026,5,4)+(11-6)*7+(5-2))<10,"0","")&DAY(DATE(2026,5,4)+(11-6)*7+(5-2)),'📅 Resumen Diario'!$C$5:$C$504,IF($F$2="TODOS", "*", $F$2))=0,"—",SUMIFS('📅 Resumen Diario'!$Q$5:$Q$504,'📅 Resumen Diario'!$B$5:$B$504,YEAR(DATE(2026,5,4)+(11-6)*7+(5-2))&"-"&IF(MONTH(DATE(2026,5,4)+(11-6)*7+(5-2))<10,"0","")&MONTH(DATE(2026,5,4)+(11-6)*7+(5-2))&"-"&IF(DAY(DATE(2026,5,4)+(11-6)*7+(5-2))<10,"0","")&DAY(DATE(2026,5,4)+(11-6)*7+(5-2)),'📅 Resumen Diario'!$C$5:$C$504,IF($F$2="TODOS", "*", $F$2))/SUMIFS('📅 Resumen Diario'!$J$5:$J$504,'📅 Resumen Diario'!$B$5:$B$504,YEAR(DATE(2026,5,4)+(11-6)*7+(5-2))&"-"&IF(MONTH(DATE(2026,5,4)+(11-6)*7+(5-2))<10,"0","")&MONTH(DATE(2026,5,4)+(11-6)*7+(5-2))&"-"&IF(DAY(DATE(2026,5,4)+(11-6)*7+(5-2))<10,"0","")&DAY(DATE(2026,5,4)+(11-6)*7+(5-2)),'📅 Resumen Diario'!$C$5:$C$504,IF($F$2="TODOS", "*", $F$2))),"—") -> 0.6312624 | F11: =IF(OR($C$2="TODOS",(YEAR(DATE(2026,5,4)+(11-6)*7+(6-2))&"-"&IF(MONTH(DATE(2026,5,4)+(11-6)*7+(6-2))<10,"0","")&MONTH(DATE(2026,5,4)+(11-6)*7+(6-2)))=$C$2),IF(SUMIFS('📅 Resumen Diario'!$J$5:$J$504,'📅 Resumen Diario'!$B$5:$B$504,YEAR(DATE(2026,5,4)+(11-6)*7+(6-2))&"-"&IF(MONTH(DATE(2026,5,4)+(11-6)*7+(6-2))<10,"0","")&MONTH(DATE(2026,5,4)+(11-6)*7+(6-2))&"-"&IF(DAY(DATE(2026,5,4)+(11-6)*7+(6-2))<10,"0","")&DAY(DATE(2026,5,4)+(11-6)*7+(6-2)),'📅 Resumen Diario'!$C$5:$C$504,IF($F$2="TODOS", "*", $F$2))=0,"—",SUMIFS('📅 Resumen Diario'!$Q$5:$Q$504,'📅 Resumen Diario'!$B$5:$B$504,YEAR(DATE(2026,5,4)+(11-6)*7+(6-2))&"-"&IF(MONTH(DATE(2026,5,4)+(11-6)*7+(6-2))<10,"0","")&MONTH(DATE(2026,5,4)+(11-6)*7+(6-2))&"-"&IF(DAY(DATE(2026,5,4)+(11-6)*7+(6-2))<10,"0","")&DAY(DATE(2026,5,4)+(11-6)*7+(6-2)),'📅 Resumen Diario'!$C$5:$C$504,IF($F$2="TODOS", "*", $F$2))/SUMIFS('📅 Resumen Diario'!$J$5:$J$504,'📅 Resumen Diario'!$B$5:$B$504,YEAR(DATE(2026,5,4)+(11-6)*7+(6-2))&"-"&IF(MONTH(DATE(2026,5,4)+(11-6)*7+(6-2))<10,"0","")&MONTH(DATE(2026,5,4)+(11-6)*7+(6-2))&"-"&IF(DAY(DATE(2026,5,4)+(11-6)*7+(6-2))<10,"0","")&DAY(DATE(2026,5,4)+(11-6)*7+(6-2)),'📅 Resumen Diario'!$C$5:$C$504,IF($F$2="TODOS", "*", $F$2))),"—") -> 0.034357365 | G11: =IF(OR($C$2="TODOS",(YEAR(DATE(2026,5,4)+(11-6)*7+(7-2))&"-"&IF(MONTH(DATE(2026,5,4)+(11-6)*7+(7-2))<10,"0","")&MONTH(DATE(2026,5,4)+(11-6)*7+(7-2)))=$C$2),IF(SUMIFS('📅 Resumen Diario'!$J$5:$J$504,'📅 Resumen Diario'!$B$5:$B$504,YEAR(DATE(2026,5,4)+(11-6)*7+(7-2))&"-"&IF(MONTH(DATE(2026,5,4)+(11-6)*7+(7-2))<10,"0","")&MONTH(DATE(2026,5,4)+(11-6)*7+(7-2))&"-"&IF(DAY(DATE(2026,5,4)+(11-6)*7+(7-2))<10,"0","")&DAY(DATE(2026,5,4)+(11-6)*7+(7-2)),'📅 Resumen Diario'!$C$5:$C$504,IF($F$2="TODOS", "*", $F$2))=0,"—",SUMIFS('📅 Resumen Diario'!$Q$5:$Q$504,'📅 Resumen Diario'!$B$5:$B$504,YEAR(DATE(2026,5,4)+(11-6)*7+(7-2))&"-"&IF(MONTH(DATE(2026,5,4)+(11-6)*7+(7-2))<10,"0","")&MONTH(DATE(2026,5,4)+(11-6)*7+(7-2))&"-"&IF(DAY(DATE(2026,5,4)+(11-6)*7+(7-2))<10,"0","")&DAY(DATE(2026,5,4)+(11-6)*7+(7-2)),'📅 Resumen Diario'!$C$5:$C$504,IF($F$2="TODOS", "*", $F$2))/SUMIFS('📅 Resumen Diario'!$J$5:$J$504,'📅 Resumen Diario'!$B$5:$B$504,YEAR(DATE(2026,5,4)+(11-6)*7+(7-2))&"-"&IF(MONTH(DATE(2026,5,4)+(11-6)*7+(7-2))<10,"0","")&MONTH(DATE(2026,5,4)+(11-6)*7+(7-2))&"-"&IF(DAY(DATE(2026,5,4)+(11-6)*7+(7-2))<10,"0","")&DAY(DATE(2026,5,4)+(11-6)*7+(7-2)),'📅 Resumen Diario'!$C$5:$C$504,IF($F$2="TODOS", "*", $F$2))),"—") -> 0.61371538 | H11: =IF(OR($C$2="TODOS",(YEAR(DATE(2026,5,4)+(11-6)*7+(8-2))&"-"&IF(MONTH(DATE(2026,5,4)+(11-6)*7+(8-2))<10,"0","")&MONTH(DATE(2026,5,4)+(11-6)*7+(8-2)))=$C$2),IF(SUMIFS('📅 Resumen Diario'!$J$5:$J$504,'📅 Resumen Diario'!$B$5:$B$504,YEAR(DATE(2026,5,4)+(11-6)*7+(8-2))&"-"&IF(MONTH(DATE(2026,5,4)+(11-6)*7+(8-2))<10,"0","")&MONTH(DATE(2026,5,4)+(11-6)*7+(8-2))&"-"&IF(DAY(DATE(2026,5,4)+(11-6)*7+(8-2))<10,"0","")&DAY(DATE(2026,5,4)+(11-6)*7+(8-2)),'📅 Resumen Diario'!$C$5:$C$504,IF($F$2="TODOS", "*", $F$2))=0,"—",SUMIFS('📅 Resumen Diario'!$Q$5:$Q$504,'📅 Resumen Diario'!$B$5:$B$504,YEAR(DATE(2026,5,4)+(11-6)*7+(8-2))&"-"&IF(MONTH(DATE(2026,5,4)+(11-6)*7+(8-2))<10,"0","")&MONTH(DATE(2026,5,4)+(11-6)*7+(8-2))&"-"&IF(DAY(DATE(2026,5,4)+(11-6)*7+(8-2))<10,"0","")&DAY(DATE(2026,5,4)+(11-6)*7+(8-2)),'📅 Resumen Diario'!$C$5:$C$504,IF($F$2="TODOS", "*", $F$2))/SUMIFS('📅 Resumen Diario'!$J$5:$J$504,'📅 Resumen Diario'!$B$5:$B$504,YEAR(DATE(2026,5,4)+(11-6)*7+(8-2))&"-"&IF(MONTH(DATE(2026,5,4)+(11-6)*7+(8-2))<10,"0","")&MONTH(DATE(2026,5,4)+(11-6)*7+(8-2))&"-"&IF(DAY(DATE(2026,5,4)+(11-6)*7+(8-2))<10,"0","")&DAY(DATE(2026,5,4)+(11-6)*7+(8-2)),'📅 Resumen Diario'!$C$5:$C$504,IF($F$2="TODOS", "*", $F$2))),"—") -> —
A14: LEYENDA: Excelente (>50%) | Bueno (25-50%) | Regular (0-25%) | Perdida (<0%)

Sheet 🌞🌙 Analisis por Turno
A1: 🌞🌙 ANALISIS COMPARATIVO POR TURNO
B2: Mes Selector: | C2: TODOS
A3: 📊 METRICAS COMPARATIVAS TURNO DIA vs NOCHE
A4: Metrica | B4: Turno DIA | C4: Turno NOCHE | D4: Diferencia | E4: Mejor Turno
A5: Dias Operados | B5: =COUNTIFS('📅 Resumen Diario'!$C$5:$C$504, "DIA", '📅 Resumen Diario'!$O$5:$O$504, IF($C$2="TODOS", "*", $C$2)) -> 42 | C5: =COUNTIFS('📅 Resumen Diario'!$C$5:$C$504, "NOCHE", '📅 Resumen Diario'!$O$5:$O$504, IF($C$2="TODOS", "*", $C$2)) -> 37 | D5: =B5-C5 -> 5 | E5: =IF(B5>C5, "DIA DIA", "NOCHE NOCHE") -> DIA DIA
A6: Unidades Producidas | B6: =SUMIFS('📅 Resumen Diario'!$D$5:$D$504, '📅 Resumen Diario'!$C$5:$C$504, "DIA", '📅 Resumen Diario'!$O$5:$O$504, IF($C$2="TODOS", "*", $C$2)) -> 26278.2 | C6: =SUMIFS('📅 Resumen Diario'!$D$5:$D$504, '📅 Resumen Diario'!$C$5:$C$504, "NOCHE", '📅 Resumen Diario'!$O$5:$O$504, IF($C$2="TODOS", "*", $C$2)) -> 26954.1 | D6: =B6-C6 -> -675.9 | E6: =IF(B6>C6, "DIA DIA", "NOCHE NOCHE") -> NOCHE NOCHE
A7: Etiquetas Procesadas | B7: =SUMIFS('📅 Resumen Diario'!$G$5:$G$504, '📅 Resumen Diario'!$C$5:$C$504, "DIA", '📅 Resumen Diario'!$O$5:$O$504, IF($C$2="TODOS", "*", $C$2)) -> 86190 | C7: =SUMIFS('📅 Resumen Diario'!$G$5:$G$504, '📅 Resumen Diario'!$C$5:$C$504, "NOCHE", '📅 Resumen Diario'!$O$5:$O$504, IF($C$2="TODOS", "*", $C$2)) -> 109065 | D7: =B7-C7 -> -22875 | E7: =IF(B7>C7, "DIA DIA", "NOCHE NOCHE") -> NOCHE NOCHE
A8: Ingreso Total | B8: =SUMIFS('📅 Resumen Diario'!$J$5:$J$504, '📅 Resumen Diario'!$C$5:$C$504, "DIA", '📅 Resumen Diario'!$O$5:$O$504, IF($C$2="TODOS", "*", $C$2)) -> 311261.56 | C8: =SUMIFS('📅 Resumen Diario'!$J$5:$J$504, '📅 Resumen Diario'!$C$5:$C$504, "NOCHE", '📅 Resumen Diario'!$O$5:$O$504, IF($C$2="TODOS", "*", $C$2)) -> 335776.53 | D8: =B8-C8 -> -24514.97 | E8: =IF(B8>C8, "DIA DIA", "NOCHE NOCHE") -> NOCHE NOCHE
A9: Costo Total | B9: =SUMIFS('📅 Resumen Diario'!$P$5:$P$504, '📅 Resumen Diario'!$C$5:$C$504, "DIA", '📅 Resumen Diario'!$O$5:$O$504, IF($C$2="TODOS", "*", $C$2)) -> 233941.86 | C9: =SUMIFS('📅 Resumen Diario'!$P$5:$P$504, '📅 Resumen Diario'!$C$5:$C$504, "NOCHE", '📅 Resumen Diario'!$O$5:$O$504, IF($C$2="TODOS", "*", $C$2)) -> 201961.31 | D9: =B9-C9 -> 31980.552 | E9: =IF(B9>C9, "DIA DIA", "NOCHE NOCHE") -> DIA DIA
A10: Ganancia Neta | B10: =SUMIFS('📅 Resumen Diario'!$Q$5:$Q$504, '📅 Resumen Diario'!$C$5:$C$504, "DIA", '📅 Resumen Diario'!$O$5:$O$504, IF($C$2="TODOS", "*", $C$2)) -> 86972.195 | C10: =SUMIFS('📅 Resumen Diario'!$Q$5:$Q$504, '📅 Resumen Diario'!$C$5:$C$504, "NOCHE", '📅 Resumen Diario'!$O$5:$O$504, IF($C$2="TODOS", "*", $C$2)) -> 136582.72 | D10: =B10-C10 -> -49610.522 | E10: =IF(B10>C10, "DIA DIA", "NOCHE NOCHE") -> NOCHE NOCHE
A11: Margen Neto % | B11: =IF(B8=0, 0, B10/B8) -> 0.27941836 | C11: =IF(C8=0, 0, C10/C8) -> 0.40676672 | D11: =B11-C11 -> -0.12734836 | E11: =IF(B11>C11, "DIA DIA", "NOCHE NOCHE") -> NOCHE NOCHE
A12: Costo por Unidad | B12: =IF(B6=0, 0, B9/B6) -> 8.9025072 | C12: =IF(C6=0, 0, C9/C6) -> 7.4927864 | D12: =B12-C12 -> 1.4097208 | E12: =IF(B12>C12, "DIA DIA", "NOCHE NOCHE") -> DIA DIA

Sheet 📅 Resumen Diario
B1: 📅 RESUMEN DIARIO — COSTO vs INGRESO vs GANANCIA (CON ETIQUETADO)
B2: Seguimiento diario por turno: Producción, Costos, Ingresos y Rentabilidad Real
B4: Fecha | C4: Turno | D4: Unidades | E4: Etiquetas R23 | F4: Etiquetas R39 | G4: Total Etiquetas | H4: Ingreso Empaque | I4: Ingreso Etiquetas | J4: Ingreso Total | K4: Costo Turno | L4: Ganancia | M4: Margen % | N4: Costo por Unidad | O4: Mes | P4: Costo Total Operativo | Q4: Ganancia Neta Real | R4: Margen Neto Real % | T4: Meses para Filtro | U4: Turnos para Filtro
B5: 2026-05-01 | C5: DIA | D5: =IF(B5="","",SUMIFS('📈 Datos Completos'!$E$7:$E$5000, '📈 Datos Completos'!$B$7:$B$5000, B5, '📈 Datos Completos'!$D$7:$D$5000, C5)) -> 674 | E5: =IF(B5="","",SUMIFS('📈 Datos Completos'!$F$7:$F$5000, '📈 Datos Completos'!$B$7:$B$5000, B5, '📈 Datos Completos'!$D$7:$D$5000, C5)) -> 520 | F5: =IF(B5="","",SUMIFS('📈 Datos Completos'!$G$7:$G$5000, '📈 Datos Completos'!$B$7:$B$5000, B5, '📈 Datos Completos'!$D$7:$D$5000, C5)) -> 1344 | G5: =IF(B5="","",E5+F5) -> 1864 | H5: =IF(B5="","",SUMIFS('📈 Datos Completos'!$I$7:$I$5000, '📈 Datos Completos'!$B$7:$B$5000, B5, '📈 Datos Completos'!$D$7:$D$5000, C5)) -> 3451.28 | I5: =IF(B5="","",IF(C5="DIA", G5*1.01, G5*1.35)) -> 1882.64 | J5: =IF(B5="","",H5+I5) -> 5333.92 | K5: =IF(B5="","",IF(C5="DIA", (SUMIFS('📋 Detalle Diario'!$D$5:$D$489, '📋 Detalle Diario'!$B$5:$B$489, B5, '📋 Detalle Diario'!$C$5:$C$489, C5) * '⚙️ Supuestos'!$C$24) + '⚙️ Supuestos'!$C$23, (SUMIFS('📋 Detalle Diario'!$D$5:$D$489, '📋 Detalle Diario'!$B$5:$B$489, B5, '📋 Detalle Diario'!$C$5:$C$489, C5) * '⚙️ Supuestos'!$C$24) + '⚙️ Supuestos'!$C$33)) -> 5044.5503 | L5: =IF(B5="","",J5-K5) -> 289.36967 | M5: =IF(B5="","",IF(J5=0, 0, L5/J5)) -> 0.054250845 | N5: =IF(B5="","",IF(D5=0, 0, K5/D5)) -> 7.484496 | O5: =IF(B5="","",IF(ISNUMBER(B5),YEAR(B5)&"-"&IF(MONTH(B5)<10,"0","")&MONTH(B5),LEFT(B5,7))) -> 2026-05 | P5: =IF(B5="","",K5+(G5*0.09)) -> 5212.3103 | Q5: =IF(B5="","",J5-P5+(SUMIFS('📋 Detalle Diario'!$E$5:$E$489, '📋 Detalle Diario'!$B$5:$B$489, B5, '📋 Detalle Diario'!$C$5:$C$489, C5)*135)+(SUMIFS('📋 Detalle Diario'!$I$5:$I$489, '📋 Detalle Diario'!$B$5:$B$489, B5, '📋 Detalle Diario'!$C$5:$C$489, C5)*200)) -> 121.60967 | R5: =IF(B5="","",IF(J5=0, 0, Q5/J5)) -> 0.022799305
B6: 2026-05-01 | C6: NOCHE | D6: =IF(B6="","",SUMIFS('📈 Datos Completos'!$E$7:$E$5000, '📈 Datos Completos'!$B$7:$B$5000, B6, '📈 Datos Completos'!$D$7:$D$5000, C6)) -> 233.7 | E6: =IF(B6="","",SUMIFS('📈 Datos Completos'!$F$7:$F$5000, '📈 Datos Completos'!$B$7:$B$5000, B6, '📈 Datos Completos'!$D$7:$D$5000, C6)) -> 1517 | F6: =IF(B6="","",SUMIFS('📈 Datos Completos'!$G$7:$G$5000, '📈 Datos Completos'!$B$7:$B$5000, B6, '📈 Datos Completos'!$D$7:$D$5000, C6)) -> 428 | G6: =IF(B6="","",E6+F6) -> 1945 | H6: =IF(B6="","",SUMIFS('📈 Datos Completos'!$I$7:$I$5000, '📈 Datos Completos'!$B$7:$B$5000, B6, '📈 Datos Completos'!$D$7:$D$5000, C6)) -> 3389.91 | I6: =IF(B6="","",IF(C6="DIA", G6*1.01, G6*1.35)) -> 2625.75 | J6: =IF(B6="","",H6+I6) -> 6015.66 | K6: =IF(B6="","",IF(C6="DIA", (SUMIFS('📋 Detalle Diario'!$D$5:$D$489, '📋 Detalle Diario'!$B$5:$B$489, B6, '📋 Detalle Diario'!$C$5:$C$489, C6) * '⚙️ Supuestos'!$C$24) + '⚙️ Supuestos'!$C$23, (SUMIFS('📋 Detalle Diario'!$D$5:$D$489, '📋 Detalle Diario'!$B$5:$B$489, B6, '📋 Detalle Diario'!$C$5:$C$489, C6) * '⚙️ Supuestos'!$C$24) + '⚙️ Supuestos'!$C$33)) -> 4935.217 | L6: =IF(B6="","",J6-K6) -> 1080.443 | M6: =IF(B6="","",IF(J6=0, 0, L6/J6)) -> 0.17960506 | N6: =IF(B6="","",IF(D6=0, 0, K6/D6)) -> 21.117745 | O6: =IF(B6="","",IF(ISNUMBER(B6),YEAR(B6)&"-"&IF(MONTH(B6)<10,"0","")&MONTH(B6),LEFT(B6,7))) -> 2026-05 | P6: =IF(B6="","",K6+(G6*0.09)) -> 5110.267 | Q6: =IF(B6="","",J6-P6+(SUMIFS('📋 Detalle Diario'!$E$5:$E$489, '📋 Detalle Diario'!$B$5:$B$489, B6, '📋 Detalle Diario'!$C$5:$C$489, C6)*135)+(SUMIFS('📋 Detalle Diario'!$I$5:$I$489, '📋 Detalle Diario'!$B$5:$B$489, B6, '📋 Detalle Diario'!$C$5:$C$489, C6)*200)) -> 905.393 | R6: =IF(B6="","",IF(J6=0, 0, Q6/J6)) -> 0.15050601
B7: 2026-05-02 | C7: DIA | D7: =IF(B7="","",SUMIFS('📈 Datos Completos'!$E$7:$E$5000, '📈 Datos Completos'!$B$7:$B$5000, B7, '📈 Datos Completos'!$D$7:$D$5000, C7)) -> 453.3 | E7: =IF(B7="","",SUMIFS('📈 Datos Completos'!$F$7:$F$5000, '📈 Datos Completos'!$B$7:$B$5000, B7, '📈 Datos Completos'!$D$7:$D$5000, C7)) -> 0 | F7: =IF(B7="","",SUMIFS('📈 Datos Completos'!$G$7:$G$5000, '📈 Datos Completos'!$B$7:$B$5000, B7, '📈 Datos Completos'!$D$7:$D$5000, C7)) -> 2270 | G7: =IF(B7="","",E7+F7) -> 2270 | H7: =IF(B7="","",SUMIFS('📈 Datos Completos'!$I$7:$I$5000, '📈 Datos Completos'!$B$7:$B$5000, B7, '📈 Datos Completos'!$D$7:$D$5000, C7)) -> 9582.9 | I7: =IF(B7="","",IF(C7="DIA", G7*1.01, G7*1.35)) -> 2292.7 | J7: =IF(B7="","",H7+I7) -> 11875.6 | K7: =IF(B7="","",IF(C7="DIA", (SUMIFS('📋 Detalle Diario'!$D$5:$D$489, '📋 Detalle Diario'!$B$5:$B$489, B7, '📋 Detalle Diario'!$C$5:$C$489, C7) * '⚙️ Supuestos'!$C$24) + '⚙️ Supuestos'!$C$23, (SUMIFS('📋 Detalle Diario'!$D$5:$D$489, '📋 Detalle Diario'!$B$5:$B$489, B7, '📋 Detalle Diario'!$C$5:$C$489, C7) * '⚙️ Supuestos'!$C$24) + '⚙️ Supuestos'!$C$33)) -> 5044.5503 | L7: =IF(B7="","",J7-K7) -> 6831.0497 | M7: =IF(B7="","",IF(J7=0, 0, L7/J7)) -> 0.57521722 | N7: =IF(B7="","",IF(D7=0, 0, K7/D7)) -> 11.128503 | O7: =IF(B7="","",IF(ISNUMBER(B7),YEAR(B7)&"-"&IF(MONTH(B7)<10,"0","")&MONTH(B7),LEFT(B7,7))) -> 2026-05 | P7: =IF(B7="","",K7+(G7*0.09)) -> 5248.8503 | Q7: =IF(B7="","",J7-P7+(SUMIFS('📋 Detalle Diario'!$E$5:$E$489, '📋 Detalle Diario'!$B$5:$B$489, B7, '📋 Detalle Diario'!$C$5:$C$489, C7)*135)+(SUMIFS('📋 Detalle Diario'!$I$5:$I$489, '📋 Detalle Diario'!$B$5:$B$489, B7, '📋 Detalle Diario'!$C$5:$C$489, C7)*200)) -> 6626.7497 | R7: =IF(B7="","",IF(J7=0, 0, Q7/J7)) -> 0.55801388
B8: 2026-05-03 | C8: NOCHE | D8: =IF(B8="","",SUMIFS('📈 Datos Completos'!$E$7:$E$5000, '📈 Datos Completos'!$B$7:$B$5000, B8, '📈 Datos Completos'!$D$7:$D$5000, C8)) -> 1279 | E8: =IF(B8="","",SUMIFS('📈 Datos Completos'!$F$7:$F$5000, '📈 Datos Completos'!$B$7:$B$5000, B8, '📈 Datos Completos'!$D$7:$D$5000, C8)) -> 1575 | F8: =IF(B8="","",SUMIFS('📈 Datos Completos'!$G$7:$G$5000, '📈 Datos Completos'!$B$7:$B$5000, B8, '📈 Datos Completos'!$D$7:$D$5000, C8)) -> 3297 | G8: =IF(B8="","",E8+F8) -> 4872 | H8: =IF(B8="","",SUMIFS('📈 Datos Completos'!$I$7:$I$5000, '📈 Datos Completos'!$B$7:$B$5000, B8, '📈 Datos Completos'!$D$7:$D$5000, C8)) -> 7766.34 | I8: =IF(B8="","",IF(C8="DIA", G8*1.01, G8*1.35)) -> 6577.2 | J8: =IF(B8="","",H8+I8) -> 14343.54 | K8: =IF(B8="","",IF(C8="DIA", (SUMIFS('📋 Detalle Diario'!$D$5:$D$489, '📋 Detalle Diario'!$B$5:$B$489, B8, '📋 Detalle Diario'!$C$5:$C$489, C8) * '⚙️ Supuestos'!$C$24) + '⚙️ Supuestos'!$C$23, (SUMIFS('📋 Detalle Diario'!$D$5:$D$489, '📋 Detalle Diario'!$B$5:$B$489, B8, '📋 Detalle Diario'!$C$5:$C$489, C8) * '⚙️ Supuestos'!$C$24) + '⚙️ Supuestos'!$C$33)) -> 4935.217 | L8: =IF(B8="","",J8-K8) -> 9408.323 | M8: =IF(B8="","",IF(J8=0, 0, L8/J8)) -> 0.65592755 | N8: =IF(B8="","",IF(D8=0, 0, K8/D8)) -> 3.8586529 | O8: =IF(B8="","",IF(ISNUMBER(B8),YEAR(B8)&"-"&IF(MONTH(B8)<10,"0","")&MONTH(B8),LEFT(B8,7))) -> 2026-05 | P8: =IF(B8="","",K8+(G8*0.09)) -> 5373.697 | Q8: =IF(B8="","",J8-P8+(SUMIFS('📋 Detalle Diario'!$E$5:$E$489, '📋 Detalle Diario'!$B$5:$B$489, B8, '📋 Detalle Diario'!$C$5:$C$489, C8)*135)+(SUMIFS('📋 Detalle Diario'!$I$5:$I$489, '📋 Detalle Diario'!$B$5:$B$489, B8, '📋 Detalle Diario'!$C$5:$C$489, C8)*200)) -> 8969.843 | R8: =IF(B8="","",IF(J8=0, 0, Q8/J8)) -> 0.62535769
B9: 2026-05-04 | C9: DIA | D9: =IF(B9="","",SUMIFS('📈 Datos Completos'!$E$7:$E$5000, '📈 Datos Completos'!$B$7:$B$5000, B9, '📈 Datos Completos'!$D$7:$D$5000, C9)) -> 958.6 | E9: =IF(B9="","",SUMIFS('📈 Datos Completos'!$F$7:$F$5000, '📈 Datos Completos'!$B$7:$B$5000, B9, '📈 Datos Completos'!$D$7:$D$5000, C9)) -> 240 | F9: =IF(B9="","",SUMIFS('📈 Datos Completos'!$G$7:$G$5000, '📈 Datos Completos'!$B$7:$B$5000, B9, '📈 Datos Completos'!$D$7:$D$5000, C9)) -> 2248 | G9: =IF(B9="","",E9+F9) -> 2488 | H9: =IF(B9="","",SUMIFS('📈 Datos Completos'!$I$7:$I$5000, '📈 Datos Completos'!$B$7:$B$5000, B9, '📈 Datos Completos'!$D$7:$D$5000, C9)) -> 4442.68 | I9: =IF(B9="","",IF(C9="DIA", G9*1.01, G9*1.35)) -> 2512.88 | J9: =IF(B9="","",H9+I9) -> 6955.56 | K9: =IF(B9="","",IF(C9="DIA", (SUMIFS('📋 Detalle Diario'!$D$5:$D$489, '📋 Detalle Diario'!$B$5:$B$489, B9, '📋 Detalle Diario'!$C$5:$C$489, C9) * '⚙️ Supuestos'!$C$24) + '⚙️ Supuestos'!$C$23, (SUMIFS('📋 Detalle Diario'!$D$5:$D$489, '📋 Detalle Diario'!$B$5:$B$489, B9, '📋 Detalle Diario'!$C$5:$C$489, C9) * '⚙️ Supuestos'!$C$24) + '⚙️ Supuestos'!$C$33)) -> 5044.5503 | L9: =IF(B9="","",J9-K9) -> 1911.0097 | M9: =IF(B9="","",IF(J9=0, 0, L9/J9)) -> 0.27474562 | N9: =IF(B9="","",IF(D9=0, 0, K9/D9)) -> 5.2624143 | O9: =IF(B9="","",IF(ISNUMBER(B9),YEAR(B9)&"-"&IF(MONTH(B9)<10,"0","")&MONTH(B9),LEFT(B9,7))) -> 2026-05 | P9: =IF(B9="","",K9+(G9*0.09)) -> 5268.4703 | Q9: =IF(B9="","",J9-P9+(SUMIFS('📋 Detalle Diario'!$E$5:$E$489, '📋 Detalle Diario'!$B$5:$B$489, B9, '📋 Detalle Diario'!$C$5:$C$489, C9)*135)+(SUMIFS('📋 Detalle Diario'!$I$5:$I$489, '📋 Detalle Diario'!$B$5:$B$489, B9, '📋 Detalle Diario'!$C$5:$C$489, C9)*200)) -> 1687.0897 | R9: =IF(B9="","",IF(J9=0, 0, Q9/J9)) -> 0.24255267
B10: 2026-05-04 | C10: NOCHE | D10: =IF(B10="","",SUMIFS('📈 Datos Completos'!$E$7:$E$5000, '📈 Datos Completos'!$B$7:$B$5000, B10, '📈 Datos Completos'!$D$7:$D$5000, C10)) -> 601 | E10: =IF(B10="","",SUMIFS('📈 Datos Completos'!$F$7:$F$5000, '📈 Datos Completos'!$B$7:$B$5000, B10, '📈 Datos Completos'!$D$7:$D$5000, C10)) -> 120 | F10: =IF(B10="","",SUMIFS('📈 Datos Completos'!$G$7:$G$5000, '📈 Datos Completos'!$B$7:$B$5000, B10, '📈 Datos Completos'!$D$7:$D$5000, C10)) -> 960 | G10: =IF(B10="","",E10+F10) -> 1080 | H10: =IF(B10="","",SUMIFS('📈 Datos Completos'!$I$7:$I$5000, '📈 Datos Completos'!$B$7:$B$5000, B10, '📈 Datos Completos'!$D$7:$D$5000, C10)) -> 4743.6 | I10: =IF(B10="","",IF(C10="DIA", G10*1.01, G10*1.35)) -> 1458 | J10: =IF(B10="","",H10+I10) -> 6201.6 | K10: =IF(B10="","",IF(C10="DIA", (SUMIFS('📋 Detalle Diario'!$D$5:$D$489, '📋 Detalle Diario'!$B$5:$B$489, B10, '📋 Detalle Diario'!$C$5:$C$489, C10) * '⚙️ Supuestos'!$C$24) + '⚙️ Supuestos'!$C$23, (SUMIFS('📋 Detalle Diario'!$D$5:$D$489, '📋 Detalle Diario'!$B$5:$B$489, B10, '📋 Detalle Diario'!$C$5:$C$489, C10) * '⚙️ Supuestos'!$C$24) + '⚙️ Supuestos'!$C$33)) -> 4935.217 | L10: =IF(B10="","",J10-K10) -> 1266.383 | M10: =IF(B10="","",IF(J10=0, 0, L10/J10)) -> 0.20420263 | N10: =IF(B10="","",IF(D10=0, 0, K10/D10)) -> 8.2116755 | O10: =IF(B10="","",IF(ISNUMBER(B10),YEAR(B10)&"-"&IF(MONTH(B10)<10,"0","")&MONTH(B10),LEFT(B10,7))) -> 2026-05 | P10: =IF(B10="","",K10+(G10*0.09)) -> 5032.417 | Q10: =IF(B10="","",J10-P10+(SUMIFS('📋 Detalle Diario'!$E$5:$E$489, '📋 Detalle Diario'!$B$5:$B$489, B10, '📋 Detalle Diario'!$C$5:$C$489, C10)*135)+(SUMIFS('📋 Detalle Diario'!$I$5:$I$489, '📋 Detalle Diario'!$B$5:$B$489, B10, '📋 Detalle Diario'!$C$5:$C$489, C10)*200)) -> 1169.183 | R10: =IF(B10="","",IF(J10=0, 0, Q10/J10)) -> 0.18852925
B11: 2026-05-05 | C11: DIA | D11: =IF(B11="","",SUMIFS('📈 Datos Completos'!$E$7:$E$5000, '📈 Datos Completos'!$B$7:$B$5000, B11, '📈 Datos Completos'!$D$7:$D$5000, C11)) -> 604 | E11: =IF(B11="","",SUMIFS('📈 Datos Completos'!$F$7:$F$5000, '📈 Datos Completos'!$B$7:$B$5000, B11, '📈 Datos Completos'!$D$7:$D$5000, C11)) -> 135 | F11: =IF(B11="","",SUMIFS('📈 Datos Completos'!$G$7:$G$5000, '📈 Datos Completos'!$B$7:$B$5000, B11, '📈 Datos Completos'!$D$7:$D$5000, C11)) -> 960 | G11: =IF(B11="","",E11+F11) -> 1095 | H11: =IF(B11="","",SUMIFS('📈 Datos Completos'!$I$7:$I$5000, '📈 Datos Completos'!$B$7:$B$5000, B11, '📈 Datos Completos'!$D$7:$D$5000, C11)) -> 3952.6 | I11: =IF(B11="","",IF(C11="DIA", G11*1.01, G11*1.35)) -> 1105.95 | J11: =IF(B11="","",H11+I11) -> 5058.55 | K11: =IF(B11="","",IF(C11="DIA", (SUMIFS('📋 Detalle Diario'!$D$5:$D$489, '📋 Detalle Diario'!$B$5:$B$489, B11, '📋 Detalle Diario'!$C$5:$C$489, C11) * '⚙️ Supuestos'!$C$24) + '⚙️ Supuestos'!$C$23, (SUMIFS('📋 Detalle Diario'!$D$5:$D$489, '📋 Detalle Diario'!$B$5:$B$489, B11, '📋 Detalle Diario'!$C$5:$C$489, C11) * '⚙️ Supuestos'!$C$24) + '⚙️ Supuestos'!$C$33)) -> 5044.5503 | L11: =IF(B11="","",J11-K11) -> 13.999667 | M11: =IF(B11="","",IF(J11=0, 0, L11/J11)) -> 0.0027675256 | N11: =IF(B11="","",IF(D11=0, 0, K11/D11)) -> 8.3519045 | O11: =IF(B11="","",IF(ISNUMBER(B11),YEAR(B11)&"-"&IF(MONTH(B11)<10,"0","")&MONTH(B11),LEFT(B11,7))) -> 2026-05 | P11: =IF(B11="","",K11+(G11*0.09)) -> 5143.1003 | Q11: =IF(B11="","",J11-P11+(SUMIFS('📋 Detalle Diario'!$E$5:$E$489, '📋 Detalle Diario'!$B$5:$B$489, B11, '📋 Detalle Diario'!$C$5:$C$489, C11)*135)+(SUMIFS('📋 Detalle Diario'!$I$5:$I$489, '📋 Detalle Diario'!$B$5:$B$489, B11, '📋 Detalle Diario'!$C$5:$C$489, C11)*200)) -> -84.550333 | R11: =IF(B11="","",IF(J11=0, 0, Q11/J11)) -> -0.016714342
B12: 2026-05-05 | C12: NOCHE | D12: =IF(B12="","",SUMIFS('📈 Datos Completos'!$E$7:$E$5000, '📈 Datos Completos'!$B$7:$B$5000, B12, '📈 Datos Completos'!$D$7:$D$5000, C12)) -> 559 | E12: =IF(B12="","",SUMIFS('📈 Datos Completos'!$F$7:$F$5000, '📈 Datos Completos'!$B$7:$B$5000, B12, '📈 Datos Completos'!$D$7:$D$5000, C12)) -> 2016 | F12: =IF(B12="","",SUMIFS('📈 Datos Completos'!$G$7:$G$5000, '📈 Datos Completos'!$B$7:$B$5000, B12, '📈 Datos Completos'!$D$7:$D$5000, C12)) -> 2972 | G12: =IF(B12="","",E12+F12) -> 4988 | H12: =IF(B12="","",SUMIFS('📈 Datos Completos'!$I$7:$I$5000, '📈 Datos Completos'!$B$7:$B$5000, B12, '📈 Datos Completos'!$D$7:$D$5000, C12)) -> 3606.9 | I12: =IF(B12="","",IF(C12="DIA", G12*1.01, G12*1.35)) -> 6733.8 | J12: =IF(B12="","",H12+I12) -> 10340.7 | K12: =IF(B12="","",IF(C12="DIA", (SUMIFS('📋 Detalle Diario'!$D$5:$D$489, '📋 Detalle Diario'!$B$5:$B$489, B12, '📋 Detalle Diario'!$C$5:$C$489, C12) * '⚙️ Supuestos'!$C$24) + '⚙️ Supuestos'!$C$23, (SUMIFS('📋 Detalle Diario'!$D$5:$D$489, '📋 Detalle Diario'!$B$5:$B$489, B12, '📋 Detalle Diario'!$C$5:$C$489, C12) * '⚙️ Supuestos'!$C$24) + '⚙️ Supuestos'!$C$33)) -> 4935.217 | L12: =IF(B12="","",J12-K12) -> 5405.483 | M12: =IF(B12="","",IF(J12=0, 0, L12/J12)) -> 0.5227386 | N12: =IF(B12="","",IF(D12=0, 0, K12/D12)) -> 8.828653 | O12: =IF(B12="","",IF(ISNUMBER(B12),YEAR(B12)&"-"&IF(MONTH(B12)<10,"0","")&MONTH(B12),LEFT(B12,7))) -> 2026-05 | P12: =IF(B12="","",K12+(G12*0.09)) -> 5384.137 | Q12: =IF(B12="","",J12-P12+(SUMIFS('📋 Detalle Diario'!$E$5:$E$489, '📋 Detalle Diario'!$B$5:$B$489, B12, '📋 Detalle Diario'!$C$5:$C$489, C12)*135)+(SUMIFS('📋 Detalle Diario'!$I$5:$I$489, '📋 Detalle Diario'!$B$5:$B$489, B12, '📋 Detalle Diario'!$C$5:$C$489, C12)*200)) -> 4956.563 | R12: =IF(B12="","",IF(J12=0, 0, Q12/J12)) -> 0.47932567
B13: 2026-05-06 | C13: DIA | D13: =IF(B13="","",SUMIFS('📈 Datos Completos'!$E$7:$E$5000, '📈 Datos Completos'!$B$7:$B$5000, B13, '📈 Datos Completos'!$D$7:$D$5000, C13)) -> 561 | E13: =IF(B13="","",SUMIFS('📈 Datos Completos'!$F$7:$F$5000, '📈 Datos Completos'!$B$7:$B$5000, B13, '📈 Datos Completos'!$D$7:$D$5000, C13)) -> 348 | F13: =IF(B13="","",SUMIFS('📈 Datos Completos'!$G$7:$G$5000, '📈 Datos Completos'!$B$7:$B$5000, B13, '📈 Datos Completos'!$D$7:$D$5000, C13)) -> 1006 | G13: =IF(B13="","",E13+F13) -> 1354 | H13: =IF(B13="","",SUMIFS('📈 Datos Completos'!$I$7:$I$5000, '📈 Datos Completos'!$B$7:$B$5000, B13, '📈 Datos Completos'!$D$7:$D$5000, C13)) -> 8317.16 | I13: =IF(B13="","",IF(C13="DIA", G13*1.01, G13*1.35)) -> 1367.54 | J13: =IF(B13="","",H13+I13) -> 9684.7 | K13: =IF(B13="","",IF(C13="DIA", (SUMIFS('📋 Detalle Diario'!$D$5:$D$489, '📋 Detalle Diario'!$B$5:$B$489, B13, '📋 Detalle Diario'!$C$5:$C$489, C13) * '⚙️ Supuestos'!$C$24) + '⚙️ Supuestos'!$C$23, (SUMIFS('📋 Detalle Diario'!$D$5:$D$489, '📋 Detalle Diario'!$B$5:$B$489, B13, '📋 Detalle Diario'!$C$5:$C$489, C13) * '⚙️ Supuestos'!$C$24) + '⚙️ Supuestos'!$C$33)) -> 5044.5503 | L13: =IF(B13="","",J13-K13) -> 4640.1497 | M13: =IF(B13="","",IF(J13=0, 0, L13/J13)) -> 0.47912167 | N13: =IF(B13="","",IF(D13=0, 0, K13/D13)) -> 8.9920683 | O13: =IF(B13="","",IF(ISNUMBER(B13),YEAR(B13)&"-"&IF(MONTH(B13)<10,"0","")&MONTH(B13),LEFT(B13,7))) -> 2026-05 | P13: =IF(B13="","",K13+(G13*0.09)) -> 5166.4103 | Q13: =IF(B13="","",J13-P13+(SUMIFS('📋 Detalle Diario'!$E$5:$E$489, '📋 Detalle Diario'!$B$5:$B$489, B13, '📋 Detalle Diario'!$C$5:$C$489, C13)*135)+(SUMIFS('📋 Detalle Diario'!$I$5:$I$489, '📋 Detalle Diario'!$B$5:$B$489, B13, '📋 Detalle Diario'!$C$5:$C$489, C13)*200)) -> 4518.2897 | R13: =IF(B13="","",IF(J13=0, 0, Q13/J13)) -> 0.46653894
B14: 2026-05-06 | C14: NOCHE | D14: =IF(B14="","",SUMIFS('📈 Datos Completos'!$E$7:$E$5000, '📈 Datos Completos'!$B$7:$B$5000, B14, '📈 Datos Completos'!$D$7:$D$5000, C14)) -> 93 | E14: =IF(B14="","",SUMIFS('📈 Datos Completos'!$F$7:$F$5000, '📈 Datos Completos'!$B$7:$B$5000, B14, '📈 Datos Completos'!$D$7:$D$5000, C14)) -> 0 | F14: =IF(B14="","",SUMIFS('📈 Datos Completos'!$G$7:$G$5000, '📈 Datos Completos'!$B$7:$B$5000, B14, '📈 Datos Completos'!$D$7:$D$5000, C14)) -> 60 | G14: =IF(B14="","",E14+F14) -> 60 | H14: =IF(B14="","",SUMIFS('📈 Datos Completos'!$I$7:$I$5000, '📈 Datos Completos'!$B$7:$B$5000, B14, '📈 Datos Completos'!$D$7:$D$5000, C14)) -> 2327.4 | I14: =IF(B14="","",IF(C14="DIA", G14*1.01, G14*1.35)) -> 81 | J14: =IF(B14="","",H14+I14) -> 2408.4 | K14: =IF(B14="","",IF(C14="DIA", (SUMIFS('📋 Detalle Diario'!$D$5:$D$489, '📋 Detalle Diario'!$B$5:$B$489, B14, '📋 Detalle Diario'!$C$5:$C$489, C14) * '⚙️ Supuestos'!$C$24) + '⚙️ Supuestos'!$C$23, (SUMIFS('📋 Detalle Diario'!$D$5:$D$489, '📋 Detalle Diario'!$B$5:$B$489, B14, '📋 Detalle Diario'!$C$5:$C$489, C14) * '⚙️ Supuestos'!$C$24) + '⚙️ Supuestos'!$C$33)) -> 4935.217 | L14: =IF(B14="","",J14-K14) -> -2526.817 | M14: =IF(B14="","",IF(J14=0, 0, L14/J14)) -> -1.0491683 | N14: =IF(B14="","",IF(D14=0, 0, K14/D14)) -> 53.066849 | O14: =IF(B14="","",IF(ISNUMBER(B14),YEAR(B14)&"-"&IF(MONTH(B14)<10,"0","")&MONTH(B14),LEFT(B14,7))) -> 2026-05 | P14: =IF(B14="","",K14+(G14*0.09)) -> 4940.617 | Q14: =IF(B14="","",J14-P14+(SUMIFS('📋 Detalle Diario'!$E$5:$E$489, '📋 Detalle Diario'!$B$5:$B$489, B14, '📋 Detalle Diario'!$C$5:$C$489, C14)*135)+(SUMIFS('📋 Detalle Diario'!$I$5:$I$489, '📋 Detalle Diario'!$B$5:$B$489, B14, '📋 Detalle Diario'!$C$5:$C$489, C14)*200)) -> -2532.217 | R14: =IF(B14="","",IF(J14=0, 0, Q14/J14)) -> -1.0514105
B15: 2026-05-07 | C15: DIA | D15: =IF(B15="","",SUMIFS('📈 Datos Completos'!$E$7:$E$5000, '📈 Datos Completos'!$B$7:$B$5000, B15, '📈 Datos Completos'!$D$7:$D$5000, C15)) -> 528.5 | E15: =IF(B15="","",SUMIFS('📈 Datos Completos'!$F$7:$F$5000, '📈 Datos Completos'!$B$7:$B$5000, B15, '📈 Datos Completos'!$D$7:$D$5000, C15)) -> 135 | F15: =IF(B15="","",SUMIFS('📈 Datos Completos'!$G$7:$G$5000, '📈 Datos Completos'!$B$7:$B$5000, B15, '📈 Datos Completos'!$D$7:$D$5000, C15)) -> 270 | G15: =IF(B15="","",E15+F15) -> 405 | H15: =IF(B15="","",SUMIFS('📈 Datos Completos'!$I$7:$I$5000, '📈 Datos Completos'!$B$7:$B$5000, B15, '📈 Datos Completos'!$D$7:$D$5000, C15)) -> 18317.7 | I15: =IF(B15="","",IF(C15="DIA", G15*1.01, G15*1.35)) -> 409.05 | J15: =IF(B15="","",H15+I15) -> 18726.75 | K15: =IF(B15="","",IF(C15="DIA", (SUMIFS('📋 Detalle Diario'!$D$5:$D$489, '📋 Detalle Diario'!$B$5:$B$489, B15, '📋 Detalle Diario'!$C$5:$C$489, C15) * '⚙️ Supuestos'!$C$24) + '⚙️ Supuestos'!$C$23, (SUMIFS('📋 Detalle Diario'!$D$5:$D$489, '📋 Detalle Diario'!$B$5:$B$489, B15, '📋 Detalle Diario'!$C$5:$C$489, C15) * '⚙️ Supuestos'!$C$24) + '⚙️ Supuestos'!$C$33)) -> 5044.5503 | L15: =IF(B15="","",J15-K15) -> 13682.2 | M15: =IF(B15="","",IF(J15=0, 0, L15/J15)) -> 0.73062329 | N15: =IF(B15="","",IF(D15=0, 0, K15/D15)) -> 9.5450337 | O15: =IF(B15="","",IF(ISNUMBER(B15),YEAR(B15)&"-"&IF(MONTH(B15)<10,"0","")&MONTH(B15),LEFT(B15,7))) -> 2026-05 | P15: =IF(B15="","",K15+(G15*0.09)) -> 5081.0003 | Q15: =IF(B15="","",J15-P15+(SUMIFS('📋 Detalle Diario'!$E$5:$E$489, '📋 Detalle Diario'!$B$5:$B$489, B15, '📋 Detalle Diario'!$C$5:$C$489, C15)*135)+(SUMIFS('📋 Detalle Diario'!$I$5:$I$489, '📋 Detalle Diario'!$B$5:$B$489, B15, '📋 Detalle Diario'!$C$5:$C$489, C15)*200)) -> 13645.75 | R15: =IF(B15="","",IF(J15=0, 0, Q15/J15)) -> 0.72867687
B16: 2026-05-07 | C16: NOCHE | D16: =IF(B16="","",SUMIFS('📈 Datos Completos'!$E$7:$E$5000, '📈 Datos Completos'!$B$7:$B$5000, B16, '📈 Datos Completos'!$D$7:$D$5000, C16)) -> 254 | E16: =IF(B16="","",SUMIFS('📈 Datos Completos'!$F$7:$F$5000, '📈 Datos Completos'!$B$7:$B$5000, B16, '📈 Datos Completos'!$D$7:$D$5000, C16)) -> 0 | F16: =IF(B16="","",SUMIFS('📈 Datos Completos'!$G$7:$G$5000, '📈 Datos Completos'!$B$7:$B$5000, B16, '📈 Datos Completos'!$D$7:$D$5000, C16)) -> 1220 | G16: =IF(B16="","",E16+F16) -> 1220 | H16: =IF(B16="","",SUMIFS('📈 Datos Completos'!$I$7:$I$5000, '📈 Datos Completos'!$B$7:$B$5000, B16, '📈 Datos Completos'!$D$7:$D$5000, C16)) -> 2820 | I16: =IF(B16="","",IF(C16="DIA", G16*1.01, G16*1.35)) -> 1647 | J16: =IF(B16="","",H16+I16) -> 4467 | K16: =IF(B16="","",IF(C16="DIA", (SUMIFS('📋 Detalle Diario'!$D$5:$D$489, '📋 Detalle Diario'!$B$5:$B$489, B16, '📋 Detalle Diario'!$C$5:$C$489, C16) * '⚙️ Supuestos'!$C$24) + '⚙️ Supuestos'!$C$23, (SUMIFS('📋 Detalle Diario'!$D$5:$D$489, '📋 Detalle Diario'!$B$5:$B$489, B16, '📋 Detalle Diario'!$C$5:$C$489, C16) * '⚙️ Supuestos'!$C$24) + '⚙️ Supuestos'!$C$33)) -> 4935.217 | L16: =IF(B16="","",J16-K16) -> -468.217 | M16: =IF(B16="","",IF(J16=0, 0, L16/J16)) -> -0.10481688 | N16: =IF(B16="","",IF(D16=0, 0, K16/D16)) -> 19.429988 | O16: =IF(B16="","",IF(ISNUMBER(B16),YEAR(B16)&"-"&IF(MONTH(B16)<10,"0","")&MONTH(B16),LEFT(B16,7))) -> 2026-05 | P16: =IF(B16="","",K16+(G16*0.09)) -> 5045.017 | Q16: =IF(B16="","",J16-P16+(SUMIFS('📋 Detalle Diario'!$E$5:$E$489, '📋 Detalle Diario'!$B$5:$B$489, B16, '📋 Detalle Diario'!$C$5:$C$489, C16)*135)+(SUMIFS('📋 Detalle Diario'!$I$5:$I$489, '📋 Detalle Diario'!$B$5:$B$489, B16, '📋 Detalle Diario'!$C$5:$C$489, C16)*200)) -> -578.017 | R16: =IF(B16="","",IF(J16=0, 0, Q16/J16)) -> -0.12939713
